Workbook
Name RankingFundamentalWeight: Settings!$C$65
Name RankingSentimentWeight: Settings!$C$66

Sheet README
A1: KADIOKO DSE SHEET
A2: Created by GODFREY MARIKI · NECUVA GROUP
A3: Kadioko DSE Sheet · workbook name, authorship and this README are locked. All analytical sheets are protected; the data-entry and Settings cells remain open for everyday use.
A4: START HERE ▸ open the 'How To Read' sheet (second tab). It explains, in five steps, how to check the data, how the Market Pressure Score is built from its six components, exactly what each Signal does and does not mean, and the three confirmations to run before you rely on any score.
A5: A daily market-analysis workbook for the Dar es Salaam Stock Exchange (DSE). It stores every market observation once, in a single master table, and derives every summary, score, report and chart from that one table. Built to run in Google Sheets, and kept compatible with Microsoft Excel 365.
A6: 1. WHAT THIS WORKBOOK IS
A7: Kadioko DSE Sheet turns raw end-of-day DSE data (price, turnover, volume, deals, outstanding bid and offer quantities, market capitalisation) into daily summaries, order-book pressure scores, momentum rankings, liquidity measures, weekly and monthly reports, and an investor dashboard.
A8: There is exactly ONE source of truth: the 'Daily Data' sheet. One row = one security on one trading date. Nothing is ever copied by hand between sheets. If a number looks wrong anywhere, it is fixed in Daily Data (or in Settings) and the whole workbook updates.
A9: 2. HOW TO ENTER OR IMPORT DATA
A10: Manual entry — type or paste raw values into Daily Data columns A to Q (Date … Validation Status). Columns R to AV are formulas and fill themselves; never type over them.
A11: CSV import — use the layout on the 'CSV Template' sheet. Column order must match exactly. Paste new rows underneath the last populated row, starting in column A.
A12: Google Apps Script — copy the code from the 'Apps Script' sheet into your Sheet's script editor. manualCsvImport() loads a CSV from Drive; importFromOfficialFeed() is the adapter for a licensed DSE data feed. Imports are idempotent: the same Symbol + Date is never inserted twice.
... A66: The Ranking sheet is colour-coded: green = strong, amber = average, red = weak, with a colour key at rows 79-81.

Sheet How To Read
A1: HOW TO READ KADIOKO DSE SHEET
A2: Created by GODFREY MARIKI · NECUVA GROUP
A3: A five-minute routine for reading the workbook correctly, and a full explanation of the Market Pressure Score and the Signal wording. Read this before you act on any number in this file.
A5: STEP 1 — CHECK THE DATA BEFORE YOU READ ANY SCORE
A6: Every score is only as good as the row it was built from. Open the Data Quality sheet and look at the three counters at the top. If ERRORS is anything other than zero, fix those rows in Daily Data first — an error means the row is structurally wrong (duplicate date, negative price, close outside the day's high/low) and the analytics built on it cannot be trusted.
A7: ="Live status: ERRORS = "&'Data Quality'!$E$2&" WARNINGS = "&'Data Quality'!$G$2&" ROWS PASSED = "&'Data Quality'!$I$2&" → "&IF('Data Quality'!$E$2>0,"DO NOT rely on the analytics until the errors are cleared.",IF('Data Quality'!$G$2>0,"Usable, but review the warnings.","Data is clean.")) -> Live status: ERRORS = 2 WARNINGS = 14 ROWS PASSED = 132 → DO NOT rely on the analytics until the errors are cleared.
A9: STEP 2 — READ THE DAY BEFORE YOU READ A COUNTER
A10: Set the date in Settings!C13, then open Daily Summary. Look at total turnover, the number of counters that actually traded, and the gainers/losers split. This is your context. A pressure score of 85 on a day when only three counters traded means far less than the same score on a busy day.
A11: Then open Market Sentiment. It lists every security in the Symbols master for that one date, side by side.
A13: STEP 3 — THE MARKET PRESSURE SCORE (0–100)
A14: The Market Pressure Score answers exactly one question: at the close, was the resting order book leaning toward the buy side or the sell side, and was that lean confirmed by price and volume? It is a measure of PRESSURE. It is not a forecast, and it is not advice.
A15: 0 = extreme sell-side pressure · 50 = balanced · 100 = extreme buy-side pressure
A17: Score band | B17: Signal shown | C17: What it means | D17: What it does NOT mean
A18: 0 – 19 | B18: Extreme Sell Pressure | C18: The offer side of the book overwhelms the bid side, and price/volume confirm the downward lean. | D18: It does not mean 'sell now'. Heavy offers can be one large seller working an order, and can clear in a day.
A19: 20 – 39 | B19: Sell Pressure | C19: More shares queued to sell than to buy; the lean is real but not extreme. | D19: It does not mean the price will fall.
A20: 40 – 60 | B20: Neutral | C20: Bid and offer are roughly balanced, or the signals disagree with each other. | D20: It does not mean 'nothing is happening' — check volume and momentum separately.
A21: 61 – 80 | B21: Buy Pressure | C21: More shares queued to buy than to sell; demand is leaning positive. | D21: It does not mean 'buy'.
A22: 81 – 100 | B22: Extreme Buy Pressure | C22: The bid side overwhelms the offer side, confirmed by price and volume. | D22: It does NOT mean 'strong buy'. A thin offer side can simply mean nobody is willing to sell at that price yet.
A24: HOW THE SIGNAL IS PRODUCED — THE FULL CHAIN
A25: Six component scores are calculated separately, each on its own 0–100 scale, in Daily Data columns AO to AT. They are then blended using the weights in Settings!C32:C37 to give the Market Pressure Score in column AH. The Signal in column AJ is nothing more than the score compared with the four thresholds in Settings!C46:C49. Nothing is hidden: you can click any component and read its formula.
A26: Component (column) | B26: Default weight | C26: The question it answers | D26: Where to see it
A27: P1 Order-book position (AO) | B27: 0.3 | C27: How far from balance is the bid/offer ratio right now? | D27: Daily Data column S (B/O Ratio)
A28: P2 B/O momentum (AP) | B28: 0.2 | C28: Is that imbalance building or fading versus its own recent average? | D28: Daily Data column AA (B/O Momentum %)
A29: P3 Price momentum (AQ) | B29: 0.15 | C29: Did the price actually move in the same direction? | D29: Daily Data column H (Change %)
A30: P4 Volume confirmation (AR) | B30: 0.15 | C30: Was the move backed by heavier-than-normal trading? | D30: Daily Data column AC (Volume Ratio)
A31: P5 Book depth vs market cap (AS) | B31: 0.1 | C31: Is the imbalance big relative to the size of the company? | D31: Daily Data columns V and W
A32: P6 Liquidity adjustment (AT) | B32: 0.1 | C32: Is this counter liquid enough for the reading to mean anything? Illiquid names are pulled back toward 50. | D32: Daily Data column AG (Liquidity Score)
A34: STEP 4 — WORKED EXAMPLE, CALCULATED LIVE
A35: ="This example follows the security selected in Settings!C14 ("&Settings!$C$14&") on "&TEXT(Settings!$C$13,"yyyy-mm-dd")&". Change either setting and the numbers below recalculate." -> This example follows the security selected in Settings!C14 (CRDB) on 2026-08-14. Change either setting and the numbers below recalculate.
A36: Component | B36: Score (0–100) | C36: Weight | D36: Weighted contribution
A37: P1 Order-book position | B37: =IFERROR(INDEX('Daily Data'!$AO$4:$AO$503,MATCH(Settings!$C$14&"|"&TEXT(Settings!$C$13,"yyyy-mm-dd"),'Daily Data'!$AU$4:$AU$503,0)),"no data") -> 100 | C37: =Settings!$C$32 -> 0.3 | D37: =IF(NOT(ISNUMBER($B37)),"",$B37*$C37) -> 30
A38: P2 B/O momentum | B38: =IFERROR(INDEX('Daily Data'!$AP$4:$AP$503,MATCH(Settings!$C$14&"|"&TEXT(Settings!$C$13,"yyyy-mm-dd"),'Daily Data'!$AU$4:$AU$503,0)),"no data") -> 50 | C38: =Settings!$C$33 -> 0.2 | D38: =IF(NOT(ISNUMBER($B38)),"",$B38*$C38) -> 10
A39: P3 Price momentum | B39: =IFERROR(INDEX('Daily Data'!$AQ$4:$AQ$503,MATCH(Settings!$C$14&"|"&TEXT(Settings!$C$13,"yyyy-mm-dd"),'Daily Data'!$AU$4:$AU$503,0)),"no data") -> 50 | C39: =Settings!$C$34 -> 0.15 | D39: =IF(NOT(ISNUMBER($B39)),"",$B39*$C39) -> 7.5
A40: P4 Volume confirmation | B40: =IFERROR(INDEX('Daily Data'!$AR$4:$AR$503,MATCH(Settings!$C$14&"|"&TEXT(Settings!$C$13,"yyyy-mm-dd"),'Daily Data'!$AU$4:$AU$503,0)),"no data") -> 50 | C40: =Settings!$C$35 -> 0.15 | D40: =IF(NOT(ISNUMBER($B40)),"",$B40*$C40) -> 7.5
A41: P5 Book depth vs market cap | B41: =IFERROR(INDEX('Daily Data'!$AS$4:$AS$503,MATCH(Settings!$C$14&"|"&TEXT(Settings!$C$13,"yyyy-mm-dd"),'Daily Data'!$AU$4:$AU$503,0)),"no data") -> 60.084588 | C41: =Settings!$C$36 -> 0.1 | D41: =IF(NOT(ISNUMBER($B41)),"",$B41*$C41) -> 6.0084588
A42: P6 Liquidity adjustment | B42: =IFERROR(INDEX('Daily Data'!$AT$4:$AT$503,MATCH(Settings!$C$14&"|"&TEXT(Settings!$C$13,"yyyy-mm-dd"),'Daily Data'!$AU$4:$AU$503,0)),"no data") -> 96.35 | C42: =Settings!$C$37 -> 0.1 | D42: =IF(NOT(ISNUMBER($B42)),"",$B42*$C42) -> 9.635
A43: MARKET PRESSURE SCORE = sum of contributions ÷ sum of weights | C43: =SUM($C$37:$C$42) -> 1 | D43: =IFERROR(ROUND(SUM($D$37:$D$42)/SUM($C$37:$C$42),1),"no data") -> 70.6
A44: SIGNAL SHOWN (from Settings!C46:C49) | D44: =IFERROR(INDEX('Daily Data'!$AJ$4:$AJ$503,MATCH(Settings!$C$14&"|"&TEXT(Settings!$C$13,"yyyy-mm-dd"),'Daily Data'!$AU$4:$AU$503,0)),"no data") -> Buy Pressure
A45: DATA CONFIDENCE FOR THIS ROW (trust the score only above Settings!C57) | D45: =IFERROR(INDEX('Daily Data'!$AI$4:$AI$503,MATCH(Settings!$C$14&"|"&TEXT(Settings!$C$13,"yyyy-mm-dd"),'Daily Data'!$AU$4:$AU$503,0)),"no data") -> 75
A47: STEP 5 — THREE CONFIRMATIONS BEFORE THE SCORE MEANS ANYTHING
A48: Check | B48: Where to look | C48: Only treat the score as meaningful if…
A49: Liquidity | B49: Daily Data AG · Momentum sheet | C49: Liquidity Score is above Settings!C30. Below that the Momentum sheet marks the counter Illiquid and refuses to rank it.
A50: Enough history | B50: Daily Data Z and AB | C50: The 5-day B/O average and 20-day average volume are populated. If they are blank, the momentum component falls back to a neutral 50.
A51: Data confidence | B51: Daily Data AI | C51: Confidence is at or above Settings!C57. Below that, Market Sentiment appends '(low confidence)' to the signal.
A52: Momentum direction | B52: Momentum sheet | C52: Pressure and momentum agree. High pressure with 'Strong Deterioration' is a contradiction worth investigating, not a signal.
A53: Order-book size | B53: Daily Data V and W | C53: The book is a meaningful share of market cap. A 10x ratio built on two tiny orders is noise.
A55: THE FIVE MISTAKES THIS WORKBOOK IS DESIGNED TO PREVENT
A56: 1. Reading a high pressure score as 'buy'. It measures resting demand pressure at one moment on one day. Nothing more.
A57: 2. Calling the bid quantity 'buyers' and the offer quantity 'sellers'. These are OUTSTANDING ORDER QUANTITIES in shares. One buyer can place a huge bid; a thousand can place tiny ones.
A58: 3. Ranking on ratios without a liquidity filter. A counter that traded twice can show a spectacular B/O ratio. The Momentum sheet excludes it deliberately.
A59: 4. Trusting a score built on missing inputs. That is what the Data Confidence Score is for — check it before quoting a number.
A60: 5. Comparing raw prices between counters. Use the rebased index on the Compare sheet, where each series starts at 100.
A62: Kadioko DSE Sheet is a decision-support tool created by Godfrey Mariki, Necuva Group. The scores, signals and rankings are descriptive summaries of historical order-book and trading data. They are not investment advice, not a recommendation to buy or sell any security, and not a guarantee of future performance. Verify against official DSE publications before acting.
A64: STEP 6 — THE RANKING SHEET: QUALITY FIRST, DEMAND SECOND
A65: Market Pressure answers 'who is being bought today'. The Ranking sheet answers a different and more important question: 'which company is worth owning'. It weights company quality at 70% and market demand at 30%, so a counter cannot reach the top of the table on a hot order book alone.
A66: Read the Ranking sheet in this order:
A67: 1. Check the status bar under the model context. It tells you whether the weights are valid, whether the market data date is an exact match or a fallback, and whether any fundamental scores exist at all.
A68: 2. Read Daraja (grade) for overall standing — BORA SANA down to DHAIFU SANA, green through red.
... A74: A high Overall Score is still not investment advice. It says the company scores well on the financial metrics you entered and that the order book was supportive on one trading day. It says nothing about valuation, price, or what happens next.

Sheet Settings
A1: 0.03
A2: Settings — all model assumptions are configurable here. Amber cells are user inputs; grey cells are calculated.
B3: Setting | C3: Value | D3: Notes / Description
B4: IDENTITY & OPERATIONS
B5: Workbook Name (locked) | C5: Kadioko DSE Sheet | D5: Locked — created by Godfrey Mariki, Necuva Group
B6: Author / Owner (locked) | C6: Godfrey Mariki — Necuva Group | D6: Locked — attribution, do not edit
B7: Default Language | C7: English | D7: English or Kiswahili (report narrative)
B8: Data Source Mode | C8: Official Feed | D8: Manual CSV | Official Feed | Configured Endpoint
B9: Import Endpoint URL (optional) | D9: Used only by importFromConfiguredEndpoint()
B10: Last Import Date | C10: 46265 | D10: Written by Apps Script
B11: Last Successful Refresh | D11: Written by Apps Script
B12: SELECTIONS
B13: Selected Analysis Date | C13: 46248 | D13: Drives Daily Summary & Market Sentiment
B14: Selected Symbol | C14: CRDB | D14: Drives Stock Analyzer
B15: Comparison Symbol A | C15: CRDB | D15: Compare sheet
B16: Comparison Symbol B | C16: NMB | D16: Compare sheet
B17: Report Week Number (ISO) | C17: 33 | D17: Weekly Report
B18: Report Year | C18: 2026 | D18: Weekly & Monthly Report
B19: Report Month (1-12) | C19: 8 | D19: Monthly Report
B20: ANALYSIS WINDOWS (trading observations)
B21: Rolling B/O window | C21: 5 | D21: Default 5 prior observations
B22: Rolling volume window | C22: 20 | D22: Default 20 prior observations
B23: Momentum / price-return window | C23: 5 | D23: Used for 5D return
B24: LIQUIDITY THRESHOLDS & BENCHMARKS
B25: Minimum trading volume threshold | C25: 1000 | D25: Below this a counter is flagged Illiquid
B26: Minimum turnover threshold (TZS) | C26: 5000000 | D26: Below this a counter is flagged Illiquid
B27: Turnover benchmark = score 100 (TZS) | C27: 1000000000 | D27: Liquidity sub-score scaling
B28: Volume benchmark = score 100 (shares) | C28: 500000 | D28: Liquidity sub-score scaling
B29: Deals benchmark = score 100 | C29: 100 | D29: Liquidity sub-score scaling
B30: Minimum liquidity score to be ranked | C30: 20 | D30: Stops illiquid counters topping rankings
B31: MARKET PRESSURE MODEL WEIGHTS (must total 100%)
B32: W1 - B/O position | C32: 0.3 | D32: Order-book imbalance level
B33: W2 - B/O momentum | C33: 0.2 | D33: Change in imbalance vs rolling average
B34: W3 - Price momentum | C34: 0.15 | D34: Daily change %
B35: W4 - Volume confirmation | C35: 0.15 | D35: Does volume confirm the price move?
B36: W5 - Book depth vs market cap | C36: 0.1 | D36: Absolute size of book vs MCAP
B37: W6 - Liquidity confirmation | C37: 0.1 | D37: Damps book signal for illiquid names
B38: Total weight check | C38: =SUM(C32:C37) -> 1 | D38: Must equal 100%
B39: SCORE CALIBRATION
B40: B/O ratio cap (x) = score 100 | C40: 4 | D40: B/O of 4.0x scores 100; 0.25x scores 0 (log scale)
B41: B/O momentum sensitivity (pts per 1%) | C41: 0.5 | D41: 50 + mom% x sensitivity
B42: Price momentum sensitivity (pts per 1%) | C42: 10 | D42: A +5% move reaches score 100
B43: Volume ratio upside cap | C43: 1 | D43: VolRatio of 2.0x = full confirmation
B44: Book depth benchmark (% of MCAP) | C44: 0.0005 | D44: Net bid-offer depth for a full-strength signal
B45: SIGNAL THRESHOLDS (Market Pressure Score)
B46: Extreme Sell Pressure below | C46: 20
B47: Sell Pressure below | C47: 40
B48: Neutral upper bound | C48: 60
B49: Buy Pressure upper bound | C49: 80 | D49: Above this = Extreme Buy Pressure
B50: MOMENTUM STATUS THRESHOLDS (B/O momentum %)
B51: Strong Acceleration above | C51: 0.25
B52: Improving above | C52: 0.05
B53: Weakening below | C53: -0.05
B54: Strong Deterioration below | C54: -0.25
B55: DATA QUALITY
B56: Max expected daily change | C56: 0.2 | D56: Larger moves raise a WARNING
B57: Minimum data confidence to trust score | C57: 60 | D57: Below this scores are flagged Low Confidence
B58: MARKET TREND THRESHOLDS (average daily change across the period)
B59: Bullish above (avg daily change) | C59: 0.01 | D59: Above this the period is labelled Bullish
B60: Mildly Bullish above (avg daily change) | C60: 0.002 | D60: Mirror negatives are used for Bearish / Mildly Bearish
B61: Model / Formula Version | C61: 1 | D61: Increment when scoring logic changes
B62: Source URL of last data load | C62: https://dse.co.tz/ — Daily Market Reports for 10–14 August 2026 | D62: Official DSE Daily Market Reports, 10–13 August 2026
B64: RANKING MODEL (Ranking sheet)
B65: Fundamental Weight | C65: 0.7 | D65: Named range: RankingFundamentalWeight
B66: Sentiment Weight | C66: 0.3 | D66: Named range: RankingSentimentWeight
B67: Weight Check | C67: =IF(ROUND($C$65+$C$66,6)=1,"OK — weights total 100%","CONFIGURATION ERROR: Ranking weights must total 100%") -> OK — weights total 100% | D67: Ranking is blocked while this shows an error
B68: Ranking As Of Date | C68: 46248 | D68: The trading date the sentiment side of the ranking must match
B69: Use latest trading date on or before | C69: YES | D69: If NO, the ranking is blank when the exact date has no observations
B70: Maximum staleness (calendar days) | C70: 7 | D70: A warning is shown when the fallback date is older than this
B71: Minimum Data Confidence to rank | C71: 60 | D71: Securities below this are not ranking-eligible
B72: Minimum Liquidity to rank | C72: 0 | D72: 0 = do not exclude on liquidity; liquidity is always displayed
B73: Hide incomplete rankings | C73: NO | D73: YES hides securities without a complete score set
B74: Ranking Model Version | C74: RANK-1.0 | D74: Increment when the ranking logic changes
B75: DARAJA / GRADE BANDS (minimum Overall Score)
B76: BORA SANA min | C76: 80
B77: NZURI SANA min | C77: 70
B78: NZURI min | C78: 60
B79: WASTANI min | C79: 50
B80: DHAIFU min | C80: 40 | D80: Below this = DHAIFU SANA
B81: DEMAND YA SOKO BANDS (minimum Sentiment Score)
B82: Demand kubwa sana min | C82: 80
B83: Demand kubwa min | C83: 50
B84: Demand ya wastani min | C84: 30 | D84: Below this = Demand ndogo sana
B85: UAMUZI / INTERPRETATION THRESHOLDS
B86: Strong fundamental min | C86: 70 | D86: Fundamental at or above this = strong company
B87: Supportive sentiment min | C87: 70 | D87: Sentiment at or above this = supportive market
B88: Medium fundamental min | C88: 50 | D88: Below this = weak fundamentals, always Epuka
B89: Adequate demand min | C89: 30 | D89: Sentiment at or above this = adequate demand
B91: FUNDAMENTAL SCORING BENCHMARKS (Fundamental Scorecard)
B92: Revenue growth — 0 pts at | C92: -0.1 | D92: Year-on-year revenue growth
B93: Revenue growth — 100 pts at | C93: 0.25
B94: Profit growth — 0 pts at | C94: -0.2 | D94: Year-on-year profit growth
B95: Profit growth — 100 pts at | C95: 0.4
B96: Net margin — 0 pts at | C96: 0 | D96: Net profit / revenue. Banks: profit / total income
B97: Net margin — 100 pts at | C97: 0.25
B98: Return on equity — 0 pts at | C98: 0
B99: Return on equity — 100 pts at | C99: 0.25
B100: Leverage — 100 pts at (best) | C100: 0 | D100: Debt / equity. Lower is better, so the scale is inverted
B101: Leverage — 0 pts at (worst) | C101: 3
B102: Minimum metrics required to score | C102: 3 | D102: Fewer than this leaves the Fundamental Score blank
...

Sheet Symbols
A1: KADIOKO DSE SHEET — SECURITY MASTER
A2: Add every DSE-listed instrument you track here. All analytics work for ANY symbol in this list (rows 4-43). Shares outstanding are indicative — verify against the official DSE register before relying on market-cap figures.
A3: Symbol | B3: Company / Security Name | C3: Security Type | D3: Sector | E3: Listed | F3: Active | G3: Currency | H3: Shares Outstanding | I3: Notes | J3: Data Source Identifier | K3: Verification Status
A4: AFRIPRISE | B4: Afriprise Investment PLC | C4: Ordinary Share | D4: Investment | F4: Yes | G4: TZS | H4: =IF($A4="","",IFERROR(ROUND(SUMIFS('Daily Data'!$N$4:$N$503,'Daily Data'!$B$4:$B$503,$A4,'Daily Data'!$AK$4:$AK$503,COUNTIF('Daily Data'!$B$4:$B$503,$A4))/SUMIFS('Daily Data'!$E$4:$E$503,'Daily Data'!$B$4:$B$503,$A4,'Daily Data'!$AK$4:$AK$503,COUNTIF('Daily Data'!$B$4:$B$503,$A4)),0),"")) -> 146032000 | I4: Derived: official DSE market capitalisation ÷ closing price (Daily Market Report, 23-Feb-2026). Listing date still to be confirmed against the DSE register. | J4: AFRIPRISE | K4: =IF($A4="","",IF(OR($E4="",NOT(ISNUMBER($E4))),"VERIFY — listing date missing",IF(N($H4)<=0,"VERIFY — shares outstanding missing","Verified"))) -> VERIFY — listing date missing
A5: CRDB | B5: CRDB Bank PLC | C5: Ordinary Share | D5: Banking | F5: Yes | G5: TZS | H5: =IF($A5="","",IFERROR(ROUND(SUMIFS('Daily Data'!$N$4:$N$503,'Daily Data'!$B$4:$B$503,$A5,'Daily Data'!$AK$4:$AK$503,COUNTIF('Daily Data'!$B$4:$B$503,$A5))/SUMIFS('Daily Data'!$E$4:$E$503,'Daily Data'!$B$4:$B$503,$A5,'Daily Data'!$AK$4:$AK$503,COUNTIF('Daily Data'!$B$4:$B$503,$A5)),0),"")) -> 2611837037 | I5: Derived: official DSE market capitalisation ÷ closing price (Daily Market Report, 23-Feb-2026). Listing date still to be confirmed against the DSE register. | J5: CRDB | K5: =IF($A5="","",IF(OR($E5="",NOT(ISNUMBER($E5))),"VERIFY — listing date missing",IF(N($H5)<=0,"VERIFY — shares outstanding missing","Verified"))) -> VERIFY — listing date missing
A6: DCB | B6: DCB Commercial Bank PLC | C6: Ordinary Share | D6: Banking | F6: Yes | G6: TZS | H6: =IF($A6="","",IFERROR(ROUND(SUMIFS('Daily Data'!$N$4:$N$503,'Daily Data'!$B$4:$B$503,$A6,'Daily Data'!$AK$4:$AK$503,COUNTIF('Daily Data'!$B$4:$B$503,$A6))/SUMIFS('Daily Data'!$E$4:$E$503,'Daily Data'!$B$4:$B$503,$A6,'Daily Data'!$AK$4:$AK$503,COUNTIF('Daily Data'!$B$4:$B$503,$A6)),0),"")) -> 191591398 | I6: Derived: official DSE market capitalisation ÷ closing price (Daily Market Report, 23-Feb-2026). Listing date still to be confirmed against the DSE register. | J6: DCB | K6: =IF($A6="","",IF(OR($E6="",NOT(ISNUMBER($E6))),"VERIFY — listing date missing",IF(N($H6)<=0,"VERIFY — shares outstanding missing","Verified"))) -> VERIFY — listing date missing
A7: DSE | B7: Dar es Salaam Stock Exchange PLC | C7: Ordinary Share | D7: Financial Services | F7: Yes | G7: TZS | H7: =IF($A7="","",IFERROR(ROUND(SUMIFS('Daily Data'!$N$4:$N$503,'Daily Data'!$B$4:$B$503,$A7,'Daily Data'!$AK$4:$AK$503,COUNTIF('Daily Data'!$B$4:$B$503,$A7))/SUMIFS('Daily Data'!$E$4:$E$503,'Daily Data'!$B$4:$B$503,$A7,'Daily Data'!$AK$4:$AK$503,COUNTIF('Daily Data'!$B$4:$B$503,$A7)),0),"")) -> 23823440 | I7: Derived: official DSE market capitalisation ÷ closing price (Daily Market Report, 23-Feb-2026). Listing date still to be confirmed against the DSE register. | J7: DSE | K7: =IF($A7="","",IF(OR($E7="",NOT(ISNUMBER($E7))),"VERIFY — listing date missing",IF(N($H7)<=0,"VERIFY — shares outstanding missing","Verified"))) -> VERIFY — listing date missing
A8: EABL | B8: East African Breweries PLC | C8: Ordinary Share (cross-listed) | D8: Consumer Goods | F8: Yes | G8: TZS | H8: =IF($A8="","",IFERROR(ROUND(SUMIFS('Daily Data'!$N$4:$N$503,'Daily Data'!$B$4:$B$503,$A8,'Daily Data'!$AK$4:$AK$503,COUNTIF('Daily Data'!$B$4:$B$503,$A8))/SUMIFS('Daily Data'!$E$4:$E$503,'Daily Data'!$B$4:$B$503,$A8,'Daily Data'!$AK$4:$AK$503,COUNTIF('Daily Data'!$B$4:$B$503,$A8)),0),"")) -> 790774597 | I8: Derived: official DSE market capitalisation ÷ closing price (Daily Market Report, 23-Feb-2026). Listing date still to be confirmed against the DSE register. | J8: EABL | K8: =IF($A8="","",IF(OR($E8="",NOT(ISNUMBER($E8))),"VERIFY — listing date missing",IF(N($H8)<=0,"VERIFY — shares outstanding missing","Verified"))) -> VERIFY — listing date missing
A9: JATU | B9: JATU PLC | C9: Ordinary Share | D9: Agriculture | F9: Yes | G9: TZS | H9: =IF($A9="","",IFERROR(ROUND(SUMIFS('Daily Data'!$N$4:$N$503,'Daily Data'!$B$4:$B$503,$A9,'Daily Data'!$AK$4:$AK$503,COUNTIF('Daily Data'!$B$4:$B$503,$A9))/SUMIFS('Daily Data'!$E$4:$E$503,'Daily Data'!$B$4:$B$503,$A9,'Daily Data'!$AK$4:$AK$503,COUNTIF('Daily Data'!$B$4:$B$503,$A9)),0),"")) -> 19924528 | I9: Derived: official DSE market capitalisation ÷ closing price (Daily Market Report, 23-Feb-2026). Listing date still to be confirmed against the DSE register. | J9: JATU | K9: =IF($A9="","",IF(OR($E9="",NOT(ISNUMBER($E9))),"VERIFY — listing date missing",IF(N($H9)<=0,"VERIFY — shares outstanding missing","Verified"))) -> VERIFY — listing date missing
A10: JHL | B10: Jubilee Holdings Ltd | C10: Ordinary Share (cross-listed) | D10: Insurance | F10: Yes | G10: TZS | H10: =IF($A10="","",IFERROR(ROUND(SUMIFS('Daily Data'!$N$4:$N$503,'Daily Data'!$B$4:$B$503,$A10,'Daily Data'!$AK$4:$AK$503,COUNTIF('Daily Data'!$B$4:$B$503,$A10))/SUMIFS('Daily Data'!$E$4:$E$503,'Daily Data'!$B$4:$B$503,$A10,'Daily Data'!$AK$4:$AK$503,COUNTIF('Daily Data'!$B$4:$B$503,$A10)),0),"")) -> 72472832 | I10: Derived: official DSE market capitalisation ÷ closing price (Daily Market Report, 23-Feb-2026). Listing date still to be confirmed against the DSE register. | J10: JHL | K10: =IF($A10="","",IF(OR($E10="",NOT(ISNUMBER($E10))),"VERIFY — listing date missing",IF(N($H10)<=0,"VERIFY — shares outstanding missing","Verified"))) -> VERIFY — listing date missing
A11: KA | B11: Kenya Airways PLC | C11: Ordinary Share (cross-listed) | D11: Transport | F11: Yes | G11: TZS | H11: =IF($A11="","",IFERROR(ROUND(SUMIFS('Daily Data'!$N$4:$N$503,'Daily Data'!$B$4:$B$503,$A11,'Daily Data'!$AK$4:$AK$503,COUNTIF('Daily Data'!$B$4:$B$503,$A11))/SUMIFS('Daily Data'!$E$4:$E$503,'Daily Data'!$B$4:$B$503,$A11,'Daily Data'!$AK$4:$AK$503,COUNTIF('Daily Data'!$B$4:$B$503,$A11)),0),"")) -> 5681454545 | I11: Derived: official DSE market capitalisation ÷ closing price (Daily Market Report, 23-Feb-2026). Listing date still to be confirmed against the DSE register. | J11: KA | K11: =IF($A11="","",IF(OR($E11="",NOT(ISNUMBER($E11))),"VERIFY — listing date missing",IF(N($H11)<=0,"VERIFY — shares outstanding missing","Verified"))) -> VERIFY — listing date missing
A12: KCB | B12: KCB Group PLC | C12: Ordinary Share (cross-listed) | D12: Banking | F12: Yes | G12: TZS | H12: =IF($A12="","",IFERROR(ROUND(SUMIFS('Daily Data'!$N$4:$N$503,'Daily Data'!$B$4:$B$503,$A12,'Daily Data'!$AK$4:$AK$503,COUNTIF('Daily Data'!$B$4:$B$503,$A12))/SUMIFS('Daily Data'!$E$4:$E$503,'Daily Data'!$B$4:$B$503,$A12,'Daily Data'!$AK$4:$AK$503,COUNTIF('Daily Data'!$B$4:$B$503,$A12)),0),"")) -> 2970338462 | I12: Derived: official DSE market capitalisation ÷ closing price (Daily Market Report, 23-Feb-2026). Listing date still to be confirmed against the DSE register. | J12: KCB | K12: =IF($A12="","",IF(OR($E12="",NOT(ISNUMBER($E12))),"VERIFY — listing date missing",IF(N($H12)<=0,"VERIFY — shares outstanding missing","Verified"))) -> VERIFY — listing date missing
A13: MBP | B13: Maendeleo Bank PLC | C13: Ordinary Share | D13: Banking | F13: Yes | G13: TZS | H13: =IF($A13="","",IFERROR(ROUND(SUMIFS('Daily Data'!$N$4:$N$503,'Daily Data'!$B$4:$B$503,$A13,'Daily Data'!$AK$4:$AK$503,COUNTIF('Daily Data'!$B$4:$B$503,$A13))/SUMIFS('Daily Data'!$E$4:$E$503,'Daily Data'!$B$4:$B$503,$A13,'Daily Data'!$AK$4:$AK$503,COUNTIF('Daily Data'!$B$4:$B$503,$A13)),0),"")) -> 29988095 | I13: Derived: official DSE market capitalisation ÷ closing price (Daily Market Report, 23-Feb-2026). Listing date still to be confirmed against the DSE register. | J13: MBP | K13: =IF($A13="","",IF(OR($E13="",NOT(ISNUMBER($E13))),"VERIFY — listing date missing",IF(N($H13)<=0,"VERIFY — shares outstanding missing","Verified"))) -> VERIFY — listing date missing
A14: MCB | B14: MCB — name to confirm with DSE | C14: Ordinary Share | D14: Banking | F14: Yes | G14: TZS | H14: =IF($A14="","",IFERROR(ROUND(SUMIFS('Daily Data'!$N$4:$N$503,'Daily Data'!$B$4:$B$503,$A14,'Daily Data'!$AK$4:$AK$503,COUNTIF('Daily Data'!$B$4:$B$503,$A14))/SUMIFS('Daily Data'!$E$4:$E$503,'Daily Data'!$B$4:$B$503,$A14,'Daily Data'!$AK$4:$AK$503,COUNTIF('Daily Data'!$B$4:$B$503,$A14)),0),"")) -> 247308642 | I14: Derived: official DSE market capitalisation ÷ closing price (Daily Market Report, 23-Feb-2026). Listing date still to be confirmed against the DSE register. | J14: MCB | K14: =IF($A14="","",IF(OR($E14="",NOT(ISNUMBER($E14))),"VERIFY — listing date missing",IF(N($H14)<=0,"VERIFY — shares outstanding missing","Verified"))) -> VERIFY — listing date missing
A15: MKCB | B15: Mkombozi Commercial Bank PLC | C15: Ordinary Share | D15: Banking | F15: Yes | G15: TZS | H15: =IF($A15="","",IFERROR(ROUND(SUMIFS('Daily Data'!$N$4:$N$503,'Daily Data'!$B$4:$B$503,$A15,'Daily Data'!$AK$4:$AK$503,COUNTIF('Daily Data'!$B$4:$B$503,$A15))/SUMIFS('Daily Data'!$E$4:$E$503,'Daily Data'!$B$4:$B$503,$A15,'Daily Data'!$AK$4:$AK$503,COUNTIF('Daily Data'!$B$4:$B$503,$A15)),0),"")) -> 23555851 | I15: Derived: official DSE market capitalisation ÷ closing price (Daily Market Report, 23-Feb-2026). Listing date still to be confirmed against the DSE register. | J15: MKCB | K15: =IF($A15="","",IF(OR($E15="",NOT(ISNUMBER($E15))),"VERIFY — listing date missing",IF(N($H15)<=0,"VERIFY — shares outstanding missing","Verified"))) -> VERIFY — listing date missing
... A33: VERTEX-ETF | B33: VERTEX ETF | C33: ETF | D33: Exchange Traded Fund | F33: Yes | G33: TZS | H33: =IF($A33="","",IFERROR(ROUND(SUMIFS('Daily Data'!$N$4:$N$503,'Daily Data'!$B$4:$B$503,$A33,'Daily Data'!$AK$4:$AK$503,COUNTIF('Daily Data'!$B$4:$B$503,$A33))/SUMIFS('Daily Data'!$E$4:$E$503,'Daily Data'!$B$4:$B$503,$A33,'Daily Data'!$AK$4:$AK$503,COUNTIF('Daily Data'!$B$4:$B$503,$A33)),0),"")) -> 54000000 | I33: Derived: official DSE market capitalisation ÷ closing price (Daily Market Report, 23-Feb-2026). Listing date still to be confirmed against the DSE register. | J33: VERTEX-ETF | K33: =IF($A33="","",IF(OR($E33="",NOT(ISNUMBER($E33))),"VERIFY — listing date missing",IF(N($H33)<=0,"VERIFY — shares outstanding missing","Verified"))) -> VERIFY — listing date missing
K34: =IF($A34="","",IF(OR($E34="",NOT(ISNUMBER($E34))),"VERIFY — listing date missing",IF(N($H34)<=0,"VERIFY — shares outstanding missing","Verified")))
K35: =IF($A35="","",IF(OR($E35="",NOT(ISNUMBER($E35))),"VERIFY — listing date missing",IF(N($H35)<=0,"VERIFY — shares outstanding missing","Verified")))
K36: =IF($A36="","",IF(OR($E36="",NOT(ISNUMBER($E36))),"VERIFY — listing date missing",IF(N($H36)<=0,"VERIFY — shares outstanding missing","Verified")))
K37: =IF($A37="","",IF(OR($E37="",NOT(ISNUMBER($E37))),"VERIFY — listing date missing",IF(N($H37)<=0,"VERIFY — shares outstanding missing","Verified")))
K38: =IF($A38="","",IF(OR($E38="",NOT(ISNUMBER($E38))),"VERIFY — listing date missing",IF(N($H38)<=0,"VERIFY — shares outstanding missing","Verified")))
K39: =IF($A39="","",IF(OR($E39="",NOT(ISNUMBER($E39))),"VERIFY — listing date missing",IF(N($H39)<=0,"VERIFY — shares outstanding missing","Verified")))
K40: =IF($A40="","",IF(OR($E40="",NOT(ISNUMBER($E40))),"VERIFY — listing date missing",IF(N($H40)<=0,"VERIFY — shares outstanding missing","Verified")))
K41: =IF($A41="","",IF(OR($E41="",NOT(ISNUMBER($E41))),"VERIFY — listing date missing",IF(N($H41)<=0,"VERIFY — shares outstanding missing","Verified")))
K42: =IF($A42="","",IF(OR($E42="",NOT(ISNUMBER($E42))),"VERIFY — listing date missing",IF(N($H42)<=0,"VERIFY — shares outstanding missing","Verified")))
K43: =IF($A43="","",IF(OR($E43="",NOT(ISNUMBER($E43))),"VERIFY — listing date missing",IF(N($H43)<=0,"VERIFY — shares outstanding missing","Verified")))

Sheet Daily Data
A1: KADIOKO DSE SHEET — DAILY DATA (MASTER OBSERVATION TABLE) | E1: =IF(COUNTIF($O$4:$O$503,"Sample Fixture")>0,"⚠ SAMPLE FIXTURE ROWS PRESENT: "&COUNTIF($O$4:$O$503,"Sample Fixture")&" — run clearSampleFixtures() from the Kadioko menu, or delete them, before using this workbook on live data.","✔ No sample fixture rows — live data only.") -> ✔ No sample fixture rows — live data only.
A2: MASTER DATA TABLE — one row = one security on one trading date. Columns A–Q are raw data; R–AV are calculated. || SOURCE: Dar es Salaam Stock Exchange, Official Daily Market Reports for 10, 11, 12, 13 and 14 August 2026 (Equity Daily Prices + ETF Daily Prices), retrieved from https://dse.co.tz/ on 15 August 2026. Previous Close is carried from the prior trading day's official close within this loaded set; it is blank for each security's first day.
A3: Date | B3: Symbol | C3: Open | D3: Previous Close | E3: Close | F3: High | G3: Low | H3: Change % | I3: Turnover TZS | J3: Deals | K3: Volume | L3: Outstanding Bid Qty | M3: Outstanding Offer Qty | N3: Market Cap TZS | O3: Source | P3: Imported At | Q3: Import Run ID | R3: Validation Status | S3: B/O Ratio | T3: Bid Value | U3: Offer Value | V3: Bid % of MCAP | W3: Offer % of MCAP | X3: Average Trade Volume | Y3: Average Deal Value | Z3: 5D Average B/O | AA3: B/O Momentum % | AB3: 20D Average Volume | AC3: Volume Ratio | AD3: 5D Price Return | AE3: 20D Price Return | AF3: Daily Range % | AG3: Liquidity Score | AH3: Market Pressure Score | AI3: Data Confidence Score | AJ3: Signal | AK3: Obs Index | AL3: Year | AM3: ISO Week | AN3: Month | AO3: P1 B/O Position | AP3: P2 B/O Momentum | AQ3: P3 Price Momentum | AR3: P4 Volume Confirm | AS3: P5 Book Depth/MCAP | AT3: P6 Liquidity Confirm | AU3: Row Key | AV3: New Date Flag
A4: 46244 | B4: AFRIPRISE | C4: 640 | E4: 635 | F4: 645 | G4: 630 | H4: =IF($B4="","",IFERROR($E4/$D4-1,"")) | I4: 32583365 | J4: 207 | K4: 51224 | L4: 14378 | M4: 21492 | N4: 92730000000 | O4: DSE Official Daily Market Report | P4: 46265 | Q4: DSE-202608-10to13 | R4: {=IF($B4="","",IFERROR(IF(INDEX('Data Quality'!$U$4:$U$503,ROW()-3)=0,"PENDING",INDEX('Data Quality'!$U$4:$U$503,ROW()-3)),"PENDING"))} -> PASS | S4: =IF($B4="","",IF(N($M4)>0,$L4/$M4,"")) -> 0.66899311 | T4: =IF($B4="","",$L4*$E4) -> 9130030 | U4: =IF($B4="","",$M4*$E4) -> 13647420 | V4: =IF($B4="","",IF(N($N4)>0,$T4/$N4,"")) -> 9.8458212e-05 | W4: =IF($B4="","",IF(N($N4)>0,$U4/$N4,"")) -> 0.00014717373 | X4: =IF($B4="","",IF(N($J4)>0,$K4/$J4,"")) -> 247.45894 | Y4: =IF($B4="","",IF(N($J4)>0,$I4/$J4,"")) -> 157407.56 | Z4: =IF($B4="","",IF($AK4<=Settings!$C$21,"",IFERROR(AVERAGEIFS($S$4:$S$503,$B$4:$B$503,$B4,$AK$4:$AK$503,">="&$AK4-Settings!$C$21,$AK$4:$AK$503,"<="&$AK4-1),""))) | AA4: =IF(OR($S4="",$Z4="",N($Z4)=0),"",$S4/$Z4-1) | AB4: =IF($B4="","",IF($AK4<=Settings!$C$22,"",IFERROR(AVERAGEIFS($K$4:$K$503,$B$4:$B$503,$B4,$AK$4:$AK$503,">="&$AK4-Settings!$C$22,$AK$4:$AK$503,"<="&$AK4-1),""))) | AC4: =IF(OR($AB4="",N($AB4)=0),"",$K4/$AB4) | AD4: =IF($B4="","",IF($AK4<=Settings!$C$23,"",IFERROR($E4/SUMIFS($E$4:$E$503,$B$4:$B$503,$B4,$AK$4:$AK$503,$AK4-Settings!$C$23)-1,""))) | AE4: =IF($B4="","",IF($AK4<=Settings!$C$22,"",IFERROR($E4/SUMIFS($E$4:$E$503,$B$4:$B$503,$B4,$AK$4:$AK$503,$AK4-Settings!$C$22)-1,""))) | AF4: =IF($B4="","",IF(N($E4)>0,($F4-$G4)/$E4,"")) -> 0.023622047 | AG4: =IF($B4="","",ROUND((MIN(100,100*N($I4)/Settings!$C$27)+MIN(100,100*N($K4)/Settings!$C$28)+MIN(100,100*N($J4)/Settings!$C$29))/3,1)) -> 37.8 | AH4: =IF($B4="","",IF(SUM(Settings!$C$32:$C$37)=0,"",ROUND((Settings!$C$32*$AO4+Settings!$C$33*$AP4+Settings!$C$34*$AQ4+Settings!$C$35*$AR4+Settings!$C$36*$AS4+Settings!$C$37*$AT4)/SUM(Settings!$C$32:$C$37),1))) -> 44.6 | AI4: =IF($B4="","",MAX(0,100-IF(N($N4)>0,0,20)-IF(AND(N($L4)=0,N($M4)=0),15,0)-IF(N($J4)>0,0,10)-IF(N($K4)>0,0,10)-IF($Z4<>"",0,15)-IF($AB4<>"",0,10)-IF($R4="ERROR",20,IF($R4="WARNING",10,0)))) -> 75 | AJ4: =IF($AH4="","",IF($AH4<Settings!$C$46,"Extreme Sell Pressure",IF($AH4<Settings!$C$47,"Sell Pressure",IF($AH4<=Settings!$C$48,"Neutral",IF($AH4<=Settings!$C$49,"Buy Pressure","Extreme Buy Pressure"))))) -> Neutral | AK4: =IF($B4="","",COUNTIFS($B$4:$B$503,$B4,$A$4:$A$503,"<="&$A4)) -> 1 | AL4: =IF($A4="","",YEAR($A4)) -> 2026 | AM4: =IF($A4="","",_xlfn.ISOWEEKNUM($A4)) -> 33 | AN4: =IF($A4="","",MONTH($A4)) -> 8 | AO4: =IF($B4="","",IF(AND(N($L4)=0,N($M4)=0),50,IF(N($M4)=0,100,IF(N($L4)=0,0,MEDIAN(0,100,50+50*LN($S4)/LN(Settings!$C$40)))))) -> 35.501582 | AP4: =IF($AA4="",50,MEDIAN(0,100,50+$AA4*100*Settings!$C$41)) -> 50 | AQ4: =IF($H4="",50,MEDIAN(0,100,50+$H4*100*Settings!$C$42)) -> 50 | AR4: =IF(OR($AC4="",$H4=""),50,MEDIAN(0,100,50+SIGN($H4)*50*MEDIAN(0,1,($AC4-1)/Settings!$C$43))) -> 50 | AS4: =IF(OR($V4="",$W4=""),50,MEDIAN(0,100,50+50*($V4-$W4)/Settings!$C$44)) -> 45.128448 | AT4: =IF($AO4="",50,50+(N($AG4)/100)*($AO4-50)) -> 44.519598 | AU4: =IF($B4="","",$B4&"|"&TEXT($A4,"yyyy-mm-dd")) -> AFRIPRISE|2026-08-10 | AV4: =IF($A4="","",IF(COUNTIFS($A$4:$A4,$A4)=1,1,0)) -> 1
A5: 46244 | B5: CRDB | C5: 2590 | E5: 2600 | F5: 2620 | G5: 2580 | H5: =IF($B5="","",IFERROR($E5/$D5-1,"")) | I5: 7453641800 | J5: 1739 | K5: 2869227 | L5: 129405 | M5: 58236 | N5: 6790780000000 | O5: DSE Official Daily Market Report | P5: 46265 | Q5: DSE-202608-10to13 | R5: {=IF($B5="","",IFERROR(IF(INDEX('Data Quality'!$U$4:$U$503,ROW()-3)=0,"PENDING",INDEX('Data Quality'!$U$4:$U$503,ROW()-3)),"PENDING"))} -> PASS | S5: =IF($B5="","",IF(N($M5)>0,$L5/$M5,"")) -> 2.2220791 | T5: =IF($B5="","",$L5*$E5) -> 336453000 | U5: =IF($B5="","",$M5*$E5) -> 151413600 | V5: =IF($B5="","",IF(N($N5)>0,$T5/$N5,"")) -> 4.954556e-05 | W5: =IF($B5="","",IF(N($N5)>0,$U5/$N5,"")) -> 2.2296938e-05 | X5: =IF($B5="","",IF(N($J5)>0,$K5/$J5,"")) -> 1649.9293 | Y5: =IF($B5="","",IF(N($J5)>0,$I5/$J5,"")) -> 4286165.5 | Z5: =IF($B5="","",IF($AK5<=Settings!$C$21,"",IFERROR(AVERAGEIFS($S$4:$S$503,$B$4:$B$503,$B5,$AK$4:$AK$503,">="&$AK5-Settings!$C$21,$AK$4:$AK$503,"<="&$AK5-1),""))) | AA5: =IF(OR($S5="",$Z5="",N($Z5)=0),"",$S5/$Z5-1) | AB5: =IF($B5="","",IF($AK5<=Settings!$C$22,"",IFERROR(AVERAGEIFS($K$4:$K$503,$B$4:$B$503,$B5,$AK$4:$AK$503,">="&$AK5-Settings!$C$22,$AK$4:$AK$503,"<="&$AK5-1),""))) | AC5: =IF(OR($AB5="",N($AB5)=0),"",$K5/$AB5) | AD5: =IF($B5="","",IF($AK5<=Settings!$C$23,"",IFERROR($E5/SUMIFS($E$4:$E$503,$B$4:$B$503,$B5,$AK$4:$AK$503,$AK5-Settings!$C$23)-1,""))) | AE5: =IF($B5="","",IF($AK5<=Settings!$C$22,"",IFERROR($E5/SUMIFS($E$4:$E$503,$B$4:$B$503,$B5,$AK$4:$AK$503,$AK5-Settings!$C$22)-1,""))) | AF5: =IF($B5="","",IF(N($E5)>0,($F5-$G5)/$E5,"")) -> 0.015384615 | AG5: =IF($B5="","",ROUND((MIN(100,100*N($I5)/Settings!$C$27)+MIN(100,100*N($K5)/Settings!$C$28)+MIN(100,100*N($J5)/Settings!$C$29))/3,1)) -> 100 | AH5: =IF($B5="","",IF(SUM(Settings!$C$32:$C$37)=0,"",ROUND((Settings!$C$32*$AO5+Settings!$C$33*$AP5+Settings!$C$34*$AQ5+Settings!$C$35*$AR5+Settings!$C$36*$AS5+Settings!$C$37*$AT5)/SUM(Settings!$C$32:$C$37),1))) -> 61.8 | AI5: =IF($B5="","",MAX(0,100-IF(N($N5)>0,0,20)-IF(AND(N($L5)=0,N($M5)=0),15,0)-IF(N($J5)>0,0,10)-IF(N($K5)>0,0,10)-IF($Z5<>"",0,15)-IF($AB5<>"",0,10)-IF($R5="ERROR",20,IF($R5="WARNING",10,0)))) -> 75 | AJ5: =IF($AH5="","",IF($AH5<Settings!$C$46,"Extreme Sell Pressure",IF($AH5<Settings!$C$47,"Sell Pressure",IF($AH5<=Settings!$C$48,"Neutral",IF($AH5<=Settings!$C$49,"Buy Pressure","Extreme Buy Pressure"))))) -> Buy Pressure | AK5: =IF($B5="","",COUNTIFS($B$4:$B$503,$B5,$A$4:$A$503,"<="&$A5)) -> 1 | AL5: =IF($A5="","",YEAR($A5)) -> 2026 | AM5: =IF($A5="","",_xlfn.ISOWEEKNUM($A5)) -> 33 | AN5: =IF($A5="","",MONTH($A5)) -> 8 | AO5: =IF($B5="","",IF(AND(N($L5)=0,N($M5)=0),50,IF(N($M5)=0,100,IF(N($L5)=0,0,MEDIAN(0,100,50+50*LN($S5)/LN(Settings!$C$40)))))) -> 78.797755 | AP5: =IF($AA5="",50,MEDIAN(0,100,50+$AA5*100*Settings!$C$41)) -> 50 | AQ5: =IF($H5="",50,MEDIAN(0,100,50+$H5*100*Settings!$C$42)) -> 50 | AR5: =IF(OR($AC5="",$H5=""),50,MEDIAN(0,100,50+SIGN($H5)*50*MEDIAN(0,1,($AC5-1)/Settings!$C$43))) -> 50 | AS5: =IF(OR($V5="",$W5=""),50,MEDIAN(0,100,50+50*($V5-$W5)/Settings!$C$44)) -> 52.724862 | AT5: =IF($AO5="",50,50+(N($AG5)/100)*($AO5-50)) -> 78.797755 | AU5: =IF($B5="","",$B5&"|"&TEXT($A5,"yyyy-mm-dd")) -> CRDB|2026-08-10 | AV5: =IF($A5="","",IF(COUNTIFS($A$4:$A5,$A5)=1,1,0)) -> 0
A6: 46244 | B6: DCB | C6: 420 | E6: 410 | F6: 420 | G6: 390 | H6: =IF($B6="","",IFERROR($E6/$D6-1,"")) | I6: 5769690 | J6: 116 | K6: 14097 | L6: 4055 | M6: 95305 | N6: 78550000000 | O6: DSE Official Daily Market Report | P6: 46265 | Q6: DSE-202608-10to13 | R6: {=IF($B6="","",IFERROR(IF(INDEX('Data Quality'!$U$4:$U$503,ROW()-3)=0,"PENDING",INDEX('Data Quality'!$U$4:$U$503,ROW()-3)),"PENDING"))} -> PASS | S6: =IF($B6="","",IF(N($M6)>0,$L6/$M6,"")) -> 0.04254761 | T6: =IF($B6="","",$L6*$E6) -> 1662550 | U6: =IF($B6="","",$M6*$E6) -> 39075050 | V6: =IF($B6="","",IF(N($N6)>0,$T6/$N6,"")) -> 2.11655e-05 | W6: =IF($B6="","",IF(N($N6)>0,$U6/$N6,"")) -> 0.00049745449 | X6: =IF($B6="","",IF(N($J6)>0,$K6/$J6,"")) -> 121.52586 | Y6: =IF($B6="","",IF(N($J6)>0,$I6/$J6,"")) -> 49738.707 | Z6: =IF($B6="","",IF($AK6<=Settings!$C$21,"",IFERROR(AVERAGEIFS($S$4:$S$503,$B$4:$B$503,$B6,$AK$4:$AK$503,">="&$AK6-Settings!$C$21,$AK$4:$AK$503,"<="&$AK6-1),""))) | AA6: =IF(OR($S6="",$Z6="",N($Z6)=0),"",$S6/$Z6-1) | AB6: =IF($B6="","",IF($AK6<=Settings!$C$22,"",IFERROR(AVERAGEIFS($K$4:$K$503,$B$4:$B$503,$B6,$AK$4:$AK$503,">="&$AK6-Settings!$C$22,$AK$4:$AK$503,"<="&$AK6-1),""))) | AC6: =IF(OR($AB6="",N($AB6)=0),"",$K6/$AB6) | AD6: =IF($B6="","",IF($AK6<=Settings!$C$23,"",IFERROR($E6/SUMIFS($E$4:$E$503,$B$4:$B$503,$B6,$AK$4:$AK$503,$AK6-Settings!$C$23)-1,""))) | AE6: =IF($B6="","",IF($AK6<=Settings!$C$22,"",IFERROR($E6/SUMIFS($E$4:$E$503,$B$4:$B$503,$B6,$AK$4:$AK$503,$AK6-Settings!$C$22)-1,""))) | AF6: =IF($B6="","",IF(N($E6)>0,($F6-$G6)/$E6,"")) -> 0.073170732 | AG6: =IF($B6="","",ROUND((MIN(100,100*N($I6)/Settings!$C$27)+MIN(100,100*N($K6)/Settings!$C$28)+MIN(100,100*N($J6)/Settings!$C$29))/3,1)) -> 34.5 | AH6: =IF($B6="","",IF(SUM(Settings!$C$32:$C$37)=0,"",ROUND((Settings!$C$32*$AO6+Settings!$C$33*$AP6+Settings!$C$34*$AQ6+Settings!$C$35*$AR6+Settings!$C$36*$AS6+Settings!$C$37*$AT6)/SUM(Settings!$C$32:$C$37),1))) -> 28.5 | AI6: =IF($B6="","",MAX(0,100-IF(N($N6)>0,0,20)-IF(AND(N($L6)=0,N($M6)=0),15,0)-IF(N($J6)>0,0,10)-IF(N($K6)>0,0,10)-IF($Z6<>"",0,15)-IF($AB6<>"",0,10)-IF($R6="ERROR",20,IF($R6="WARNING",10,0)))) -> 75 | AJ6: =IF($AH6="","",IF($AH6<Settings!$C$46,"Extreme Sell Pressure",IF($AH6<Settings!$C$47,"Sell Pressure",IF($AH6<=Settings!$C$48,"Neutral",IF($AH6<=Settings!$C$49,"Buy Pressure","Extreme Buy Pressure"))))) -> Sell Pressure | AK6: =IF($B6="","",COUNTIFS($B$4:$B$503,$B6,$A$4:$A$503,"<="&$A6)) -> 1 | AL6: =IF($A6="","",YEAR($A6)) -> 2026 | AM6: =IF($A6="","",_xlfn.ISOWEEKNUM($A6)) -> 33 | AN6: =IF($A6="","",MONTH($A6)) -> 8 | AO6: =IF($B6="","",IF(AND(N($L6)=0,N($M6)=0),50,IF(N($M6)=0,100,IF(N($L6)=0,0,MEDIAN(0,100,50+50*LN($S6)/LN(Settings!$C$40)))))) -> 0 | AP6: =IF($AA6="",50,MEDIAN(0,100,50+$AA6*100*Settings!$C$41)) -> 50 | AQ6: =IF($H6="",50,MEDIAN(0,100,50+$H6*100*Settings!$C$42)) -> 50 | AR6: =IF(OR($AC6="",$H6=""),50,MEDIAN(0,100,50+SIGN($H6)*50*MEDIAN(0,1,($AC6-1)/Settings!$C$43))) -> 50 | AS6: =IF(OR($V6="",$W6=""),50,MEDIAN(0,100,50+50*($V6-$W6)/Settings!$C$44)) -> 2.3711012 | AT6: =IF($AO6="",50,50+(N($AG6)/100)*($AO6-50)) -> 32.75 | AU6: =IF($B6="","",$B6&"|"&TEXT($A6,"yyyy-mm-dd")) -> DCB|2026-08-10 | AV6: =IF($A6="","",IF(COUNTIFS($A$4:$A6,$A6)=1,1,0)) -> 0
A7: 46244 | B7: DSE | C7: 6580 | E7: 6450 | F7: 6580 | G7: 5760 | H7: =IF($B7="","",IFERROR($E7/$D7-1,"")) | I7: 15493780 | J7: 32 | K7: 2411 | L7: 1282 | M7: 4500 | N7: 153660000000 | O7: DSE Official Daily Market Report | P7: 46265 | Q7: DSE-202608-10to13 | R7: {=IF($B7="","",IFERROR(IF(INDEX('Data Quality'!$U$4:$U$503,ROW()-3)=0,"PENDING",INDEX('Data Quality'!$U$4:$U$503,ROW()-3)),"PENDING"))} -> PASS | S7: =IF($B7="","",IF(N($M7)>0,$L7/$M7,"")) -> 0.28488889 | T7: =IF($B7="","",$L7*$E7) -> 8268900 | U7: =IF($B7="","",$M7*$E7) -> 29025000 | V7: =IF($B7="","",IF(N($N7)>0,$T7/$N7,"")) -> 5.3812964e-05 | W7: =IF($B7="","",IF(N($N7)>0,$U7/$N7,"")) -> 0.00018889106 | X7: =IF($B7="","",IF(N($J7)>0,$K7/$J7,"")) -> 75.34375 | Y7: =IF($B7="","",IF(N($J7)>0,$I7/$J7,"")) -> 484180.62 | Z7: =IF($B7="","",IF($AK7<=Settings!$C$21,"",IFERROR(AVERAGEIFS($S$4:$S$503,$B$4:$B$503,$B7,$AK$4:$AK$503,">="&$AK7-Settings!$C$21,$AK$4:$AK$503,"<="&$AK7-1),""))) | AA7: =IF(OR($S7="",$Z7="",N($Z7)=0),"",$S7/$Z7-1) | AB7: =IF($B7="","",IF($AK7<=Settings!$C$22,"",IFERROR(AVERAGEIFS($K$4:$K$503,$B$4:$B$503,$B7,$AK$4:$AK$503,">="&$AK7-Settings!$C$22,$AK$4:$AK$503,"<="&$AK7-1),""))) | AC7: =IF(OR($AB7="",N($AB7)=0),"",$K7/$AB7) | AD7: =IF($B7="","",IF($AK7<=Settings!$C$23,"",IFERROR($E7/SUMIFS($E$4:$E$503,$B$4:$B$503,$B7,$AK$4:$AK$503,$AK7-Settings!$C$23)-1,""))) | AE7: =IF($B7="","",IF($AK7<=Settings!$C$22,"",IFERROR($E7/SUMIFS($E$4:$E$503,$B$4:$B$503,$B7,$AK$4:$AK$503,$AK7-Settings!$C$22)-1,""))) | AF7: =IF($B7="","",IF(N($E7)>0,($F7-$G7)/$E7,"")) -> 0.12713178 | AG7: =IF($B7="","",ROUND((MIN(100,100*N($I7)/Settings!$C$27)+MIN(100,100*N($K7)/Settings!$C$28)+MIN(100,100*N($J7)/Settings!$C$29))/3,1)) -> 11.3 | AH7: =IF($B7="","",IF(SUM(Settings!$C$32:$C$37)=0,"",ROUND((Settings!$C$32*$AO7+Settings!$C$33*$AP7+Settings!$C$34*$AQ7+Settings!$C$35*$AR7+Settings!$C$36*$AS7+Settings!$C$37*$AT7)/SUM(Settings!$C$32:$C$37),1))) -> 34.6 | AI7: =IF($B7="","",MAX(0,100-IF(N($N7)>0,0,20)-IF(AND(N($L7)=0,N($M7)=0),15,0)-IF(N($J7)>0,0,10)-IF(N($K7)>0,0,10)-IF($Z7<>"",0,15)-IF($AB7<>"",0,10)-IF($R7="ERROR",20,IF($R7="WARNING",10,0)))) -> 75 | AJ7: =IF($AH7="","",IF($AH7<Settings!$C$46,"Extreme Sell Pressure",IF($AH7<Settings!$C$47,"Sell Pressure",IF($AH7<=Settings!$C$48,"Neutral",IF($AH7<=Settings!$C$49,"Buy Pressure","Extreme Buy Pressure"))))) -> Sell Pressure | AK7: =IF($B7="","",COUNTIFS($B$4:$B$503,$B7,$A$4:$A$503,"<="&$A7)) -> 1 | AL7: =IF($A7="","",YEAR($A7)) -> 2026 | AM7: =IF($A7="","",_xlfn.ISOWEEKNUM($A7)) -> 33 | AN7: =IF($A7="","",MONTH($A7)) -> 8 | AO7: =IF($B7="","",IF(AND(N($L7)=0,N($M7)=0),50,IF(N($M7)=0,100,IF(N($L7)=0,0,MEDIAN(0,100,50+50*LN($S7)/LN(Settings!$C$40)))))) -> 4.7117815 | AP7: =IF($AA7="",50,MEDIAN(0,100,50+$AA7*100*Settings!$C$41)) -> 50 | AQ7: =IF($H7="",50,MEDIAN(0,100,50+$H7*100*Settings!$C$42)) -> 50 | AR7: =IF(OR($AC7="",$H7=""),50,MEDIAN(0,100,50+SIGN($H7)*50*MEDIAN(0,1,($AC7-1)/Settings!$C$43))) -> 50 | AS7: =IF(OR($V7="",$W7=""),50,MEDIAN(0,100,50+50*($V7-$W7)/Settings!$C$44)) -> 36.492191 | AT7: =IF($AO7="",50,50+(N($AG7)/100)*($AO7-50)) -> 44.882431 | AU7: =IF($B7="","",$B7&"|"&TEXT($A7,"yyyy-mm-dd")) -> DSE|2026-08-10 | AV7: =IF($A7="","",IF(COUNTIFS($A$4:$A7,$A7)=1,1,0)) -> 0
A8: 46244 | B8: EABL | C8: 5830 | E8: 5680 | H8: =IF($B8="","",IFERROR($E8/$D8-1,"")) | I8: 0 | J8: 0 | K8: 0 | L8: 20 | M8: 0 | N8: 4491600000000 | O8: DSE Official Daily Market Report | P8: 46265 | Q8: DSE-202608-10to13 | R8: {=IF($B8="","",IFERROR(IF(INDEX('Data Quality'!$U$4:$U$503,ROW()-3)=0,"PENDING",INDEX('Data Quality'!$U$4:$U$503,ROW()-3)),"PENDING"))} -> PASS | S8: =IF($B8="","",IF(N($M8)>0,$L8/$M8,"")) | T8: =IF($B8="","",$L8*$E8) -> 113600 | U8: =IF($B8="","",$M8*$E8) -> 0 | V8: =IF($B8="","",IF(N($N8)>0,$T8/$N8,"")) -> 2.5291656e-08 | W8: =IF($B8="","",IF(N($N8)>0,$U8/$N8,"")) -> 0 | X8: =IF($B8="","",IF(N($J8)>0,$K8/$J8,"")) | Y8: =IF($B8="","",IF(N($J8)>0,$I8/$J8,"")) | Z8: =IF($B8="","",IF($AK8<=Settings!$C$21,"",IFERROR(AVERAGEIFS($S$4:$S$503,$B$4:$B$503,$B8,$AK$4:$AK$503,">="&$AK8-Settings!$C$21,$AK$4:$AK$503,"<="&$AK8-1),""))) | AA8: =IF(OR($S8="",$Z8="",N($Z8)=0),"",$S8/$Z8-1) | AB8: =IF($B8="","",IF($AK8<=Settings!$C$22,"",IFERROR(AVERAGEIFS($K$4:$K$503,$B$4:$B$503,$B8,$AK$4:$AK$503,">="&$AK8-Settings!$C$22,$AK$4:$AK$503,"<="&$AK8-1),""))) | AC8: =IF(OR($AB8="",N($AB8)=0),"",$K8/$AB8) | AD8: =IF($B8="","",IF($AK8<=Settings!$C$23,"",IFERROR($E8/SUMIFS($E$4:$E$503,$B$4:$B$503,$B8,$AK$4:$AK$503,$AK8-Settings!$C$23)-1,""))) | AE8: =IF($B8="","",IF($AK8<=Settings!$C$22,"",IFERROR($E8/SUMIFS($E$4:$E$503,$B$4:$B$503,$B8,$AK$4:$AK$503,$AK8-Settings!$C$22)-1,""))) | AF8: =IF($B8="","",IF(N($E8)>0,($F8-$G8)/$E8,"")) -> 0 | AG8: =IF($B8="","",ROUND((MIN(100,100*N($I8)/Settings!$C$27)+MIN(100,100*N($K8)/Settings!$C$28)+MIN(100,100*N($J8)/Settings!$C$29))/3,1)) -> 0 | AH8: =IF($B8="","",IF(SUM(Settings!$C$32:$C$37)=0,"",ROUND((Settings!$C$32*$AO8+Settings!$C$33*$AP8+Settings!$C$34*$AQ8+Settings!$C$35*$AR8+Settings!$C$36*$AS8+Settings!$C$37*$AT8)/SUM(Settings!$C$32:$C$37),1))) -> 65 | AI8: =IF($B8="","",MAX(0,100-IF(N($N8)>0,0,20)-IF(AND(N($L8)=0,N($M8)=0),15,0)-IF(N($J8)>0,0,10)-IF(N($K8)>0,0,10)-IF($Z8<>"",0,15)-IF($AB8<>"",0,10)-IF($R8="ERROR",20,IF($R8="WARNING",10,0)))) -> 55 | AJ8: =IF($AH8="","",IF($AH8<Settings!$C$46,"Extreme Sell Pressure",IF($AH8<Settings!$C$47,"Sell Pressure",IF($AH8<=Settings!$C$48,"Neutral",IF($AH8<=Settings!$C$49,"Buy Pressure","Extreme Buy Pressure"))))) -> Buy Pressure | AK8: =IF($B8="","",COUNTIFS($B$4:$B$503,$B8,$A$4:$A$503,"<="&$A8)) -> 1 | AL8: =IF($A8="","",YEAR($A8)) -> 2026 | AM8: =IF($A8="","",_xlfn.ISOWEEKNUM($A8)) -> 33 | AN8: =IF($A8="","",MONTH($A8)) -> 8 | AO8: =IF($B8="","",IF(AND(N($L8)=0,N($M8)=0),50,IF(N($M8)=0,100,IF(N($L8)=0,0,MEDIAN(0,100,50+50*LN($S8)/LN(Settings!$C$40)))))) -> 100 | AP8: =IF($AA8="",50,MEDIAN(0,100,50+$AA8*100*Settings!$C$41)) -> 50 | AQ8: =IF($H8="",50,MEDIAN(0,100,50+$H8*100*Settings!$C$42)) -> 50 | AR8: =IF(OR($AC8="",$H8=""),50,MEDIAN(0,100,50+SIGN($H8)*50*MEDIAN(0,1,($AC8-1)/Settings!$C$43))) -> 50 | AS8: =IF(OR($V8="",$W8=""),50,MEDIAN(0,100,50+50*($V8-$W8)/Settings!$C$44)) -> 50.002529 | AT8: =IF($AO8="",50,50+(N($AG8)/100)*($AO8-50)) -> 50 | AU8: =IF($B8="","",$B8&"|"&TEXT($A8,"yyyy-mm-dd")) -> EABL|2026-08-10 | AV8: =IF($A8="","",IF(COUNTIFS($A$4:$A8,$A8)=1,1,0)) -> 0
A9: 46244 | B9: JATU | C9: 265 | E9: 265 | H9: =IF($B9="","",IFERROR($E9/$D9-1,"")) | I9: 0 | J9: 0 | K9: 0 | L9: 0 | M9: 0 | N9: 5280000000 | O9: DSE Official Daily Market Report | P9: 46265 | Q9: DSE-202608-10to13 | R9: {=IF($B9="","",IFERROR(IF(INDEX('Data Quality'!$U$4:$U$503,ROW()-3)=0,"PENDING",INDEX('Data Quality'!$U$4:$U$503,ROW()-3)),"PENDING"))} -> WARNING | S9: =IF($B9="","",IF(N($M9)>0,$L9/$M9,"")) | T9: =IF($B9="","",$L9*$E9) -> 0 | U9: =IF($B9="","",$M9*$E9) -> 0 | V9: =IF($B9="","",IF(N($N9)>0,$T9/$N9,"")) -> 0 | W9: =IF($B9="","",IF(N($N9)>0,$U9/$N9,"")) -> 0 | X9: =IF($B9="","",IF(N($J9)>0,$K9/$J9,"")) | Y9: =IF($B9="","",IF(N($J9)>0,$I9/$J9,"")) | Z9: =IF($B9="","",IF($AK9<=Settings!$C$21,"",IFERROR(AVERAGEIFS($S$4:$S$503,$B$4:$B$503,$B9,$AK$4:$AK$503,">="&$AK9-Settings!$C$21,$AK$4:$AK$503,"<="&$AK9-1),""))) | AA9: =IF(OR($S9="",$Z9="",N($Z9)=0),"",$S9/$Z9-1) | AB9: =IF($B9="","",IF($AK9<=Settings!$C$22,"",IFERROR(AVERAGEIFS($K$4:$K$503,$B$4:$B$503,$B9,$AK$4:$AK$503,">="&$AK9-Settings!$C$22,$AK$4:$AK$503,"<="&$AK9-1),""))) | AC9: =IF(OR($AB9="",N($AB9)=0),"",$K9/$AB9) | AD9: =IF($B9="","",IF($AK9<=Settings!$C$23,"",IFERROR($E9/SUMIFS($E$4:$E$503,$B$4:$B$503,$B9,$AK$4:$AK$503,$AK9-Settings!$C$23)-1,""))) | AE9: =IF($B9="","",IF($AK9<=Settings!$C$22,"",IFERROR($E9/SUMIFS($E$4:$E$503,$B$4:$B$503,$B9,$AK$4:$AK$503,$AK9-Settings!$C$22)-1,""))) | AF9: =IF($B9="","",IF(N($E9)>0,($F9-$G9)/$E9,"")) -> 0 | AG9: =IF($B9="","",ROUND((MIN(100,100*N($I9)/Settings!$C$27)+MIN(100,100*N($K9)/Settings!$C$28)+MIN(100,100*N($J9)/Settings!$C$29))/3,1)) -> 0 | AH9: =IF($B9="","",IF(SUM(Settings!$C$32:$C$37)=0,"",ROUND((Settings!$C$32*$AO9+Settings!$C$33*$AP9+Settings!$C$34*$AQ9+Settings!$C$35*$AR9+Settings!$C$36*$AS9+Settings!$C$37*$AT9)/SUM(Settings!$C$32:$C$37),1))) -> 50 | AI9: =IF($B9="","",MAX(0,100-IF(N($N9)>0,0,20)-IF(AND(N($L9)=0,N($M9)=0),15,0)-IF(N($J9)>0,0,10)-IF(N($K9)>0,0,10)-IF($Z9<>"",0,15)-IF($AB9<>"",0,10)-IF($R9="ERROR",20,IF($R9="WARNING",10,0)))) -> 30 | AJ9: =IF($AH9="","",IF($AH9<Settings!$C$46,"Extreme Sell Pressure",IF($AH9<Settings!$C$47,"Sell Pressure",IF($AH9<=Settings!$C$48,"Neutral",IF($AH9<=Settings!$C$49,"Buy Pressure","Extreme Buy Pressure"))))) -> Neutral | AK9: =IF($B9="","",COUNTIFS($B$4:$B$503,$B9,$A$4:$A$503,"<="&$A9)) -> 1 | AL9: =IF($A9="","",YEAR($A9)) -> 2026 | AM9: =IF($A9="","",_xlfn.ISOWEEKNUM($A9)) -> 33 | AN9: =IF($A9="","",MONTH($A9)) -> 8 | AO9: =IF($B9="","",IF(AND(N($L9)=0,N($M9)=0),50,IF(N($M9)=0,100,IF(N($L9)=0,0,MEDIAN(0,100,50+50*LN($S9)/LN(Settings!$C$40)))))) -> 50 | AP9: =IF($AA9="",50,MEDIAN(0,100,50+$AA9*100*Settings!$C$41)) -> 50 | AQ9: =IF($H9="",50,MEDIAN(0,100,50+$H9*100*Settings!$C$42)) -> 50 | AR9: =IF(OR($AC9="",$H9=""),50,MEDIAN(0,100,50+SIGN($H9)*50*MEDIAN(0,1,($AC9-1)/Settings!$C$43))) -> 50 | AS9: =IF(OR($V9="",$W9=""),50,MEDIAN(0,100,50+50*($V9-$W9)/Settings!$C$44)) -> 50 | AT9: =IF($AO9="",50,50+(N($AG9)/100)*($AO9-50)) -> 50 | AU9: =IF($B9="","",$B9&"|"&TEXT($A9,"yyyy-mm-dd")) -> JATU|2026-08-10 | AV9: =IF($A9="","",IF(COUNTIFS($A$4:$A9,$A9)=1,1,0)) -> 0
A10: 46244 | B10: JHL | C10: 8650 | E10: 8650 | H10: =IF($B10="","",IFERROR($E10/$D10-1,"")) | I10: 0 | J10: 0 | K10: 0 | L10: 0 | M10: 0 | N10: 626890000000 | O10: DSE Official Daily Market Report | P10: 46265 | Q10: DSE-202608-10to13 | R10: {=IF($B10="","",IFERROR(IF(INDEX('Data Quality'!$U$4:$U$503,ROW()-3)=0,"PENDING",INDEX('Data Quality'!$U$4:$U$503,ROW()-3)),"PENDING"))} -> WARNING | S10: =IF($B10="","",IF(N($M10)>0,$L10/$M10,"")) | T10: =IF($B10="","",$L10*$E10) -> 0 | U10: =IF($B10="","",$M10*$E10) -> 0 | V10: =IF($B10="","",IF(N($N10)>0,$T10/$N10,"")) -> 0 | W10: =IF($B10="","",IF(N($N10)>0,$U10/$N10,"")) -> 0 | X10: =IF($B10="","",IF(N($J10)>0,$K10/$J10,"")) | Y10: =IF($B10="","",IF(N($J10)>0,$I10/$J10,"")) | Z10: =IF($B10="","",IF($AK10<=Settings!$C$21,"",IFERROR(AVERAGEIFS($S$4:$S$503,$B$4:$B$503,$B10,$AK$4:$AK$503,">="&$AK10-Settings!$C$21,$AK$4:$AK$503,"<="&$AK10-1),""))) | AA10: =IF(OR($S10="",$Z10="",N($Z10)=0),"",$S10/$Z10-1) | AB10: =IF($B10="","",IF($AK10<=Settings!$C$22,"",IFERROR(AVERAGEIFS($K$4:$K$503,$B$4:$B$503,$B10,$AK$4:$AK$503,">="&$AK10-Settings!$C$22,$AK$4:$AK$503,"<="&$AK10-1),""))) | AC10: =IF(OR($AB10="",N($AB10)=0),"",$K10/$AB10) | AD10: =IF($B10="","",IF($AK10<=Settings!$C$23,"",IFERROR($E10/SUMIFS($E$4:$E$503,$B$4:$B$503,$B10,$AK$4:$AK$503,$AK10-Settings!$C$23)-1,""))) | AE10: =IF($B10="","",IF($AK10<=Settings!$C$22,"",IFERROR($E10/SUMIFS($E$4:$E$503,$B$4:$B$503,$B10,$AK$4:$AK$503,$AK10-Settings!$C$22)-1,""))) | AF10: =IF($B10="","",IF(N($E10)>0,($F10-$G10)/$E10,"")) -> 0 | AG10: =IF($B10="","",ROUND((MIN(100,100*N($I10)/Settings!$C$27)+MIN(100,100*N($K10)/Settings!$C$28)+MIN(100,100*N($J10)/Settings!$C$29))/3,1)) -> 0 | AH10: =IF($B10="","",IF(SUM(Settings!$C$32:$C$37)=0,"",ROUND((Settings!$C$32*$AO10+Settings!$C$33*$AP10+Settings!$C$34*$AQ10+Settings!$C$35*$AR10+Settings!$C$36*$AS10+Settings!$C$37*$AT10)/SUM(Settings!$C$32:$C$37),1))) -> 50 | AI10: =IF($B10="","",MAX(0,100-IF(N($N10)>0,0,20)-IF(AND(N($L10)=0,N($M10)=0),15,0)-IF(N($J10)>0,0,10)-IF(N($K10)>0,0,10)-IF($Z10<>"",0,15)-IF($AB10<>"",0,10)-IF($R10="ERROR",20,IF($R10="WARNING",10,0)))) -> 30 | AJ10: =IF($AH10="","",IF($AH10<Settings!$C$46,"Extreme Sell Pressure",IF($AH10<Settings!$C$47,"Sell Pressure",IF($AH10<=Settings!$C$48,"Neutral",IF($AH10<=Settings!$C$49,"Buy Pressure","Extreme Buy Pressure"))))) -> Neutral | AK10: =IF($B10="","",COUNTIFS($B$4:$B$503,$B10,$A$4:$A$503,"<="&$A10)) -> 1 | AL10: =IF($A10="","",YEAR($A10)) -> 2026 | AM10: =IF($A10="","",_xlfn.ISOWEEKNUM($A10)) -> 33 | AN10: =IF($A10="","",MONTH($A10)) -> 8 | AO10: =IF($B10="","",IF(AND(N($L10)=0,N($M10)=0),50,IF(N($M10)=0,100,IF(N($L10)=0,0,MEDIAN(0,100,50+50*LN($S10)/LN(Settings!$C$40)))))) -> 50 | AP10: =IF($AA10="",50,MEDIAN(0,100,50+$AA10*100*Settings!$C$41)) -> 50 | AQ10: =IF($H10="",50,MEDIAN(0,100,50+$H10*100*Settings!$C$42)) -> 50 | AR10: =IF(OR($AC10="",$H10=""),50,MEDIAN(0,100,50+SIGN($H10)*50*MEDIAN(0,1,($AC10-1)/Settings!$C$43))) -> 50 | AS10: =IF(OR($V10="",$W10=""),50,MEDIAN(0,100,50+50*($V10-$W10)/Settings!$C$44)) -> 50 | AT10: =IF($AO10="",50,50+(N($AG10)/100)*($AO10-50)) -> 50 | AU10: =IF($B10="","",$B10&"|"&TEXT($A10,"yyyy-mm-dd")) -> JHL|2026-08-10 | AV10: =IF($A10="","",IF(COUNTIFS($A$4:$A10,$A10)=1,1,0)) -> 0
A11: 46244 | B11: KA | C11: 110 | E11: 110 | H11: =IF($B11="","",IFERROR($E11/$D11-1,"")) | I11: 0 | J11: 0 | K11: 0 | L11: 230 | M11: 0 | N11: 624960000000 | O11: DSE Official Daily Market Report | P11: 46265 | Q11: DSE-202608-10to13 | R11: {=IF($B11="","",IFERROR(IF(INDEX('Data Quality'!$U$4:$U$503,ROW()-3)=0,"PENDING",INDEX('Data Quality'!$U$4:$U$503,ROW()-3)),"PENDING"))} -> PASS | S11: =IF($B11="","",IF(N($M11)>0,$L11/$M11,"")) | T11: =IF($B11="","",$L11*$E11) -> 25300 | U11: =IF($B11="","",$M11*$E11) -> 0 | V11: =IF($B11="","",IF(N($N11)>0,$T11/$N11,"")) -> 4.0482591e-08 | W11: =IF($B11="","",IF(N($N11)>0,$U11/$N11,"")) -> 0 | X11: =IF($B11="","",IF(N($J11)>0,$K11/$J11,"")) | Y11: =IF($B11="","",IF(N($J11)>0,$I11/$J11,"")) | Z11: =IF($B11="","",IF($AK11<=Settings!$C$21,"",IFERROR(AVERAGEIFS($S$4:$S$503,$B$4:$B$503,$B11,$AK$4:$AK$503,">="&$AK11-Settings!$C$21,$AK$4:$AK$503,"<="&$AK11-1),""))) | AA11: =IF(OR($S11="",$Z11="",N($Z11)=0),"",$S11/$Z11-1) | AB11: =IF($B11="","",IF($AK11<=Settings!$C$22,"",IFERROR(AVERAGEIFS($K$4:$K$503,$B$4:$B$503,$B11,$AK$4:$AK$503,">="&$AK11-Settings!$C$22,$AK$4:$AK$503,"<="&$AK11-1),""))) | AC11: =IF(OR($AB11="",N($AB11)=0),"",$K11/$AB11) | AD11: =IF($B11="","",IF($AK11<=Settings!$C$23,"",IFERROR($E11/SUMIFS($E$4:$E$503,$B$4:$B$503,$B11,$AK$4:$AK$503,$AK11-Settings!$C$23)-1,""))) | AE11: =IF($B11="","",IF($AK11<=Settings!$C$22,"",IFERROR($E11/SUMIFS($E$4:$E$503,$B$4:$B$503,$B11,$AK$4:$AK$503,$AK11-Settings!$C$22)-1,""))) | AF11: =IF($B11="","",IF(N($E11)>0,($F11-$G11)/$E11,"")) -> 0 | AG11: =IF($B11="","",ROUND((MIN(100,100*N($I11)/Settings!$C$27)+MIN(100,100*N($K11)/Settings!$C$28)+MIN(100,100*N($J11)/Settings!$C$29))/3,1)) -> 0 | AH11: =IF($B11="","",IF(SUM(Settings!$C$32:$C$37)=0,"",ROUND((Settings!$C$32*$AO11+Settings!$C$33*$AP11+Settings!$C$34*$AQ11+Settings!$C$35*$AR11+Settings!$C$36*$AS11+Settings!$C$37*$AT11)/SUM(Settings!$C$32:$C$37),1))) -> 65 | AI11: =IF($B11="","",MAX(0,100-IF(N($N11)>0,0,20)-IF(AND(N($L11)=0,N($M11)=0),15,0)-IF(N($J11)>0,0,10)-IF(N($K11)>0,0,10)-IF($Z11<>"",0,15)-IF($AB11<>"",0,10)-IF($R11="ERROR",20,IF($R11="WARNING",10,0)))) -> 55 | AJ11: =IF($AH11="","",IF($AH11<Settings!$C$46,"Extreme Sell Pressure",IF($AH11<Settings!$C$47,"Sell Pressure",IF($AH11<=Settings!$C$48,"Neutral",IF($AH11<=Settings!$C$49,"Buy Pressure","Extreme Buy Pressure"))))) -> Buy Pressure | AK11: =IF($B11="","",COUNTIFS($B$4:$B$503,$B11,$A$4:$A$503,"<="&$A11)) -> 1 | AL11: =IF($A11="","",YEAR($A11)) -> 2026 | AM11: =IF($A11="","",_xlfn.ISOWEEKNUM($A11)) -> 33 | AN11: =IF($A11="","",MONTH($A11)) -> 8 | AO11: =IF($B11="","",IF(AND(N($L11)=0,N($M11)=0),50,IF(N($M11)=0,100,IF(N($L11)=0,0,MEDIAN(0,100,50+50*LN($S11)/LN(Settings!$C$40)))))) -> 100 | AP11: =IF($AA11="",50,MEDIAN(0,100,50+$AA11*100*Settings!$C$41)) -> 50 | AQ11: =IF($H11="",50,MEDIAN(0,100,50+$H11*100*Settings!$C$42)) -> 50 | AR11: =IF(OR($AC11="",$H11=""),50,MEDIAN(0,100,50+SIGN($H11)*50*MEDIAN(0,1,($AC11-1)/Settings!$C$43))) -> 50 | AS11: =IF(OR($V11="",$W11=""),50,MEDIAN(0,100,50+50*($V11-$W11)/Settings!$C$44)) -> 50.004048 | AT11: =IF($AO11="",50,50+(N($AG11)/100)*($AO11-50)) -> 50 | AU11: =IF($B11="","",$B11&"|"&TEXT($A11,"yyyy-mm-dd")) -> KA|2026-08-10 | AV11: =IF($A11="","",IF(COUNTIFS($A$4:$A11,$A11)=1,1,0)) -> 0
A12: 46244 | B12: KCB | C12: 1890 | E12: 1900 | F12: 1900 | G12: 1880 | H12: =IF($B12="","",IFERROR($E12/$D12-1,"")) | I12: 10287840 | J12: 53 | K12: 5425 | L12: 10141 | M12: 23591 | N12: 5643650000000 | O12: DSE Official Daily Market Report | P12: 46265 | Q12: DSE-202608-10to13 | R12: {=IF($B12="","",IFERROR(IF(INDEX('Data Quality'!$U$4:$U$503,ROW()-3)=0,"PENDING",INDEX('Data Quality'!$U$4:$U$503,ROW()-3)),"PENDING"))} -> PASS | S12: =IF($B12="","",IF(N($M12)>0,$L12/$M12,"")) -> 0.42986732 | T12: =IF($B12="","",$L12*$E12) -> 19267900 | U12: =IF($B12="","",$M12*$E12) -> 44822900 | V12: =IF($B12="","",IF(N($N12)>0,$T12/$N12,"")) -> 3.4140849e-06 | W12: =IF($B12="","",IF(N($N12)>0,$U12/$N12,"")) -> 7.9421828e-06 | X12: =IF($B12="","",IF(N($J12)>0,$K12/$J12,"")) -> 102.35849 | Y12: =IF($B12="","",IF(N($J12)>0,$I12/$J12,"")) -> 194110.19 | Z12: =IF($B12="","",IF($AK12<=Settings!$C$21,"",IFERROR(AVERAGEIFS($S$4:$S$503,$B$4:$B$503,$B12,$AK$4:$AK$503,">="&$AK12-Settings!$C$21,$AK$4:$AK$503,"<="&$AK12-1),""))) | AA12: =IF(OR($S12="",$Z12="",N($Z12)=0),"",$S12/$Z12-1) | AB12: =IF($B12="","",IF($AK12<=Settings!$C$22,"",IFERROR(AVERAGEIFS($K$4:$K$503,$B$4:$B$503,$B12,$AK$4:$AK$503,">="&$AK12-Settings!$C$22,$AK$4:$AK$503,"<="&$AK12-1),""))) | AC12: =IF(OR($AB12="",N($AB12)=0),"",$K12/$AB12) | AD12: =IF($B12="","",IF($AK12<=Settings!$C$23,"",IFERROR($E12/SUMIFS($E$4:$E$503,$B$4:$B$503,$B12,$AK$4:$AK$503,$AK12-Settings!$C$23)-1,""))) | AE12: =IF($B12="","",IF($AK12<=Settings!$C$22,"",IFERROR($E12/SUMIFS($E$4:$E$503,$B$4:$B$503,$B12,$AK$4:$AK$503,$AK12-Settings!$C$22)-1,""))) | AF12: =IF($B12="","",IF(N($E12)>0,($F12-$G12)/$E12,"")) -> 0.010526316 | AG12: =IF($B12="","",ROUND((MIN(100,100*N($I12)/Settings!$C$27)+MIN(100,100*N($K12)/Settings!$C$28)+MIN(100,100*N($J12)/Settings!$C$29))/3,1)) -> 18.4 | AH12: =IF($B12="","",IF(SUM(Settings!$C$32:$C$37)=0,"",ROUND((Settings!$C$32*$AO12+Settings!$C$33*$AP12+Settings!$C$34*$AQ12+Settings!$C$35*$AR12+Settings!$C$36*$AS12+Settings!$C$37*$AT12)/SUM(Settings!$C$32:$C$37),1))) -> 40.3 | AI12: =IF($B12="","",MAX(0,100-IF(N($N12)>0,0,20)-IF(AND(N($L12)=0,N($M12)=0),15,0)-IF(N($J12)>0,0,10)-IF(N($K12)>0,0,10)-IF($Z12<>"",0,15)-IF($AB12<>"",0,10)-IF($R12="ERROR",20,IF($R12="WARNING",10,0)))) -> 75 | AJ12: =IF($AH12="","",IF($AH12<Settings!$C$46,"Extreme Sell Pressure",IF($AH12<Settings!$C$47,"Sell Pressure",IF($AH12<=Settings!$C$48,"Neutral",IF($AH12<=Settings!$C$49,"Buy Pressure","Extreme Buy Pressure"))))) -> Neutral | AK12: =IF($B12="","",COUNTIFS($B$4:$B$503,$B12,$A$4:$A$503,"<="&$A12)) -> 1 | AL12: =IF($A12="","",YEAR($A12)) -> 2026 | AM12: =IF($A12="","",_xlfn.ISOWEEKNUM($A12)) -> 33 | AN12: =IF($A12="","",MONTH($A12)) -> 8 | AO12: =IF($B12="","",IF(AND(N($L12)=0,N($M12)=0),50,IF(N($M12)=0,100,IF(N($L12)=0,0,MEDIAN(0,100,50+50*LN($S12)/LN(Settings!$C$40)))))) -> 19.549084 | AP12: =IF($AA12="",50,MEDIAN(0,100,50+$AA12*100*Settings!$C$41)) -> 50 | AQ12: =IF($H12="",50,MEDIAN(0,100,50+$H12*100*Settings!$C$42)) -> 50 | AR12: =IF(OR($AC12="",$H12=""),50,MEDIAN(0,100,50+SIGN($H12)*50*MEDIAN(0,1,($AC12-1)/Settings!$C$43))) -> 50 | AS12: =IF(OR($V12="",$W12=""),50,MEDIAN(0,100,50+50*($V12-$W12)/Settings!$C$44)) -> 49.54719 | AT12: =IF($AO12="",50,50+(N($AG12)/100)*($AO12-50)) -> 44.397031 | AU12: =IF($B12="","",$B12&"|"&TEXT($A12,"yyyy-mm-dd")) -> KCB|2026-08-10 | AV12: =IF($A12="","",IF(COUNTIFS($A$4:$A12,$A12)=1,1,0)) -> 0
A13: 46244 | B13: MBP | C13: 1600 | E13: 1660 | F13: 1790 | G13: 1600 | H13: =IF($B13="","",IFERROR($E13/$D13-1,"")) | I13: 2049600 | J13: 13 | K13: 1232 | L13: 4005 | M13: 23587 | N13: 49780000000 | O13: DSE Official Daily Market Report | P13: 46265 | Q13: DSE-202608-10to13 | R13: {=IF($B13="","",IFERROR(IF(INDEX('Data Quality'!$U$4:$U$503,ROW()-3)=0,"PENDING",INDEX('Data Quality'!$U$4:$U$503,ROW()-3)),"PENDING"))} -> PASS | S13: =IF($B13="","",IF(N($M13)>0,$L13/$M13,"")) -> 0.16979692 | T13: =IF($B13="","",$L13*$E13) -> 6648300 | U13: =IF($B13="","",$M13*$E13) -> 39154420 | V13: =IF($B13="","",IF(N($N13)>0,$T13/$N13,"")) -> 0.00013355364 | W13: =IF($B13="","",IF(N($N13)>0,$U13/$N13,"")) -> 0.00078654922 | X13: =IF($B13="","",IF(N($J13)>0,$K13/$J13,"")) -> 94.769231 | Y13: =IF($B13="","",IF(N($J13)>0,$I13/$J13,"")) -> 157661.54 | Z13: =IF($B13="","",IF($AK13<=Settings!$C$21,"",IFERROR(AVERAGEIFS($S$4:$S$503,$B$4:$B$503,$B13,$AK$4:$AK$503,">="&$AK13-Settings!$C$21,$AK$4:$AK$503,"<="&$AK13-1),""))) | AA13: =IF(OR($S13="",$Z13="",N($Z13)=0),"",$S13/$Z13-1) | AB13: =IF($B13="","",IF($AK13<=Settings!$C$22,"",IFERROR(AVERAGEIFS($K$4:$K$503,$B$4:$B$503,$B13,$AK$4:$AK$503,">="&$AK13-Settings!$C$22,$AK$4:$AK$503,"<="&$AK13-1),""))) | AC13: =IF(OR($AB13="",N($AB13)=0),"",$K13/$AB13) | AD13: =IF($B13="","",IF($AK13<=Settings!$C$23,"",IFERROR($E13/SUMIFS($E$4:$E$503,$B$4:$B$503,$B13,$AK$4:$AK$503,$AK13-Settings!$C$23)-1,""))) | AE13: =IF($B13="","",IF($AK13<=Settings!$C$22,"",IFERROR($E13/SUMIFS($E$4:$E$503,$B$4:$B$503,$B13,$AK$4:$AK$503,$AK13-Settings!$C$22)-1,""))) | AF13: =IF($B13="","",IF(N($E13)>0,($F13-$G13)/$E13,"")) -> 0.11445783 | AG13: =IF($B13="","",ROUND((MIN(100,100*N($I13)/Settings!$C$27)+MIN(100,100*N($K13)/Settings!$C$28)+MIN(100,100*N($J13)/Settings!$C$29))/3,1)) -> 4.5 | AH13: =IF($B13="","",IF(SUM(Settings!$C$32:$C$37)=0,"",ROUND((Settings!$C$32*$AO13+Settings!$C$33*$AP13+Settings!$C$34*$AQ13+Settings!$C$35*$AR13+Settings!$C$36*$AS13+Settings!$C$37*$AT13)/SUM(Settings!$C$32:$C$37),1))) -> 29.8 | AI13: =IF($B13="","",MAX(0,100-IF(N($N13)>0,0,20)-IF(AND(N($L13)=0,N($M13)=0),15,0)-IF(N($J13)>0,0,10)-IF(N($K13)>0,0,10)-IF($Z13<>"",0,15)-IF($AB13<>"",0,10)-IF($R13="ERROR",20,IF($R13="WARNING",10,0)))) -> 75 | AJ13: =IF($AH13="","",IF($AH13<Settings!$C$46,"Extreme Sell Pressure",IF($AH13<Settings!$C$47,"Sell Pressure",IF($AH13<=Settings!$C$48,"Neutral",IF($AH13<=Settings!$C$49,"Buy Pressure","Extreme Buy Pressure"))))) -> Sell Pressure | AK13: =IF($B13="","",COUNTIFS($B$4:$B$503,$B13,$A$4:$A$503,"<="&$A13)) -> 1 | AL13: =IF($A13="","",YEAR($A13)) -> 2026 | AM13: =IF($A13="","",_xlfn.ISOWEEKNUM($A13)) -> 33 | AN13: =IF($A13="","",MONTH($A13)) -> 8 | AO13: =IF($B13="","",IF(AND(N($L13)=0,N($M13)=0),50,IF(N($M13)=0,100,IF(N($L13)=0,0,MEDIAN(0,100,50+50*LN($S13)/LN(Settings!$C$40)))))) -> 0 | AP13: =IF($AA13="",50,MEDIAN(0,100,50+$AA13*100*Settings!$C$41)) -> 50 | AQ13: =IF($H13="",50,MEDIAN(0,100,50+$H13*100*Settings!$C$42)) -> 50 | AR13: =IF(OR($AC13="",$H13=""),50,MEDIAN(0,100,50+SIGN($H13)*50*MEDIAN(0,1,($AC13-1)/Settings!$C$43))) -> 50 | AS13: =IF(OR($V13="",$W13=""),50,MEDIAN(0,100,50+50*($V13-$W13)/Settings!$C$44)) -> 0 | AT13: =IF($AO13="",50,50+(N($AG13)/100)*($AO13-50)) -> 47.75 | AU13: =IF($B13="","",$B13&"|"&TEXT($A13,"yyyy-mm-dd")) -> MBP|2026-08-10 | AV13: =IF($A13="","",IF(COUNTIFS($A$4:$A13,$A13)=1,1,0)) -> 0
A14: 46244 | B14: MCB | C14: 470 | E14: 525 | F14: 540 | G14: 470 | H14: =IF($B14="","",IFERROR($E14/$D14-1,"")) | I14: 197649400 | J14: 621 | K14: 376487 | L14: 102784 | M14: 137956 | N14: 129830000000 | O14: DSE Official Daily Market Report | P14: 46265 | Q14: DSE-202608-10to13 | R14: {=IF($B14="","",IFERROR(IF(INDEX('Data Quality'!$U$4:$U$503,ROW()-3)=0,"PENDING",INDEX('Data Quality'!$U$4:$U$503,ROW()-3)),"PENDING"))} -> PASS | S14: =IF($B14="","",IF(N($M14)>0,$L14/$M14,"")) -> 0.74504915 | T14: =IF($B14="","",$L14*$E14) -> 53961600 | U14: =IF($B14="","",$M14*$E14) -> 72426900 | V14: =IF($B14="","",IF(N($N14)>0,$T14/$N14,"")) -> 0.00041563275 | W14: =IF($B14="","",IF(N($N14)>0,$U14/$N14,"")) -> 0.00055785951 | X14: =IF($B14="","",IF(N($J14)>0,$K14/$J14,"")) -> 606.25926 | Y14: =IF($B14="","",IF(N($J14)>0,$I14/$J14,"")) -> 318276.01 | Z14: =IF($B14="","",IF($AK14<=Settings!$C$21,"",IFERROR(AVERAGEIFS($S$4:$S$503,$B$4:$B$503,$B14,$AK$4:$AK$503,">="&$AK14-Settings!$C$21,$AK$4:$AK$503,"<="&$AK14-1),""))) | AA14: =IF(OR($S14="",$Z14="",N($Z14)=0),"",$S14/$Z14-1) | AB14: =IF($B14="","",IF($AK14<=Settings!$C$22,"",IFERROR(AVERAGEIFS($K$4:$K$503,$B$4:$B$503,$B14,$AK$4:$AK$503,">="&$AK14-Settings!$C$22,$AK$4:$AK$503,"<="&$AK14-1),""))) | AC14: =IF(OR($AB14="",N($AB14)=0),"",$K14/$AB14) | AD14: =IF($B14="","",IF($AK14<=Settings!$C$23,"",IFERROR($E14/SUMIFS($E$4:$E$503,$B$4:$B$503,$B14,$AK$4:$AK$503,$AK14-Settings!$C$23)-1,""))) | AE14: =IF($B14="","",IF($AK14<=Settings!$C$22,"",IFERROR($E14/SUMIFS($E$4:$E$503,$B$4:$B$503,$B14,$AK$4:$AK$503,$AK14-Settings!$C$22)-1,""))) | AF14: =IF($B14="","",IF(N($E14)>0,($F14-$G14)/$E14,"")) -> 0.13333333 | AG14: =IF($B14="","",ROUND((MIN(100,100*N($I14)/Settings!$C$27)+MIN(100,100*N($K14)/Settings!$C$28)+MIN(100,100*N($J14)/Settings!$C$29))/3,1)) -> 65 | AH14: =IF($B14="","",IF(SUM(Settings!$C$32:$C$37)=0,"",ROUND((Settings!$C$32*$AO14+Settings!$C$33*$AP14+Settings!$C$34*$AQ14+Settings!$C$35*$AR14+Settings!$C$36*$AS14+Settings!$C$37*$AT14)/SUM(Settings!$C$32:$C$37),1))) -> 44.7 | AI14: =IF($B14="","",MAX(0,100-IF(N($N14)>0,0,20)-IF(AND(N($L14)=0,N($M14)=0),15,0)-IF(N($J14)>0,0,10)-IF(N($K14)>0,0,10)-IF($Z14<>"",0,15)-IF($AB14<>"",0,10)-IF($R14="ERROR",20,IF($R14="WARNING",10,0)))) -> 75 | AJ14: =IF($AH14="","",IF($AH14<Settings!$C$46,"Extreme Sell Pressure",IF($AH14<Settings!$C$47,"Sell Pressure",IF($AH14<=Settings!$C$48,"Neutral",IF($AH14<=Settings!$C$49,"Buy Pressure","Extreme Buy Pressure"))))) -> Neutral | AK14: =IF($B14="","",COUNTIFS($B$4:$B$503,$B14,$A$4:$A$503,"<="&$A14)) -> 1 | AL14: =IF($A14="","",YEAR($A14)) -> 2026 | AM14: =IF($A14="","",_xlfn.ISOWEEKNUM($A14)) -> 33 | AN14: =IF($A14="","",MONTH($A14)) -> 8 | AO14: =IF($B14="","",IF(AND(N($L14)=0,N($M14)=0),50,IF(N($M14)=0,100,IF(N($L14)=0,0,MEDIAN(0,100,50+50*LN($S14)/LN(Settings!$C$40)))))) -> 39.385187 | AP14: =IF($AA14="",50,MEDIAN(0,100,50+$AA14*100*Settings!$C$41)) -> 50 | AQ14: =IF($H14="",50,MEDIAN(0,100,50+$H14*100*Settings!$C$42)) -> 50 | AR14: =IF(OR($AC14="",$H14=""),50,MEDIAN(0,100,50+SIGN($H14)*50*MEDIAN(0,1,($AC14-1)/Settings!$C$43))) -> 50 | AS14: =IF(OR($V14="",$W14=""),50,MEDIAN(0,100,50+50*($V14-$W14)/Settings!$C$44)) -> 35.777324 | AT14: =IF($AO14="",50,50+(N($AG14)/100)*($AO14-50)) -> 43.100372 | AU14: =IF($B14="","",$B14&"|"&TEXT($A14,"yyyy-mm-dd")) -> MCB|2026-08-10 | AV14: =IF($A14="","",IF(COUNTIFS($A$4:$A14,$A14)=1,1,0)) -> 0
A15: 46244 | B15: MKCB | C15: 3670 | E15: 3740 | F15: 3800 | G15: 3500 | H15: =IF($B15="","",IFERROR($E15/$D15-1,"")) | I15: 10029550 | J15: 21 | K15: 2692 | L15: 1039 | M15: 818 | N15: 88100000000 | O15: DSE Official Daily Market Report | P15: 46265 | Q15: DSE-202608-10to13 | R15: {=IF($B15="","",IFERROR(IF(INDEX('Data Quality'!$U$4:$U$503,ROW()-3)=0,"PENDING",INDEX('Data Quality'!$U$4:$U$503,ROW()-3)),"PENDING"))} -> PASS | S15: =IF($B15="","",IF(N($M15)>0,$L15/$M15,"")) -> 1.2701711 | T15: =IF($B15="","",$L15*$E15) -> 3885860 | U15: =IF($B15="","",$M15*$E15) -> 3059320 | V15: =IF($B15="","",IF(N($N15)>0,$T15/$N15,"")) -> 4.4107378e-05 | W15: =IF($B15="","",IF(N($N15)>0,$U15/$N15,"")) -> 3.4725539e-05 | X15: =IF($B15="","",IF(N($J15)>0,$K15/$J15,"")) -> 128.19048 | Y15: =IF($B15="","",IF(N($J15)>0,$I15/$J15,"")) -> 477597.62 | Z15: =IF($B15="","",IF($AK15<=Settings!$C$21,"",IFERROR(AVERAGEIFS($S$4:$S$503,$B$4:$B$503,$B15,$AK$4:$AK$503,">="&$AK15-Settings!$C$21,$AK$4:$AK$503,"<="&$AK15-1),""))) | AA15: =IF(OR($S15="",$Z15="",N($Z15)=0),"",$S15/$Z15-1) | AB15: =IF($B15="","",IF($AK15<=Settings!$C$22,"",IFERROR(AVERAGEIFS($K$4:$K$503,$B$4:$B$503,$B15,$AK$4:$AK$503,">="&$AK15-Settings!$C$22,$AK$4:$AK$503,"<="&$AK15-1),""))) | AC15: =IF(OR($AB15="",N($AB15)=0),"",$K15/$AB15) | AD15: =IF($B15="","",IF($AK15<=Settings!$C$23,"",IFERROR($E15/SUMIFS($E$4:$E$503,$B$4:$B$503,$B15,$AK$4:$AK$503,$AK15-Settings!$C$23)-1,""))) | AE15: =IF($B15="","",IF($AK15<=Settings!$C$22,"",IFERROR($E15/SUMIFS($E$4:$E$503,$B$4:$B$503,$B15,$AK$4:$AK$503,$AK15-Settings!$C$22)-1,""))) | AF15: =IF($B15="","",IF(N($E15)>0,($F15-$G15)/$E15,"")) -> 0.080213904 | AG15: =IF($B15="","",ROUND((MIN(100,100*N($I15)/Settings!$C$27)+MIN(100,100*N($K15)/Settings!$C$28)+MIN(100,100*N($J15)/Settings!$C$29))/3,1)) -> 7.5 | AH15: =IF($B15="","",IF(SUM(Settings!$C$32:$C$37)=0,"",ROUND((Settings!$C$32*$AO15+Settings!$C$33*$AP15+Settings!$C$34*$AQ15+Settings!$C$35*$AR15+Settings!$C$36*$AS15+Settings!$C$37*$AT15)/SUM(Settings!$C$32:$C$37),1))) -> 52.7 | AI15: =IF($B15="","",MAX(0,100-IF(N($N15)>0,0,20)-IF(AND(N($L15)=0,N($M15)=0),15,0)-IF(N($J15)>0,0,10)-IF(N($K15)>0,0,10)-IF($Z15<>"",0,15)-IF($AB15<>"",0,10)-IF($R15="ERROR",20,IF($R15="WARNING",10,0)))) -> 75 | AJ15: =IF($AH15="","",IF($AH15<Settings!$C$46,"Extreme Sell Pressure",IF($AH15<Settings!$C$47,"Sell Pressure",IF($AH15<=Settings!$C$48,"Neutral",IF($AH15<=Settings!$C$49,"Buy Pressure","Extreme Buy Pressure"))))) -> Neutral | AK15: =IF($B15="","",COUNTIFS($B$4:$B$503,$B15,$A$4:$A$503,"<="&$A15)) -> 1 | AL15: =IF($A15="","",YEAR($A15)) -> 2026 | AM15: =IF($A15="","",_xlfn.ISOWEEKNUM($A15)) -> 33 | AN15: =IF($A15="","",MONTH($A15)) -> 8 | AO15: =IF($B15="","",IF(AND(N($L15)=0,N($M15)=0),50,IF(N($M15)=0,100,IF(N($L15)=0,0,MEDIAN(0,100,50+50*LN($S15)/LN(Settings!$C$40)))))) -> 58.625573 | AP15: =IF($AA15="",50,MEDIAN(0,100,50+$AA15*100*Settings!$C$41)) -> 50 | AQ15: =IF($H15="",50,MEDIAN(0,100,50+$H15*100*Settings!$C$42)) -> 50 | AR15: =IF(OR($AC15="",$H15=""),50,MEDIAN(0,100,50+SIGN($H15)*50*MEDIAN(0,1,($AC15-1)/Settings!$C$43))) -> 50 | AS15: =IF(OR($V15="",$W15=""),50,MEDIAN(0,100,50+50*($V15-$W15)/Settings!$C$44)) -> 50.938184 | AT15: =IF($AO15="",50,50+(N($AG15)/100)*($AO15-50)) -> 50.646918 | AU15: =IF($B15="","",$B15&"|"&TEXT($A15,"yyyy-mm-dd")) -> MKCB|2026-08-10 | AV15: =IF($A15="","",IF(COUNTIFS($A$4:$A15,$A15)=1,1,0)) -> 0
A16: 46244 | B16: MUCOBA | C16: 440 | E16: 455 | F16: 465 | G16: 445 | H16: =IF($B16="","",IFERROR($E16/$D16-1,"")) | I16: 666475 | J16: 29 | K16: 1455 | L16: 2688 | M16: 1705 | N16: 14860000000 | O16: DSE Official Daily Market Report | P16: 46265 | Q16: DSE-202608-10to13 | R16: {=IF($B16="","",IFERROR(IF(INDEX('Data Quality'!$U$4:$U$503,ROW()-3)=0,"PENDING",INDEX('Data Quality'!$U$4:$U$503,ROW()-3)),"PENDING"))} -> PASS | S16: =IF($B16="","",IF(N($M16)>0,$L16/$M16,"")) -> 1.5765396 | T16: =IF($B16="","",$L16*$E16) -> 1223040 | U16: =IF($B16="","",$M16*$E16) -> 775775 | V16: =IF($B16="","",IF(N($N16)>0,$T16/$N16,"")) -> 8.2304172e-05 | W16: =IF($B16="","",IF(N($N16)>0,$U16/$N16,"")) -> 5.2205585e-05 | X16: =IF($B16="","",IF(N($J16)>0,$K16/$J16,"")) -> 50.172414 | Y16: =IF($B16="","",IF(N($J16)>0,$I16/$J16,"")) -> 22981.897 | Z16: =IF($B16="","",IF($AK16<=Settings!$C$21,"",IFERROR(AVERAGEIFS($S$4:$S$503,$B$4:$B$503,$B16,$AK$4:$AK$503,">="&$AK16-Settings!$C$21,$AK$4:$AK$503,"<="&$AK16-1),""))) | AA16: =IF(OR($S16="",$Z16="",N($Z16)=0),"",$S16/$Z16-1) | AB16: =IF($B16="","",IF($AK16<=Settings!$C$22,"",IFERROR(AVERAGEIFS($K$4:$K$503,$B$4:$B$503,$B16,$AK$4:$AK$503,">="&$AK16-Settings!$C$22,$AK$4:$AK$503,"<="&$AK16-1),""))) | AC16: =IF(OR($AB16="",N($AB16)=0),"",$K16/$AB16) | AD16: =IF($B16="","",IF($AK16<=Settings!$C$23,"",IFERROR($E16/SUMIFS($E$4:$E$503,$B$4:$B$503,$B16,$AK$4:$AK$503,$AK16-Settings!$C$23)-1,""))) | AE16: =IF($B16="","",IF($AK16<=Settings!$C$22,"",IFERROR($E16/SUMIFS($E$4:$E$503,$B$4:$B$503,$B16,$AK$4:$AK$503,$AK16-Settings!$C$22)-1,""))) | AF16: =IF($B16="","",IF(N($E16)>0,($F16-$G16)/$E16,"")) -> 0.043956044 | AG16: =IF($B16="","",ROUND((MIN(100,100*N($I16)/Settings!$C$27)+MIN(100,100*N($K16)/Settings!$C$28)+MIN(100,100*N($J16)/Settings!$C$29))/3,1)) -> 9.8 | AH16: =IF($B16="","",IF(SUM(Settings!$C$32:$C$37)=0,"",ROUND((Settings!$C$32*$AO16+Settings!$C$33*$AP16+Settings!$C$34*$AQ16+Settings!$C$35*$AR16+Settings!$C$36*$AS16+Settings!$C$37*$AT16)/SUM(Settings!$C$32:$C$37),1))) -> 55.4 | AI16: =IF($B16="","",MAX(0,100-IF(N($N16)>0,0,20)-IF(AND(N($L16)=0,N($M16)=0),15,0)-IF(N($J16)>0,0,10)-IF(N($K16)>0,0,10)-IF($Z16<>"",0,15)-IF($AB16<>"",0,10)-IF($R16="ERROR",20,IF($R16="WARNING",10,0)))) -> 75 | AJ16: =IF($AH16="","",IF($AH16<Settings!$C$46,"Extreme Sell Pressure",IF($AH16<Settings!$C$47,"Sell Pressure",IF($AH16<=Settings!$C$48,"Neutral",IF($AH16<=Settings!$C$49,"Buy Pressure","Extreme Buy Pressure"))))) -> Neutral | AK16: =IF($B16="","",COUNTIFS($B$4:$B$503,$B16,$A$4:$A$503,"<="&$A16)) -> 1 | AL16: =IF($A16="","",YEAR($A16)) -> 2026 | AM16: =IF($A16="","",_xlfn.ISOWEEKNUM($A16)) -> 33 | AN16: =IF($A16="","",MONTH($A16)) -> 8 | AO16: =IF($B16="","",IF(AND(N($L16)=0,N($M16)=0),50,IF(N($M16)=0,100,IF(N($L16)=0,0,MEDIAN(0,100,50+50*LN($S16)/LN(Settings!$C$40)))))) -> 66.419035 | AP16: =IF($AA16="",50,MEDIAN(0,100,50+$AA16*100*Settings!$C$41)) -> 50 | AQ16: =IF($H16="",50,MEDIAN(0,100,50+$H16*100*Settings!$C$42)) -> 50 | AR16: =IF(OR($AC16="",$H16=""),50,MEDIAN(0,100,50+SIGN($H16)*50*MEDIAN(0,1,($AC16-1)/Settings!$C$43))) -> 50 | AS16: =IF(OR($V16="",$W16=""),50,MEDIAN(0,100,50+50*($V16-$W16)/Settings!$C$44)) -> 53.009859 | AT16: =IF($AO16="",50,50+(N($AG16)/100)*($AO16-50)) -> 51.609065 | AU16: =IF($B16="","",$B16&"|"&TEXT($A16,"yyyy-mm-dd")) -> MUCOBA|2026-08-10 | AV16: =IF($A16="","",IF(COUNTIFS($A$4:$A16,$A16)=1,1,0)) -> 0
A17: 46244 | B17: NICO | C17: 3550 | E17: 3590 | F17: 3730 | G17: 3500 | H17: =IF($B17="","",IFERROR($E17/$D17-1,"")) | I17: 61151520 | J17: 126 | K17: 17044 | L17: 6476 | M17: 12387 | N17: 221300000000 | O17: DSE Official Daily Market Report | P17: 46265 | Q17: DSE-202608-10to13 | R17: {=IF($B17="","",IFERROR(IF(INDEX('Data Quality'!$U$4:$U$503,ROW()-3)=0,"PENDING",INDEX('Data Quality'!$U$4:$U$503,ROW()-3)),"PENDING"))} -> PASS | S17: =IF($B17="","",IF(N($M17)>0,$L17/$M17,"")) -> 0.52280617 | T17: =IF($B17="","",$L17*$E17) -> 23248840 | U17: =IF($B17="","",$M17*$E17) -> 44469330 | V17: =IF($B17="","",IF(N($N17)>0,$T17/$N17,"")) -> 0.00010505576 | W17: =IF($B17="","",IF(N($N17)>0,$U17/$N17,"")) -> 0.00020094591 | X17: =IF($B17="","",IF(N($J17)>0,$K17/$J17,"")) -> 135.26984 | Y17: =IF($B17="","",IF(N($J17)>0,$I17/$J17,"")) -> 485329.52 | Z17: =IF($B17="","",IF($AK17<=Settings!$C$21,"",IFERROR(AVERAGEIFS($S$4:$S$503,$B$4:$B$503,$B17,$AK$4:$AK$503,">="&$AK17-Settings!$C$21,$AK$4:$AK$503,"<="&$AK17-1),""))) | AA17: =IF(OR($S17="",$Z17="",N($Z17)=0),"",$S17/$Z17-1) | AB17: =IF($B17="","",IF($AK17<=Settings!$C$22,"",IFERROR(AVERAGEIFS($K$4:$K$503,$B$4:$B$503,$B17,$AK$4:$AK$503,">="&$AK17-Settings!$C$22,$AK$4:$AK$503,"<="&$AK17-1),""))) | AC17: =IF(OR($AB17="",N($AB17)=0),"",$K17/$AB17) | AD17: =IF($B17="","",IF($AK17<=Settings!$C$23,"",IFERROR($E17/SUMIFS($E$4:$E$503,$B$4:$B$503,$B17,$AK$4:$AK$503,$AK17-Settings!$C$23)-1,""))) | AE17: =IF($B17="","",IF($AK17<=Settings!$C$22,"",IFERROR($E17/SUMIFS($E$4:$E$503,$B$4:$B$503,$B17,$AK$4:$AK$503,$AK17-Settings!$C$22)-1,""))) | AF17: =IF($B17="","",IF(N($E17)>0,($F17-$G17)/$E17,"")) -> 0.064066852 | AG17: =IF($B17="","",ROUND((MIN(100,100*N($I17)/Settings!$C$27)+MIN(100,100*N($K17)/Settings!$C$28)+MIN(100,100*N($J17)/Settings!$C$29))/3,1)) -> 36.5 | AH17: =IF($B17="","",IF(SUM(Settings!$C$32:$C$37)=0,"",ROUND((Settings!$C$32*$AO17+Settings!$C$33*$AP17+Settings!$C$34*$AQ17+Settings!$C$35*$AR17+Settings!$C$36*$AS17+Settings!$C$37*$AT17)/SUM(Settings!$C$32:$C$37),1))) -> 41.2 | AI17: =IF($B17="","",MAX(0,100-IF(N($N17)>0,0,20)-IF(AND(N($L17)=0,N($M17)=0),15,0)-IF(N($J17)>0,0,10)-IF(N($K17)>0,0,10)-IF($Z17<>"",0,15)-IF($AB17<>"",0,10)-IF($R17="ERROR",20,IF($R17="WARNING",10,0)))) -> 75 | AJ17: =IF($AH17="","",IF($AH17<Settings!$C$46,"Extreme Sell Pressure",IF($AH17<Settings!$C$47,"Sell Pressure",IF($AH17<=Settings!$C$48,"Neutral",IF($AH17<=Settings!$C$49,"Buy Pressure","Extreme Buy Pressure"))))) -> Neutral | AK17: =IF($B17="","",COUNTIFS($B$4:$B$503,$B17,$A$4:$A$503,"<="&$A17)) -> 1 | AL17: =IF($A17="","",YEAR($A17)) -> 2026 | AM17: =IF($A17="","",_xlfn.ISOWEEKNUM($A17)) -> 33 | AN17: =IF($A17="","",MONTH($A17)) -> 8 | AO17: =IF($B17="","",IF(AND(N($L17)=0,N($M17)=0),50,IF(N($M17)=0,100,IF(N($L17)=0,0,MEDIAN(0,100,50+50*LN($S17)/LN(Settings!$C$40)))))) -> 26.608702 | AP17: =IF($AA17="",50,MEDIAN(0,100,50+$AA17*100*Settings!$C$41)) -> 50 | AQ17: =IF($H17="",50,MEDIAN(0,100,50+$H17*100*Settings!$C$42)) -> 50 | AR17: =IF(OR($AC17="",$H17=""),50,MEDIAN(0,100,50+SIGN($H17)*50*MEDIAN(0,1,($AC17-1)/Settings!$C$43))) -> 50 | AS17: =IF(OR($V17="",$W17=""),50,MEDIAN(0,100,50+50*($V17-$W17)/Settings!$C$44)) -> 40.410985 | AT17: =IF($AO17="",50,50+(N($AG17)/100)*($AO17-50)) -> 41.462176 | AU17: =IF($B17="","",$B17&"|"&TEXT($A17,"yyyy-mm-dd")) -> NICO|2026-08-10 | AV17: =IF($A17="","",IF(COUNTIFS($A$4:$A17,$A17)=1,1,0)) -> 0
A18: 46244 | B18: NMB | C18: 17580 | E18: 17600 | F18: 17660 | G18: 17570 | H18: =IF($B18="","",IFERROR($E18/$D18-1,"")) | I18: 1681576840 | J18: 528 | K18: 95563 | L18: 12100 | M18: 20114 | N18: 8800000000000 | O18: DSE Official Daily Market Report | P18: 46265 | Q18: DSE-202608-10to13 | R18: {=IF($B18="","",IFERROR(IF(INDEX('Data Quality'!$U$4:$U$503,ROW()-3)=0,"PENDING",INDEX('Data Quality'!$U$4:$U$503,ROW()-3)),"PENDING"))} -> PASS | S18: =IF($B18="","",IF(N($M18)>0,$L18/$M18,"")) -> 0.60157105 | T18: =IF($B18="","",$L18*$E18) -> 212960000 | U18: =IF($B18="","",$M18*$E18) -> 354006400 | V18: =IF($B18="","",IF(N($N18)>0,$T18/$N18,"")) -> 2.42e-05 | W18: =IF($B18="","",IF(N($N18)>0,$U18/$N18,"")) -> 4.0228e-05 | X18: =IF($B18="","",IF(N($J18)>0,$K18/$J18,"")) -> 180.99053 | Y18: =IF($B18="","",IF(N($J18)>0,$I18/$J18,"")) -> 3184804.6 | Z18: =IF($B18="","",IF($AK18<=Settings!$C$21,"",IFERROR(AVERAGEIFS($S$4:$S$503,$B$4:$B$503,$B18,$AK$4:$AK$503,">="&$AK18-Settings!$C$21,$AK$4:$AK$503,"<="&$AK18-1),""))) | AA18: =IF(OR($S18="",$Z18="",N($Z18)=0),"",$S18/$Z18-1) | AB18: =IF($B18="","",IF($AK18<=Settings!$C$22,"",IFERROR(AVERAGEIFS($K$4:$K$503,$B$4:$B$503,$B18,$AK$4:$AK$503,">="&$AK18-Settings!$C$22,$AK$4:$AK$503,"<="&$AK18-1),""))) | AC18: =IF(OR($AB18="",N($AB18)=0),"",$K18/$AB18) | AD18: =IF($B18="","",IF($AK18<=Settings!$C$23,"",IFERROR($E18/SUMIFS($E$4:$E$503,$B$4:$B$503,$B18,$AK$4:$AK$503,$AK18-Settings!$C$23)-1,""))) | AE18: =IF($B18="","",IF($AK18<=Settings!$C$22,"",IFERROR($E18/SUMIFS($E$4:$E$503,$B$4:$B$503,$B18,$AK$4:$AK$503,$AK18-Settings!$C$22)-1,""))) | AF18: =IF($B18="","",IF(N($E18)>0,($F18-$G18)/$E18,"")) -> 0.0051136364 | AG18: =IF($B18="","",ROUND((MIN(100,100*N($I18)/Settings!$C$27)+MIN(100,100*N($K18)/Settings!$C$28)+MIN(100,100*N($J18)/Settings!$C$29))/3,1)) -> 73 | AH18: =IF($B18="","",IF(SUM(Settings!$C$32:$C$37)=0,"",ROUND((Settings!$C$32*$AO18+Settings!$C$33*$AP18+Settings!$C$34*$AQ18+Settings!$C$35*$AR18+Settings!$C$36*$AS18+Settings!$C$37*$AT18)/SUM(Settings!$C$32:$C$37),1))) -> 43 | AI18: =IF($B18="","",MAX(0,100-IF(N($N18)>0,0,20)-IF(AND(N($L18)=0,N($M18)=0),15,0)-IF(N($J18)>0,0,10)-IF(N($K18)>0,0,10)-IF($Z18<>"",0,15)-IF($AB18<>"",0,10)-IF($R18="ERROR",20,IF($R18="WARNING",10,0)))) -> 75 | AJ18: =IF($AH18="","",IF($AH18<Settings!$C$46,"Extreme Sell Pressure",IF($AH18<Settings!$C$47,"Sell Pressure",IF($AH18<=Settings!$C$48,"Neutral",IF($AH18<=Settings!$C$49,"Buy Pressure","Extreme Buy Pressure"))))) -> Neutral | AK18: =IF($B18="","",COUNTIFS($B$4:$B$503,$B18,$A$4:$A$503,"<="&$A18)) -> 1 | AL18: =IF($A18="","",YEAR($A18)) -> 2026 | AM18: =IF($A18="","",_xlfn.ISOWEEKNUM($A18)) -> 33 | AN18: =IF($A18="","",MONTH($A18)) -> 8 | AO18: =IF($B18="","",IF(AND(N($L18)=0,N($M18)=0),50,IF(N($M18)=0,100,IF(N($L18)=0,0,MEDIAN(0,100,50+50*LN($S18)/LN(Settings!$C$40)))))) -> 31.670176 | AP18: =IF($AA18="",50,MEDIAN(0,100,50+$AA18*100*Settings!$C$41)) -> 50 | AQ18: =IF($H18="",50,MEDIAN(0,100,50+$H18*100*Settings!$C$42)) -> 50 | AR18: =IF(OR($AC18="",$H18=""),50,MEDIAN(0,100,50+SIGN($H18)*50*MEDIAN(0,1,($AC18-1)/Settings!$C$43))) -> 50 | AS18: =IF(OR($V18="",$W18=""),50,MEDIAN(0,100,50+50*($V18-$W18)/Settings!$C$44)) -> 48.3972 | AT18: =IF($AO18="",50,50+(N($AG18)/100)*($AO18-50)) -> 36.619228 | AU18: =IF($B18="","",$B18&"|"&TEXT($A18,"yyyy-mm-dd")) -> NMB|2026-08-10 | AV18: =IF($A18="","",IF(COUNTIFS($A$4:$A18,$A18)=1,1,0)) -> 0
A19: 46244 | B19: NMG | C19: 265 | E19: 265 | H19: =IF($B19="","",IFERROR($E19/$D19-1,"")) | I19: 0 | J19: 0 | K19: 0 | L19: 2843 | M19: 0 | N19: 49960000000 | O19: DSE Official Daily Market Report | P19: 46265 | Q19: DSE-202608-10to13 | R19: {=IF($B19="","",IFERROR(IF(INDEX('Data Quality'!$U$4:$U$503,ROW()-3)=0,"PENDING",INDEX('Data Quality'!$U$4:$U$503,ROW()-3)),"PENDING"))} -> PASS | S19: =IF($B19="","",IF(N($M19)>0,$L19/$M19,"")) | T19: =IF($B19="","",$L19*$E19) -> 753395 | U19: =IF($B19="","",$M19*$E19) -> 0 | V19: =IF($B19="","",IF(N($N19)>0,$T19/$N19,"")) -> 1.5079964e-05 | W19: =IF($B19="","",IF(N($N19)>0,$U19/$N19,"")) -> 0 | X19: =IF($B19="","",IF(N($J19)>0,$K19/$J19,"")) | Y19: =IF($B19="","",IF(N($J19)>0,$I19/$J19,"")) | Z19: =IF($B19="","",IF($AK19<=Settings!$C$21,"",IFERROR(AVERAGEIFS($S$4:$S$503,$B$4:$B$503,$B19,$AK$4:$AK$503,">="&$AK19-Settings!$C$21,$AK$4:$AK$503,"<="&$AK19-1),""))) | AA19: =IF(OR($S19="",$Z19="",N($Z19)=0),"",$S19/$Z19-1) | AB19: =IF($B19="","",IF($AK19<=Settings!$C$22,"",IFERROR(AVERAGEIFS($K$4:$K$503,$B$4:$B$503,$B19,$AK$4:$AK$503,">="&$AK19-Settings!$C$22,$AK$4:$AK$503,"<="&$AK19-1),""))) | AC19: =IF(OR($AB19="",N($AB19)=0),"",$K19/$AB19) | AD19: =IF($B19="","",IF($AK19<=Settings!$C$23,"",IFERROR($E19/SUMIFS($E$4:$E$503,$B$4:$B$503,$B19,$AK$4:$AK$503,$AK19-Settings!$C$23)-1,""))) | AE19: =IF($B19="","",IF($AK19<=Settings!$C$22,"",IFERROR($E19/SUMIFS($E$4:$E$503,$B$4:$B$503,$B19,$AK$4:$AK$503,$AK19-Settings!$C$22)-1,""))) | AF19: =IF($B19="","",IF(N($E19)>0,($F19-$G19)/$E19,"")) -> 0 | AG19: =IF($B19="","",ROUND((MIN(100,100*N($I19)/Settings!$C$27)+MIN(100,100*N($K19)/Settings!$C$28)+MIN(100,100*N($J19)/Settings!$C$29))/3,1)) -> 0 | AH19: =IF($B19="","",IF(SUM(Settings!$C$32:$C$37)=0,"",ROUND((Settings!$C$32*$AO19+Settings!$C$33*$AP19+Settings!$C$34*$AQ19+Settings!$C$35*$AR19+Settings!$C$36*$AS19+Settings!$C$37*$AT19)/SUM(Settings!$C$32:$C$37),1))) -> 65.2 | AI19: =IF($B19="","",MAX(0,100-IF(N($N19)>0,0,20)-IF(AND(N($L19)=0,N($M19)=0),15,0)-IF(N($J19)>0,0,10)-IF(N($K19)>0,0,10)-IF($Z19<>"",0,15)-IF($AB19<>"",0,10)-IF($R19="ERROR",20,IF($R19="WARNING",10,0)))) -> 55 | AJ19: =IF($AH19="","",IF($AH19<Settings!$C$46,"Extreme Sell Pressure",IF($AH19<Settings!$C$47,"Sell Pressure",IF($AH19<=Settings!$C$48,"Neutral",IF($AH19<=Settings!$C$49,"Buy Pressure","Extreme Buy Pressure"))))) -> Buy Pressure | AK19: =IF($B19="","",COUNTIFS($B$4:$B$503,$B19,$A$4:$A$503,"<="&$A19)) -> 1 | AL19: =IF($A19="","",YEAR($A19)) -> 2026 | AM19: =IF($A19="","",_xlfn.ISOWEEKNUM($A19)) -> 33 | AN19: =IF($A19="","",MONTH($A19)) -> 8 | AO19: =IF($B19="","",IF(AND(N($L19)=0,N($M19)=0),50,IF(N($M19)=0,100,IF(N($L19)=0,0,MEDIAN(0,100,50+50*LN($S19)/LN(Settings!$C$40)))))) -> 100 | AP19: =IF($AA19="",50,MEDIAN(0,100,50+$AA19*100*Settings!$C$41)) -> 50 | AQ19: =IF($H19="",50,MEDIAN(0,100,50+$H19*100*Settings!$C$42)) -> 50 | AR19: =IF(OR($AC19="",$H19=""),50,MEDIAN(0,100,50+SIGN($H19)*50*MEDIAN(0,1,($AC19-1)/Settings!$C$43))) -> 50 | AS19: =IF(OR($V19="",$W19=""),50,MEDIAN(0,100,50+50*($V19-$W19)/Settings!$C$44)) -> 51.507996 | AT19: =IF($AO19="",50,50+(N($AG19)/100)*($AO19-50)) -> 50 | AU19: =IF($B19="","",$B19&"|"&TEXT($A19,"yyyy-mm-dd")) -> NMG|2026-08-10 | AV19: =IF($A19="","",IF(COUNTIFS($A$4:$A19,$A19)=1,1,0)) -> 0
A20: 46244 | B20: PAL | C20: 310 | E20: 310 | F20: 310 | G20: 300 | H20: =IF($B20="","",IFERROR($E20/$D20-1,"")) | I20: 1771480 | J20: 58 | K20: 5749 | L20: 4655 | M20: 15362 | N20: 49750000000 | O20: DSE Official Daily Market Report | P20: 46265 | Q20: DSE-202608-10to13 | R20: {=IF($B20="","",IFERROR(IF(INDEX('Data Quality'!$U$4:$U$503,ROW()-3)=0,"PENDING",INDEX('Data Quality'!$U$4:$U$503,ROW()-3)),"PENDING"))} -> PASS | S20: =IF($B20="","",IF(N($M20)>0,$L20/$M20,"")) -> 0.30302044 | T20: =IF($B20="","",$L20*$E20) -> 1443050 | U20: =IF($B20="","",$M20*$E20) -> 4762220 | V20: =IF($B20="","",IF(N($N20)>0,$T20/$N20,"")) -> 2.900603e-05 | W20: =IF($B20="","",IF(N($N20)>0,$U20/$N20,"")) -> 9.5723015e-05 | X20: =IF($B20="","",IF(N($J20)>0,$K20/$J20,"")) -> 99.12069 | Y20: =IF($B20="","",IF(N($J20)>0,$I20/$J20,"")) -> 30542.759 | Z20: =IF($B20="","",IF($AK20<=Settings!$C$21,"",IFERROR(AVERAGEIFS($S$4:$S$503,$B$4:$B$503,$B20,$AK$4:$AK$503,">="&$AK20-Settings!$C$21,$AK$4:$AK$503,"<="&$AK20-1),""))) | AA20: =IF(OR($S20="",$Z20="",N($Z20)=0),"",$S20/$Z20-1) | AB20: =IF($B20="","",IF($AK20<=Settings!$C$22,"",IFERROR(AVERAGEIFS($K$4:$K$503,$B$4:$B$503,$B20,$AK$4:$AK$503,">="&$AK20-Settings!$C$22,$AK$4:$AK$503,"<="&$AK20-1),""))) | AC20: =IF(OR($AB20="",N($AB20)=0),"",$K20/$AB20) | AD20: =IF($B20="","",IF($AK20<=Settings!$C$23,"",IFERROR($E20/SUMIFS($E$4:$E$503,$B$4:$B$503,$B20,$AK$4:$AK$503,$AK20-Settings!$C$23)-1,""))) | AE20: =IF($B20="","",IF($AK20<=Settings!$C$22,"",IFERROR($E20/SUMIFS($E$4:$E$503,$B$4:$B$503,$B20,$AK$4:$AK$503,$AK20-Settings!$C$22)-1,""))) | AF20: =IF($B20="","",IF(N($E20)>0,($F20-$G20)/$E20,"")) -> 0.032258065 | AG20: =IF($B20="","",ROUND((MIN(100,100*N($I20)/Settings!$C$27)+MIN(100,100*N($K20)/Settings!$C$28)+MIN(100,100*N($J20)/Settings!$C$29))/3,1)) -> 19.8 | AH20: =IF($B20="","",IF(SUM(Settings!$C$32:$C$37)=0,"",ROUND((Settings!$C$32*$AO20+Settings!$C$33*$AP20+Settings!$C$34*$AQ20+Settings!$C$35*$AR20+Settings!$C$36*$AS20+Settings!$C$37*$AT20)/SUM(Settings!$C$32:$C$37),1))) -> 35.6 | AI20: =IF($B20="","",MAX(0,100-IF(N($N20)>0,0,20)-IF(AND(N($L20)=0,N($M20)=0),15,0)-IF(N($J20)>0,0,10)-IF(N($K20)>0,0,10)-IF($Z20<>"",0,15)-IF($AB20<>"",0,10)-IF($R20="ERROR",20,IF($R20="WARNING",10,0)))) -> 75 | AJ20: =IF($AH20="","",IF($AH20<Settings!$C$46,"Extreme Sell Pressure",IF($AH20<Settings!$C$47,"Sell Pressure",IF($AH20<=Settings!$C$48,"Neutral",IF($AH20<=Settings!$C$49,"Buy Pressure","Extreme Buy Pressure"))))) -> Sell Pressure | AK20: =IF($B20="","",COUNTIFS($B$4:$B$503,$B20,$A$4:$A$503,"<="&$A20)) -> 1 | AL20: =IF($A20="","",YEAR($A20)) -> 2026 | AM20: =IF($A20="","",_xlfn.ISOWEEKNUM($A20)) -> 33 | AN20: =IF($A20="","",MONTH($A20)) -> 8 | AO20: =IF($B20="","",IF(AND(N($L20)=0,N($M20)=0),50,IF(N($M20)=0,100,IF(N($L20)=0,0,MEDIAN(0,100,50+50*LN($S20)/LN(Settings!$C$40)))))) -> 6.9371755 | AP20: =IF($AA20="",50,MEDIAN(0,100,50+$AA20*100*Settings!$C$41)) -> 50 | AQ20: =IF($H20="",50,MEDIAN(0,100,50+$H20*100*Settings!$C$42)) -> 50 | AR20: =IF(OR($AC20="",$H20=""),50,MEDIAN(0,100,50+SIGN($H20)*50*MEDIAN(0,1,($AC20-1)/Settings!$C$43))) -> 50 | AS20: =IF(OR($V20="",$W20=""),50,MEDIAN(0,100,50+50*($V20-$W20)/Settings!$C$44)) -> 43.328302 | AT20: =IF($AO20="",50,50+(N($AG20)/100)*($AO20-50)) -> 41.473561 | AU20: =IF($B20="","",$B20&"|"&TEXT($A20,"yyyy-mm-dd")) -> PAL|2026-08-10 | AV20: =IF($A20="","",IF(COUNTIFS($A$4:$A20,$A20)=1,1,0)) -> 0
A21: 46244 | B21: SWALA | C21: 450 | E21: 450 | H21: =IF($B21="","",IFERROR($E21/$D21-1,"")) | I21: 0 | J21: 0 | K21: 0 | L21: 0 | M21: 0 | N21: 47790000000 | O21: DSE Official Daily Market Report | P21: 46265 | Q21: DSE-202608-10to13 | R21: {=IF($B21="","",IFERROR(IF(INDEX('Data Quality'!$U$4:$U$503,ROW()-3)=0,"PENDING",INDEX('Data Quality'!$U$4:$U$503,ROW()-3)),"PENDING"))} -> WARNING | S21: =IF($B21="","",IF(N($M21)>0,$L21/$M21,"")) | T21: =IF($B21="","",$L21*$E21) -> 0 | U21: =IF($B21="","",$M21*$E21) -> 0 | V21: =IF($B21="","",IF(N($N21)>0,$T21/$N21,"")) -> 0 | W21: =IF($B21="","",IF(N($N21)>0,$U21/$N21,"")) -> 0 | X21: =IF($B21="","",IF(N($J21)>0,$K21/$J21,"")) | Y21: =IF($B21="","",IF(N($J21)>0,$I21/$J21,"")) | Z21: =IF($B21="","",IF($AK21<=Settings!$C$21,"",IFERROR(AVERAGEIFS($S$4:$S$503,$B$4:$B$503,$B21,$AK$4:$AK$503,">="&$AK21-Settings!$C$21,$AK$4:$AK$503,"<="&$AK21-1),""))) | AA21: =IF(OR($S21="",$Z21="",N($Z21)=0),"",$S21/$Z21-1) | AB21: =IF($B21="","",IF($AK21<=Settings!$C$22,"",IFERROR(AVERAGEIFS($K$4:$K$503,$B$4:$B$503,$B21,$AK$4:$AK$503,">="&$AK21-Settings!$C$22,$AK$4:$AK$503,"<="&$AK21-1),""))) | AC21: =IF(OR($AB21="",N($AB21)=0),"",$K21/$AB21) | AD21: =IF($B21="","",IF($AK21<=Settings!$C$23,"",IFERROR($E21/SUMIFS($E$4:$E$503,$B$4:$B$503,$B21,$AK$4:$AK$503,$AK21-Settings!$C$23)-1,""))) | AE21: =IF($B21="","",IF($AK21<=Settings!$C$22,"",IFERROR($E21/SUMIFS($E$4:$E$503,$B$4:$B$503,$B21,$AK$4:$AK$503,$AK21-Settings!$C$22)-1,""))) | AF21: =IF($B21="","",IF(N($E21)>0,($F21-$G21)/$E21,"")) -> 0 | AG21: =IF($B21="","",ROUND((MIN(100,100*N($I21)/Settings!$C$27)+MIN(100,100*N($K21)/Settings!$C$28)+MIN(100,100*N($J21)/Settings!$C$29))/3,1)) -> 0 | AH21: =IF($B21="","",IF(SUM(Settings!$C$32:$C$37)=0,"",ROUND((Settings!$C$32*$AO21+Settings!$C$33*$AP21+Settings!$C$34*$AQ21+Settings!$C$35*$AR21+Settings!$C$36*$AS21+Settings!$C$37*$AT21)/SUM(Settings!$C$32:$C$37),1))) -> 50 | AI21: =IF($B21="","",MAX(0,100-IF(N($N21)>0,0,20)-IF(AND(N($L21)=0,N($M21)=0),15,0)-IF(N($J21)>0,0,10)-IF(N($K21)>0,0,10)-IF($Z21<>"",0,15)-IF($AB21<>"",0,10)-IF($R21="ERROR",20,IF($R21="WARNING",10,0)))) -> 30 | AJ21: =IF($AH21="","",IF($AH21<Settings!$C$46,"Extreme Sell Pressure",IF($AH21<Settings!$C$47,"Sell Pressure",IF($AH21<=Settings!$C$48,"Neutral",IF($AH21<=Settings!$C$49,"Buy Pressure","Extreme Buy Pressure"))))) -> Neutral | AK21: =IF($B21="","",COUNTIFS($B$4:$B$503,$B21,$A$4:$A$503,"<="&$A21)) -> 1 | AL21: =IF($A21="","",YEAR($A21)) -> 2026 | AM21: =IF($A21="","",_xlfn.ISOWEEKNUM($A21)) -> 33 | AN21: =IF($A21="","",MONTH($A21)) -> 8 | AO21: =IF($B21="","",IF(AND(N($L21)=0,N($M21)=0),50,IF(N($M21)=0,100,IF(N($L21)=0,0,MEDIAN(0,100,50+50*LN($S21)/LN(Settings!$C$40)))))) -> 50 | AP21: =IF($AA21="",50,MEDIAN(0,100,50+$AA21*100*Settings!$C$41)) -> 50 | AQ21: =IF($H21="",50,MEDIAN(0,100,50+$H21*100*Settings!$C$42)) -> 50 | AR21: =IF(OR($AC21="",$H21=""),50,MEDIAN(0,100,50+SIGN($H21)*50*MEDIAN(0,1,($AC21-1)/Settings!$C$43))) -> 50 | AS21: =IF(OR($V21="",$W21=""),50,MEDIAN(0,100,50+50*($V21-$W21)/Settings!$C$44)) -> 50 | AT21: =IF($AO21="",50,50+(N($AG21)/100)*($AO21-50)) -> 50 | AU21: =IF($B21="","",$B21&"|"&TEXT($A21,"yyyy-mm-dd")) -> SWALA|2026-08-10 | AV21: =IF($A21="","",IF(COUNTIFS($A$4:$A21,$A21)=1,1,0)) -> 0
A22: 46244 | B22: SWIS | C22: 2690 | E22: 2620 | F22: 2690 | G22: 2550 | H22: =IF($B22="","",IFERROR($E22/$D22-1,"")) | I22: 3429910 | J22: 24 | K22: 1305 | L22: 10151 | M22: 21238 | N22: 94320000000 | O22: DSE Official Daily Market Report | P22: 46265 | Q22: DSE-202608-10to13 | R22: {=IF($B22="","",IFERROR(IF(INDEX('Data Quality'!$U$4:$U$503,ROW()-3)=0,"PENDING",INDEX('Data Quality'!$U$4:$U$503,ROW()-3)),"PENDING"))} -> PASS | S22: =IF($B22="","",IF(N($M22)>0,$L22/$M22,"")) -> 0.47796403 | T22: =IF($B22="","",$L22*$E22) -> 26595620 | U22: =IF($B22="","",$M22*$E22) -> 55643560 | V22: =IF($B22="","",IF(N($N22)>0,$T22/$N22,"")) -> 0.00028197222 | W22: =IF($B22="","",IF(N($N22)>0,$U22/$N22,"")) -> 0.00058994444 | X22: =IF($B22="","",IF(N($J22)>0,$K22/$J22,"")) -> 54.375 | Y22: =IF($B22="","",IF(N($J22)>0,$I22/$J22,"")) -> 142912.92 | Z22: =IF($B22="","",IF($AK22<=Settings!$C$21,"",IFERROR(AVERAGEIFS($S$4:$S$503,$B$4:$B$503,$B22,$AK$4:$AK$503,">="&$AK22-Settings!$C$21,$AK$4:$AK$503,"<="&$AK22-1),""))) | AA22: =IF(OR($S22="",$Z22="",N($Z22)=0),"",$S22/$Z22-1) | AB22: =IF($B22="","",IF($AK22<=Settings!$C$22,"",IFERROR(AVERAGEIFS($K$4:$K$503,$B$4:$B$503,$B22,$AK$4:$AK$503,">="&$AK22-Settings!$C$22,$AK$4:$AK$503,"<="&$AK22-1),""))) | AC22: =IF(OR($AB22="",N($AB22)=0),"",$K22/$AB22) | AD22: =IF($B22="","",IF($AK22<=Settings!$C$23,"",IFERROR($E22/SUMIFS($E$4:$E$503,$B$4:$B$503,$B22,$AK$4:$AK$503,$AK22-Settings!$C$23)-1,""))) | AE22: =IF($B22="","",IF($AK22<=Settings!$C$22,"",IFERROR($E22/SUMIFS($E$4:$E$503,$B$4:$B$503,$B22,$AK$4:$AK$503,$AK22-Settings!$C$22)-1,""))) | AF22: =IF($B22="","",IF(N($E22)>0,($F22-$G22)/$E22,"")) -> 0.053435115 | AG22: =IF($B22="","",ROUND((MIN(100,100*N($I22)/Settings!$C$27)+MIN(100,100*N($K22)/Settings!$C$28)+MIN(100,100*N($J22)/Settings!$C$29))/3,1)) -> 8.2 | AH22: =IF($B22="","",IF(SUM(Settings!$C$32:$C$37)=0,"",ROUND((Settings!$C$32*$AO22+Settings!$C$33*$AP22+Settings!$C$34*$AQ22+Settings!$C$35*$AR22+Settings!$C$36*$AS22+Settings!$C$37*$AT22)/SUM(Settings!$C$32:$C$37),1))) -> 38.7 | AI22: =IF($B22="","",MAX(0,100-IF(N($N22)>0,0,20)-IF(AND(N($L22)=0,N($M22)=0),15,0)-IF(N($J22)>0,0,10)-IF(N($K22)>0,0,10)-IF($Z22<>"",0,15)-IF($AB22<>"",0,10)-IF($R22="ERROR",20,IF($R22="WARNING",10,0)))) -> 75 | AJ22: =IF($AH22="","",IF($AH22<Settings!$C$46,"Extreme Sell Pressure",IF($AH22<Settings!$C$47,"Sell Pressure",IF($AH22<=Settings!$C$48,"Neutral",IF($AH22<=Settings!$C$49,"Buy Pressure","Extreme Buy Pressure"))))) -> Sell Pressure | AK22: =IF($B22="","",COUNTIFS($B$4:$B$503,$B22,$A$4:$A$503,"<="&$A22)) -> 1 | AL22: =IF($A22="","",YEAR($A22)) -> 2026 | AM22: =IF($A22="","",_xlfn.ISOWEEKNUM($A22)) -> 33 | AN22: =IF($A22="","",MONTH($A22)) -> 8 | AO22: =IF($B22="","",IF(AND(N($L22)=0,N($M22)=0),50,IF(N($M22)=0,100,IF(N($L22)=0,0,MEDIAN(0,100,50+50*LN($S22)/LN(Settings!$C$40)))))) -> 23.374349 | AP22: =IF($AA22="",50,MEDIAN(0,100,50+$AA22*100*Settings!$C$41)) -> 50 | AQ22: =IF($H22="",50,MEDIAN(0,100,50+$H22*100*Settings!$C$42)) -> 50 | AR22: =IF(OR($AC22="",$H22=""),50,MEDIAN(0,100,50+SIGN($H22)*50*MEDIAN(0,1,($AC22-1)/Settings!$C$43))) -> 50 | AS22: =IF(OR($V22="",$W22=""),50,MEDIAN(0,100,50+50*($V22-$W22)/Settings!$C$44)) -> 19.202778 | AT22: =IF($AO22="",50,50+(N($AG22)/100)*($AO22-50)) -> 47.816697 | AU22: =IF($B22="","",$B22&"|"&TEXT($A22,"yyyy-mm-dd")) -> SWIS|2026-08-10 | AV22: =IF($A22="","",IF(COUNTIFS($A$4:$A22,$A22)=1,1,0)) -> 0
A23: 46244 | B23: TBL | C23: 10000 | E23: 9950 | F23: 10110 | G23: 9950 | H23: =IF($B23="","",IFERROR($E23/$D23-1,"")) | I23: 10970760 | J23: 23 | K23: 1100 | L23: 352 | M23: 944 | N23: 2935810000000 | O23: DSE Official Daily Market Report | P23: 46265 | Q23: DSE-202608-10to13 | R23: {=IF($B23="","",IFERROR(IF(INDEX('Data Quality'!$U$4:$U$503,ROW()-3)=0,"PENDING",INDEX('Data Quality'!$U$4:$U$503,ROW()-3)),"PENDING"))} -> PASS | S23: =IF($B23="","",IF(N($M23)>0,$L23/$M23,"")) -> 0.37288136 | T23: =IF($B23="","",$L23*$E23) -> 3502400 | U23: =IF($B23="","",$M23*$E23) -> 9392800 | V23: =IF($B23="","",IF(N($N23)>0,$T23/$N23,"")) -> 1.1929927e-06 | W23: =IF($B23="","",IF(N($N23)>0,$U23/$N23,"")) -> 3.1993896e-06 | X23: =IF($B23="","",IF(N($J23)>0,$K23/$J23,"")) -> 47.826087 | Y23: =IF($B23="","",IF(N($J23)>0,$I23/$J23,"")) -> 476989.57 | Z23: =IF($B23="","",IF($AK23<=Settings!$C$21,"",IFERROR(AVERAGEIFS($S$4:$S$503,$B$4:$B$503,$B23,$AK$4:$AK$503,">="&$AK23-Settings!$C$21,$AK$4:$AK$503,"<="&$AK23-1),""))) | AA23: =IF(OR($S23="",$Z23="",N($Z23)=0),"",$S23/$Z23-1) | AB23: =IF($B23="","",IF($AK23<=Settings!$C$22,"",IFERROR(AVERAGEIFS($K$4:$K$503,$B$4:$B$503,$B23,$AK$4:$AK$503,">="&$AK23-Settings!$C$22,$AK$4:$AK$503,"<="&$AK23-1),""))) | AC23: =IF(OR($AB23="",N($AB23)=0),"",$K23/$AB23) | AD23: =IF($B23="","",IF($AK23<=Settings!$C$23,"",IFERROR($E23/SUMIFS($E$4:$E$503,$B$4:$B$503,$B23,$AK$4:$AK$503,$AK23-Settings!$C$23)-1,""))) | AE23: =IF($B23="","",IF($AK23<=Settings!$C$22,"",IFERROR($E23/SUMIFS($E$4:$E$503,$B$4:$B$503,$B23,$AK$4:$AK$503,$AK23-Settings!$C$22)-1,""))) | AF23: =IF($B23="","",IF(N($E23)>0,($F23-$G23)/$E23,"")) -> 0.016080402 | AG23: =IF($B23="","",ROUND((MIN(100,100*N($I23)/Settings!$C$27)+MIN(100,100*N($K23)/Settings!$C$28)+MIN(100,100*N($J23)/Settings!$C$29))/3,1)) -> 8.1 | AH23: =IF($B23="","",IF(SUM(Settings!$C$32:$C$37)=0,"",ROUND((Settings!$C$32*$AO23+Settings!$C$33*$AP23+Settings!$C$34*$AQ23+Settings!$C$35*$AR23+Settings!$C$36*$AS23+Settings!$C$37*$AT23)/SUM(Settings!$C$32:$C$37),1))) -> 39 | AI23: =IF($B23="","",MAX(0,100-IF(N($N23)>0,0,20)-IF(AND(N($L23)=0,N($M23)=0),15,0)-IF(N($J23)>0,0,10)-IF(N($K23)>0,0,10)-IF($Z23<>"",0,15)-IF($AB23<>"",0,10)-IF($R23="ERROR",20,IF($R23="WARNING",10,0)))) -> 75 | AJ23: =IF($AH23="","",IF($AH23<Settings!$C$46,"Extreme Sell Pressure",IF($AH23<Settings!$C$47,"Sell Pressure",IF($AH23<=Settings!$C$48,"Neutral",IF($AH23<=Settings!$C$49,"Buy Pressure","Extreme Buy Pressure"))))) -> Sell Pressure | AK23: =IF($B23="","",COUNTIFS($B$4:$B$503,$B23,$A$4:$A$503,"<="&$A23)) -> 1 | AL23: =IF($A23="","",YEAR($A23)) -> 2026 | AM23: =IF($A23="","",_xlfn.ISOWEEKNUM($A23)) -> 33 | AN23: =IF($A23="","",MONTH($A23)) -> 8 | AO23: =IF($B23="","",IF(AND(N($L23)=0,N($M23)=0),50,IF(N($M23)=0,100,IF(N($L23)=0,0,MEDIAN(0,100,50+50*LN($S23)/LN(Settings!$C$40)))))) -> 14.419714 | AP23: =IF($AA23="",50,MEDIAN(0,100,50+$AA23*100*Settings!$C$41)) -> 50 | AQ23: =IF($H23="",50,MEDIAN(0,100,50+$H23*100*Settings!$C$42)) -> 50 | AR23: =IF(OR($AC23="",$H23=""),50,MEDIAN(0,100,50+SIGN($H23)*50*MEDIAN(0,1,($AC23-1)/Settings!$C$43))) -> 50 | AS23: =IF(OR($V23="",$W23=""),50,MEDIAN(0,100,50+50*($V23-$W23)/Settings!$C$44)) -> 49.79936 | AT23: =IF($AO23="",50,50+(N($AG23)/100)*($AO23-50)) -> 47.117997 | AU23: =IF($B23="","",$B23&"|"&TEXT($A23,"yyyy-mm-dd")) -> TBL|2026-08-10 | AV23: =IF($A23="","",IF(COUNTIFS($A$4:$A23,$A23)=1,1,0)) -> 0
A24: 46244 | B24: TCC | C24: 12300 | E24: 12500 | F24: 12500 | G24: 12500 | H24: =IF($B24="","",IFERROR($E24/$D24-1,"")) | I24: 20175000 | J24: 13 | K24: 1614 | L24: 279 | M24: 0 | N24: 1250000000000 | O24: DSE Official Daily Market Report | P24: 46265 | Q24: DSE-202608-10to13 | R24: {=IF($B24="","",IFERROR(IF(INDEX('Data Quality'!$U$4:$U$503,ROW()-3)=0,"PENDING",INDEX('Data Quality'!$U$4:$U$503,ROW()-3)),"PENDING"))} -> PASS | S24: =IF($B24="","",IF(N($M24)>0,$L24/$M24,"")) | T24: =IF($B24="","",$L24*$E24) -> 3487500 | U24: =IF($B24="","",$M24*$E24) -> 0 | V24: =IF($B24="","",IF(N($N24)>0,$T24/$N24,"")) -> 2.79e-06 | W24: =IF($B24="","",IF(N($N24)>0,$U24/$N24,"")) -> 0 | X24: =IF($B24="","",IF(N($J24)>0,$K24/$J24,"")) -> 124.15385 | Y24: =IF($B24="","",IF(N($J24)>0,$I24/$J24,"")) -> 1551923.1 | Z24: =IF($B24="","",IF($AK24<=Settings!$C$21,"",IFERROR(AVERAGEIFS($S$4:$S$503,$B$4:$B$503,$B24,$AK$4:$AK$503,">="&$AK24-Settings!$C$21,$AK$4:$AK$503,"<="&$AK24-1),""))) | AA24: =IF(OR($S24="",$Z24="",N($Z24)=0),"",$S24/$Z24-1) | AB24: =IF($B24="","",IF($AK24<=Settings!$C$22,"",IFERROR(AVERAGEIFS($K$4:$K$503,$B$4:$B$503,$B24,$AK$4:$AK$503,">="&$AK24-Settings!$C$22,$AK$4:$AK$503,"<="&$AK24-1),""))) | AC24: =IF(OR($AB24="",N($AB24)=0),"",$K24/$AB24) | AD24: =IF($B24="","",IF($AK24<=Settings!$C$23,"",IFERROR($E24/SUMIFS($E$4:$E$503,$B$4:$B$503,$B24,$AK$4:$AK$503,$AK24-Settings!$C$23)-1,""))) | AE24: =IF($B24="","",IF($AK24<=Settings!$C$22,"",IFERROR($E24/SUMIFS($E$4:$E$503,$B$4:$B$503,$B24,$AK$4:$AK$503,$AK24-Settings!$C$22)-1,""))) | AF24: =IF($B24="","",IF(N($E24)>0,($F24-$G24)/$E24,"")) -> 0 | AG24: =IF($B24="","",ROUND((MIN(100,100*N($I24)/Settings!$C$27)+MIN(100,100*N($K24)/Settings!$C$28)+MIN(100,100*N($J24)/Settings!$C$29))/3,1)) -> 5.1 | AH24: =IF($B24="","",IF(SUM(Settings!$C$32:$C$37)=0,"",ROUND((Settings!$C$32*$AO24+Settings!$C$33*$AP24+Settings!$C$34*$AQ24+Settings!$C$35*$AR24+Settings!$C$36*$AS24+Settings!$C$37*$AT24)/SUM(Settings!$C$32:$C$37),1))) -> 65.3 | AI24: =IF($B24="","",MAX(0,100-IF(N($N24)>0,0,20)-IF(AND(N($L24)=0,N($M24)=0),15,0)-IF(N($J24)>0,0,10)-IF(N($K24)>0,0,10)-IF($Z24<>"",0,15)-IF($AB24<>"",0,10)-IF($R24="ERROR",20,IF($R24="WARNING",10,0)))) -> 75 | AJ24: =IF($AH24="","",IF($AH24<Settings!$C$46,"Extreme Sell Pressure",IF($AH24<Settings!$C$47,"Sell Pressure",IF($AH24<=Settings!$C$48,"Neutral",IF($AH24<=Settings!$C$49,"Buy Pressure","Extreme Buy Pressure"))))) -> Buy Pressure | AK24: =IF($B24="","",COUNTIFS($B$4:$B$503,$B24,$A$4:$A$503,"<="&$A24)) -> 1 | AL24: =IF($A24="","",YEAR($A24)) -> 2026 | AM24: =IF($A24="","",_xlfn.ISOWEEKNUM($A24)) -> 33 | AN24: =IF($A24="","",MONTH($A24)) -> 8 | AO24: =IF($B24="","",IF(AND(N($L24)=0,N($M24)=0),50,IF(N($M24)=0,100,IF(N($L24)=0,0,MEDIAN(0,100,50+50*LN($S24)/LN(Settings!$C$40)))))) -> 100 | AP24: =IF($AA24="",50,MEDIAN(0,100,50+$AA24*100*Settings!$C$41)) -> 50 | AQ24: =IF($H24="",50,MEDIAN(0,100,50+$H24*100*Settings!$C$42)) -> 50 | AR24: =IF(OR($AC24="",$H24=""),50,MEDIAN(0,100,50+SIGN($H24)*50*MEDIAN(0,1,($AC24-1)/Settings!$C$43))) -> 50 | AS24: =IF(OR($V24="",$W24=""),50,MEDIAN(0,100,50+50*($V24-$W24)/Settings!$C$44)) -> 50.279 | AT24: =IF($AO24="",50,50+(N($AG24)/100)*($AO24-50)) -> 52.55 | AU24: =IF($B24="","",$B24&"|"&TEXT($A24,"yyyy-mm-dd")) -> TCC|2026-08-10 | AV24: =IF($A24="","",IF(COUNTIFS($A$4:$A24,$A24)=1,1,0)) -> 0
A25: 46244 | B25: TCCL | C25: 3710 | E25: 3850 | F25: 4000 | G25: 3620 | H25: =IF($B25="","",IFERROR($E25/$D25-1,"")) | I25: 7866260 | J25: 21 | K25: 2046 | L25: 20117 | M25: 17999 | N25: 735400000000 | O25: DSE Official Daily Market Report | P25: 46265 | Q25: DSE-202608-10to13 | R25: {=IF($B25="","",IFERROR(IF(INDEX('Data Quality'!$U$4:$U$503,ROW()-3)=0,"PENDING",INDEX('Data Quality'!$U$4:$U$503,ROW()-3)),"PENDING"))} -> PASS | S25: =IF($B25="","",IF(N($M25)>0,$L25/$M25,"")) -> 1.1176732 | T25: =IF($B25="","",$L25*$E25) -> 77450450 | U25: =IF($B25="","",$M25*$E25) -> 69296150 | V25: =IF($B25="","",IF(N($N25)>0,$T25/$N25,"")) -> 0.00010531745 | W25: =IF($B25="","",IF(N($N25)>0,$U25/$N25,"")) -> 9.4229195e-05 | X25: =IF($B25="","",IF(N($J25)>0,$K25/$J25,"")) -> 97.428571 | Y25: =IF($B25="","",IF(N($J25)>0,$I25/$J25,"")) -> 374583.81 | Z25: =IF($B25="","",IF($AK25<=Settings!$C$21,"",IFERROR(AVERAGEIFS($S$4:$S$503,$B$4:$B$503,$B25,$AK$4:$AK$503,">="&$AK25-Settings!$C$21,$AK$4:$AK$503,"<="&$AK25-1),""))) | AA25: =IF(OR($S25="",$Z25="",N($Z25)=0),"",$S25/$Z25-1) | AB25: =IF($B25="","",IF($AK25<=Settings!$C$22,"",IFERROR(AVERAGEIFS($K$4:$K$503,$B$4:$B$503,$B25,$AK$4:$AK$503,">="&$AK25-Settings!$C$22,$AK$4:$AK$503,"<="&$AK25-1),""))) | AC25: =IF(OR($AB25="",N($AB25)=0),"",$K25/$AB25) | AD25: =IF($B25="","",IF($AK25<=Settings!$C$23,"",IFERROR($E25/SUMIFS($E$4:$E$503,$B$4:$B$503,$B25,$AK$4:$AK$503,$AK25-Settings!$C$23)-1,""))) | AE25: =IF($B25="","",IF($AK25<=Settings!$C$22,"",IFERROR($E25/SUMIFS($E$4:$E$503,$B$4:$B$503,$B25,$AK$4:$AK$503,$AK25-Settings!$C$22)-1,""))) | AF25: =IF($B25="","",IF(N($E25)>0,($F25-$G25)/$E25,"")) -> 0.098701299 | AG25: =IF($B25="","",ROUND((MIN(100,100*N($I25)/Settings!$C$27)+MIN(100,100*N($K25)/Settings!$C$28)+MIN(100,100*N($J25)/Settings!$C$29))/3,1)) -> 7.4 | AH25: =IF($B25="","",IF(SUM(Settings!$C$32:$C$37)=0,"",ROUND((Settings!$C$32*$AO25+Settings!$C$33*$AP25+Settings!$C$34*$AQ25+Settings!$C$35*$AR25+Settings!$C$36*$AS25+Settings!$C$37*$AT25)/SUM(Settings!$C$32:$C$37),1))) -> 51.3 | AI25: =IF($B25="","",MAX(0,100-IF(N($N25)>0,0,20)-IF(AND(N($L25)=0,N($M25)=0),15,0)-IF(N($J25)>0,0,10)-IF(N($K25)>0,0,10)-IF($Z25<>"",0,15)-IF($AB25<>"",0,10)-IF($R25="ERROR",20,IF($R25="WARNING",10,0)))) -> 75 | AJ25: =IF($AH25="","",IF($AH25<Settings!$C$46,"Extreme Sell Pressure",IF($AH25<Settings!$C$47,"Sell Pressure",IF($AH25<=Settings!$C$48,"Neutral",IF($AH25<=Settings!$C$49,"Buy Pressure","Extreme Buy Pressure"))))) -> Neutral | AK25: =IF($B25="","",COUNTIFS($B$4:$B$503,$B25,$A$4:$A$503,"<="&$A25)) -> 1 | AL25: =IF($A25="","",YEAR($A25)) -> 2026 | AM25: =IF($A25="","",_xlfn.ISOWEEKNUM($A25)) -> 33 | AN25: =IF($A25="","",MONTH($A25)) -> 8 | AO25: =IF($B25="","",IF(AND(N($L25)=0,N($M25)=0),50,IF(N($M25)=0,100,IF(N($L25)=0,0,MEDIAN(0,100,50+50*LN($S25)/LN(Settings!$C$40)))))) -> 54.012461 | AP25: =IF($AA25="",50,MEDIAN(0,100,50+$AA25*100*Settings!$C$41)) -> 50 | AQ25: =IF($H25="",50,MEDIAN(0,100,50+$H25*100*Settings!$C$42)) -> 50 | AR25: =IF(OR($AC25="",$H25=""),50,MEDIAN(0,100,50+SIGN($H25)*50*MEDIAN(0,1,($AC25-1)/Settings!$C$43))) -> 50 | AS25: =IF(OR($V25="",$W25=""),50,MEDIAN(0,100,50+50*($V25-$W25)/Settings!$C$44)) -> 51.108825 | AT25: =IF($AO25="",50,50+(N($AG25)/100)*($AO25-50)) -> 50.296922 | AU25: =IF($B25="","",$B25&"|"&TEXT($A25,"yyyy-mm-dd")) -> TCCL|2026-08-10 | AV25: =IF($A25="","",IF(COUNTIFS($A$4:$A25,$A25)=1,1,0)) -> 0
A26: 46244 | B26: TOL | C26: 1500 | E26: 1500 | F26: 1500 | G26: 1480 | H26: =IF($B26="","",IFERROR($E26/$D26-1,"")) | I26: 5100790 | J26: 29 | K26: 3406 | L26: 3987 | M26: 26585 | N26: 86260000000 | O26: DSE Official Daily Market Report | P26: 46265 | Q26: DSE-202608-10to13 | R26: {=IF($B26="","",IFERROR(IF(INDEX('Data Quality'!$U$4:$U$503,ROW()-3)=0,"PENDING",INDEX('Data Quality'!$U$4:$U$503,ROW()-3)),"PENDING"))} -> PASS | S26: =IF($B26="","",IF(N($M26)>0,$L26/$M26,"")) -> 0.14997179 | T26: =IF($B26="","",$L26*$E26) -> 5980500 | U26: =IF($B26="","",$M26*$E26) -> 39877500 | V26: =IF($B26="","",IF(N($N26)>0,$T26/$N26,"")) -> 6.9331092e-05 | W26: =IF($B26="","",IF(N($N26)>0,$U26/$N26,"")) -> 0.00046229423 | X26: =IF($B26="","",IF(N($J26)>0,$K26/$J26,"")) -> 117.44828 | Y26: =IF($B26="","",IF(N($J26)>0,$I26/$J26,"")) -> 175889.31 | Z26: =IF($B26="","",IF($AK26<=Settings!$C$21,"",IFERROR(AVERAGEIFS($S$4:$S$503,$B$4:$B$503,$B26,$AK$4:$AK$503,">="&$AK26-Settings!$C$21,$AK$4:$AK$503,"<="&$AK26-1),""))) | AA26: =IF(OR($S26="",$Z26="",N($Z26)=0),"",$S26/$Z26-1) | AB26: =IF($B26="","",IF($AK26<=Settings!$C$22,"",IFERROR(AVERAGEIFS($K$4:$K$503,$B$4:$B$503,$B26,$AK$4:$AK$503,">="&$AK26-Settings!$C$22,$AK$4:$AK$503,"<="&$AK26-1),""))) | AC26: =IF(OR($AB26="",N($AB26)=0),"",$K26/$AB26) | AD26: =IF($B26="","",IF($AK26<=Settings!$C$23,"",IFERROR($E26/SUMIFS($E$4:$E$503,$B$4:$B$503,$B26,$AK$4:$AK$503,$AK26-Settings!$C$23)-1,""))) | AE26: =IF($B26="","",IF($AK26<=Settings!$C$22,"",IFERROR($E26/SUMIFS($E$4:$E$503,$B$4:$B$503,$B26,$AK$4:$AK$503,$AK26-Settings!$C$22)-1,""))) | AF26: =IF($B26="","",IF(N($E26)>0,($F26-$G26)/$E26,"")) -> 0.013333333 | AG26: =IF($B26="","",ROUND((MIN(100,100*N($I26)/Settings!$C$27)+MIN(100,100*N($K26)/Settings!$C$28)+MIN(100,100*N($J26)/Settings!$C$29))/3,1)) -> 10.1 | AH26: =IF($B26="","",IF(SUM(Settings!$C$32:$C$37)=0,"",ROUND((Settings!$C$32*$AO26+Settings!$C$33*$AP26+Settings!$C$34*$AQ26+Settings!$C$35*$AR26+Settings!$C$36*$AS26+Settings!$C$37*$AT26)/SUM(Settings!$C$32:$C$37),1))) -> 30.6 | AI26: =IF($B26="","",MAX(0,100-IF(N($N26)>0,0,20)-IF(AND(N($L26)=0,N($M26)=0),15,0)-IF(N($J26)>0,0,10)-IF(N($K26)>0,0,10)-IF($Z26<>"",0,15)-IF($AB26<>"",0,10)-IF($R26="ERROR",20,IF($R26="WARNING",10,0)))) -> 75 | AJ26: =IF($AH26="","",IF($AH26<Settings!$C$46,"Extreme Sell Pressure",IF($AH26<Settings!$C$47,"Sell Pressure",IF($AH26<=Settings!$C$48,"Neutral",IF($AH26<=Settings!$C$49,"Buy Pressure","Extreme Buy Pressure"))))) -> Sell Pressure | AK26: =IF($B26="","",COUNTIFS($B$4:$B$503,$B26,$A$4:$A$503,"<="&$A26)) -> 1 | AL26: =IF($A26="","",YEAR($A26)) -> 2026 | AM26: =IF($A26="","",_xlfn.ISOWEEKNUM($A26)) -> 33 | AN26: =IF($A26="","",MONTH($A26)) -> 8 | AO26: =IF($B26="","",IF(AND(N($L26)=0,N($M26)=0),50,IF(N($M26)=0,100,IF(N($L26)=0,0,MEDIAN(0,100,50+50*LN($S26)/LN(Settings!$C$40)))))) -> 0 | AP26: =IF($AA26="",50,MEDIAN(0,100,50+$AA26*100*Settings!$C$41)) -> 50 | AQ26: =IF($H26="",50,MEDIAN(0,100,50+$H26*100*Settings!$C$42)) -> 50 | AR26: =IF(OR($AC26="",$H26=""),50,MEDIAN(0,100,50+SIGN($H26)*50*MEDIAN(0,1,($AC26-1)/Settings!$C$43))) -> 50 | AS26: =IF(OR($V26="",$W26=""),50,MEDIAN(0,100,50+50*($V26-$W26)/Settings!$C$44)) -> 10.703687 | AT26: =IF($AO26="",50,50+(N($AG26)/100)*($AO26-50)) -> 44.95 | AU26: =IF($B26="","",$B26&"|"&TEXT($A26,"yyyy-mm-dd")) -> TOL|2026-08-10 | AV26: =IF($A26="","",IF(COUNTIFS($A$4:$A26,$A26)=1,1,0)) -> 0
A27: 46244 | B27: TPCC | C27: 5850 | E27: 5850 | F27: 5950 | G27: 5850 | H27: =IF($B27="","",IFERROR($E27/$D27-1,"")) | I27: 16039250 | J27: 33 | K27: 2739 | L27: 979 | M27: 0 | N27: 1052550000000 | O27: DSE Official Daily Market Report | P27: 46265 | Q27: DSE-202608-10to13 | R27: {=IF($B27="","",IFERROR(IF(INDEX('Data Quality'!$U$4:$U$503,ROW()-3)=0,"PENDING",INDEX('Data Quality'!$U$4:$U$503,ROW()-3)),"PENDING"))} -> PASS | S27: =IF($B27="","",IF(N($M27)>0,$L27/$M27,"")) | T27: =IF($B27="","",$L27*$E27) -> 5727150 | U27: =IF($B27="","",$M27*$E27) -> 0 | V27: =IF($B27="","",IF(N($N27)>0,$T27/$N27,"")) -> 5.4412142e-06 | W27: =IF($B27="","",IF(N($N27)>0,$U27/$N27,"")) -> 0 | X27: =IF($B27="","",IF(N($J27)>0,$K27/$J27,"")) -> 83 | Y27: =IF($B27="","",IF(N($J27)>0,$I27/$J27,"")) -> 486037.88 | Z27: =IF($B27="","",IF($AK27<=Settings!$C$21,"",IFERROR(AVERAGEIFS($S$4:$S$503,$B$4:$B$503,$B27,$AK$4:$AK$503,">="&$AK27-Settings!$C$21,$AK$4:$AK$503,"<="&$AK27-1),""))) | AA27: =IF(OR($S27="",$Z27="",N($Z27)=0),"",$S27/$Z27-1) | AB27: =IF($B27="","",IF($AK27<=Settings!$C$22,"",IFERROR(AVERAGEIFS($K$4:$K$503,$B$4:$B$503,$B27,$AK$4:$AK$503,">="&$AK27-Settings!$C$22,$AK$4:$AK$503,"<="&$AK27-1),""))) | AC27: =IF(OR($AB27="",N($AB27)=0),"",$K27/$AB27) | AD27: =IF($B27="","",IF($AK27<=Settings!$C$23,"",IFERROR($E27/SUMIFS($E$4:$E$503,$B$4:$B$503,$B27,$AK$4:$AK$503,$AK27-Settings!$C$23)-1,""))) | AE27: =IF($B27="","",IF($AK27<=Settings!$C$22,"",IFERROR($E27/SUMIFS($E$4:$E$503,$B$4:$B$503,$B27,$AK$4:$AK$503,$AK27-Settings!$C$22)-1,""))) | AF27: =IF($B27="","",IF(N($E27)>0,($F27-$G27)/$E27,"")) -> 0.017094017 | AG27: =IF($B27="","",ROUND((MIN(100,100*N($I27)/Settings!$C$27)+MIN(100,100*N($K27)/Settings!$C$28)+MIN(100,100*N($J27)/Settings!$C$29))/3,1)) -> 11.7 | AH27: =IF($B27="","",IF(SUM(Settings!$C$32:$C$37)=0,"",ROUND((Settings!$C$32*$AO27+Settings!$C$33*$AP27+Settings!$C$34*$AQ27+Settings!$C$35*$AR27+Settings!$C$36*$AS27+Settings!$C$37*$AT27)/SUM(Settings!$C$32:$C$37),1))) -> 65.6 | AI27: =IF($B27="","",MAX(0,100-IF(N($N27)>0,0,20)-IF(AND(N($L27)=0,N($M27)=0),15,0)-IF(N($J27)>0,0,10)-IF(N($K27)>0,0,10)-IF($Z27<>"",0,15)-IF($AB27<>"",0,10)-IF($R27="ERROR",20,IF($R27="WARNING",10,0)))) -> 75 | AJ27: =IF($AH27="","",IF($AH27<Settings!$C$46,"Extreme Sell Pressure",IF($AH27<Settings!$C$47,"Sell Pressure",IF($AH27<=Settings!$C$48,"Neutral",IF($AH27<=Settings!$C$49,"Buy Pressure","Extreme Buy Pressure"))))) -> Buy Pressure | AK27: =IF($B27="","",COUNTIFS($B$4:$B$503,$B27,$A$4:$A$503,"<="&$A27)) -> 1 | AL27: =IF($A27="","",YEAR($A27)) -> 2026 | AM27: =IF($A27="","",_xlfn.ISOWEEKNUM($A27)) -> 33 | AN27: =IF($A27="","",MONTH($A27)) -> 8 | AO27: =IF($B27="","",IF(AND(N($L27)=0,N($M27)=0),50,IF(N($M27)=0,100,IF(N($L27)=0,0,MEDIAN(0,100,50+50*LN($S27)/LN(Settings!$C$40)))))) -> 100 | AP27: =IF($AA27="",50,MEDIAN(0,100,50+$AA27*100*Settings!$C$41)) -> 50 | AQ27: =IF($H27="",50,MEDIAN(0,100,50+$H27*100*Settings!$C$42)) -> 50 | AR27: =IF(OR($AC27="",$H27=""),50,MEDIAN(0,100,50+SIGN($H27)*50*MEDIAN(0,1,($AC27-1)/Settings!$C$43))) -> 50 | AS27: =IF(OR($V27="",$W27=""),50,MEDIAN(0,100,50+50*($V27-$W27)/Settings!$C$44)) -> 50.544121 | AT27: =IF($AO27="",50,50+(N($AG27)/100)*($AO27-50)) -> 55.85 | AU27: =IF($B27="","",$B27&"|"&TEXT($A27,"yyyy-mm-dd")) -> TPCC|2026-08-10 | AV27: =IF($A27="","",IF(COUNTIFS($A$4:$A27,$A27)=1,1,0)) -> 0
A28: 46244 | B28: TTP | C28: 450 | E28: 450 | F28: 450 | G28: 450 | H28: =IF($B28="","",IFERROR($E28/$D28-1,"")) | I28: 158400 | J28: 16 | K28: 352 | L28: 46 | M28: 1529 | N28: 42780000000 | O28: DSE Official Daily Market Report | P28: 46265 | Q28: DSE-202608-10to13 | R28: {=IF($B28="","",IFERROR(IF(INDEX('Data Quality'!$U$4:$U$503,ROW()-3)=0,"PENDING",INDEX('Data Quality'!$U$4:$U$503,ROW()-3)),"PENDING"))} -> PASS | S28: =IF($B28="","",IF(N($M28)>0,$L28/$M28,"")) -> 0.030085023 | T28: =IF($B28="","",$L28*$E28) -> 20700 | U28: =IF($B28="","",$M28*$E28) -> 688050 | V28: =IF($B28="","",IF(N($N28)>0,$T28/$N28,"")) -> 4.8387097e-07 | W28: =IF($B28="","",IF(N($N28)>0,$U28/$N28,"")) -> 1.608345e-05 | X28: =IF($B28="","",IF(N($J28)>0,$K28/$J28,"")) -> 22 | Y28: =IF($B28="","",IF(N($J28)>0,$I28/$J28,"")) -> 9900 | Z28: =IF($B28="","",IF($AK28<=Settings!$C$21,"",IFERROR(AVERAGEIFS($S$4:$S$503,$B$4:$B$503,$B28,$AK$4:$AK$503,">="&$AK28-Settings!$C$21,$AK$4:$AK$503,"<="&$AK28-1),""))) | AA28: =IF(OR($S28="",$Z28="",N($Z28)=0),"",$S28/$Z28-1) | AB28: =IF($B28="","",IF($AK28<=Settings!$C$22,"",IFERROR(AVERAGEIFS($K$4:$K$503,$B$4:$B$503,$B28,$AK$4:$AK$503,">="&$AK28-Settings!$C$22,$AK$4:$AK$503,"<="&$AK28-1),""))) | AC28: =IF(OR($AB28="",N($AB28)=0),"",$K28/$AB28) | AD28: =IF($B28="","",IF($AK28<=Settings!$C$23,"",IFERROR($E28/SUMIFS($E$4:$E$503,$B$4:$B$503,$B28,$AK$4:$AK$503,$AK28-Settings!$C$23)-1,""))) | AE28: =IF($B28="","",IF($AK28<=Settings!$C$22,"",IFERROR($E28/SUMIFS($E$4:$E$503,$B$4:$B$503,$B28,$AK$4:$AK$503,$AK28-Settings!$C$22)-1,""))) | AF28: =IF($B28="","",IF(N($E28)>0,($F28-$G28)/$E28,"")) -> 0 | AG28: =IF($B28="","",ROUND((MIN(100,100*N($I28)/Settings!$C$27)+MIN(100,100*N($K28)/Settings!$C$28)+MIN(100,100*N($J28)/Settings!$C$29))/3,1)) -> 5.4 | AH28: =IF($B28="","",IF(SUM(Settings!$C$32:$C$37)=0,"",ROUND((Settings!$C$32*$AO28+Settings!$C$33*$AP28+Settings!$C$34*$AQ28+Settings!$C$35*$AR28+Settings!$C$36*$AS28+Settings!$C$37*$AT28)/SUM(Settings!$C$32:$C$37),1))) -> 34.6 | AI28: =IF($B28="","",MAX(0,100-IF(N($N28)>0,0,20)-IF(AND(N($L28)=0,N($M28)=0),15,0)-IF(N($J28)>0,0,10)-IF(N($K28)>0,0,10)-IF($Z28<>"",0,15)-IF($AB28<>"",0,10)-IF($R28="ERROR",20,IF($R28="WARNING",10,0)))) -> 75 | AJ28: =IF($AH28="","",IF($AH28<Settings!$C$46,"Extreme Sell Pressure",IF($AH28<Settings!$C$47,"Sell Pressure",IF($AH28<=Settings!$C$48,"Neutral",IF($AH28<=Settings!$C$49,"Buy Pressure","Extreme Buy Pressure"))))) -> Sell Pressure | AK28: =IF($B28="","",COUNTIFS($B$4:$B$503,$B28,$A$4:$A$503,"<="&$A28)) -> 1 | AL28: =IF($A28="","",YEAR($A28)) -> 2026 | AM28: =IF($A28="","",_xlfn.ISOWEEKNUM($A28)) -> 33 | AN28: =IF($A28="","",MONTH($A28)) -> 8 | AO28: =IF($B28="","",IF(AND(N($L28)=0,N($M28)=0),50,IF(N($M28)=0,100,IF(N($L28)=0,0,MEDIAN(0,100,50+50*LN($S28)/LN(Settings!$C$40)))))) -> 0 | AP28: =IF($AA28="",50,MEDIAN(0,100,50+$AA28*100*Settings!$C$41)) -> 50 | AQ28: =IF($H28="",50,MEDIAN(0,100,50+$H28*100*Settings!$C$42)) -> 50 | AR28: =IF(OR($AC28="",$H28=""),50,MEDIAN(0,100,50+SIGN($H28)*50*MEDIAN(0,1,($AC28-1)/Settings!$C$43))) -> 50 | AS28: =IF(OR($V28="",$W28=""),50,MEDIAN(0,100,50+50*($V28-$W28)/Settings!$C$44)) -> 48.440042 | AT28: =IF($AO28="",50,50+(N($AG28)/100)*($AO28-50)) -> 47.3 | AU28: =IF($B28="","",$B28&"|"&TEXT($A28,"yyyy-mm-dd")) -> TTP|2026-08-10 | AV28: =IF($A28="","",IF(COUNTIFS($A$4:$A28,$A28)=1,1,0)) -> 0
A29: 46244 | B29: USL | C29: 30 | E29: 30 | H29: =IF($B29="","",IFERROR($E29/$D29-1,"")) | I29: 0 | J29: 0 | K29: 0 | L29: 1686 | M29: 0 | N29: 10950000000 | O29: DSE Official Daily Market Report | P29: 46265 | Q29: DSE-202608-10to13 | R29: {=IF($B29="","",IFERROR(IF(INDEX('Data Quality'!$U$4:$U$503,ROW()-3)=0,"PENDING",INDEX('Data Quality'!$U$4:$U$503,ROW()-3)),"PENDING"))} -> PASS | S29: =IF($B29="","",IF(N($M29)>0,$L29/$M29,"")) | T29: =IF($B29="","",$L29*$E29) -> 50580 | U29: =IF($B29="","",$M29*$E29) -> 0 | V29: =IF($B29="","",IF(N($N29)>0,$T29/$N29,"")) -> 4.6191781e-06 | W29: =IF($B29="","",IF(N($N29)>0,$U29/$N29,"")) -> 0 | X29: =IF($B29="","",IF(N($J29)>0,$K29/$J29,"")) | Y29: =IF($B29="","",IF(N($J29)>0,$I29/$J29,"")) | Z29: =IF($B29="","",IF($AK29<=Settings!$C$21,"",IFERROR(AVERAGEIFS($S$4:$S$503,$B$4:$B$503,$B29,$AK$4:$AK$503,">="&$AK29-Settings!$C$21,$AK$4:$AK$503,"<="&$AK29-1),""))) | AA29: =IF(OR($S29="",$Z29="",N($Z29)=0),"",$S29/$Z29-1) | AB29: =IF($B29="","",IF($AK29<=Settings!$C$22,"",IFERROR(AVERAGEIFS($K$4:$K$503,$B$4:$B$503,$B29,$AK$4:$AK$503,">="&$AK29-Settings!$C$22,$AK$4:$AK$503,"<="&$AK29-1),""))) | AC29: =IF(OR($AB29="",N($AB29)=0),"",$K29/$AB29) | AD29: =IF($B29="","",IF($AK29<=Settings!$C$23,"",IFERROR($E29/SUMIFS($E$4:$E$503,$B$4:$B$503,$B29,$AK$4:$AK$503,$AK29-Settings!$C$23)-1,""))) | AE29: =IF($B29="","",IF($AK29<=Settings!$C$22,"",IFERROR($E29/SUMIFS($E$4:$E$503,$B$4:$B$503,$B29,$AK$4:$AK$503,$AK29-Settings!$C$22)-1,""))) | AF29: =IF($B29="","",IF(N($E29)>0,($F29-$G29)/$E29,"")) -> 0 | AG29: =IF($B29="","",ROUND((MIN(100,100*N($I29)/Settings!$C$27)+MIN(100,100*N($K29)/Settings!$C$28)+MIN(100,100*N($J29)/Settings!$C$29))/3,1)) -> 0 | AH29: =IF($B29="","",IF(SUM(Settings!$C$32:$C$37)=0,"",ROUND((Settings!$C$32*$AO29+Settings!$C$33*$AP29+Settings!$C$34*$AQ29+Settings!$C$35*$AR29+Settings!$C$36*$AS29+Settings!$C$37*$AT29)/SUM(Settings!$C$32:$C$37),1))) -> 65 | AI29: =IF($B29="","",MAX(0,100-IF(N($N29)>0,0,20)-IF(AND(N($L29)=0,N($M29)=0),15,0)-IF(N($J29)>0,0,10)-IF(N($K29)>0,0,10)-IF($Z29<>"",0,15)-IF($AB29<>"",0,10)-IF($R29="ERROR",20,IF($R29="WARNING",10,0)))) -> 55 | AJ29: =IF($AH29="","",IF($AH29<Settings!$C$46,"Extreme Sell Pressure",IF($AH29<Settings!$C$47,"Sell Pressure",IF($AH29<=Settings!$C$48,"Neutral",IF($AH29<=Settings!$C$49,"Buy Pressure","Extreme Buy Pressure"))))) -> Buy Pressure | AK29: =IF($B29="","",COUNTIFS($B$4:$B$503,$B29,$A$4:$A$503,"<="&$A29)) -> 1 | AL29: =IF($A29="","",YEAR($A29)) -> 2026 | AM29: =IF($A29="","",_xlfn.ISOWEEKNUM($A29)) -> 33 | AN29: =IF($A29="","",MONTH($A29)) -> 8 | AO29: =IF($B29="","",IF(AND(N($L29)=0,N($M29)=0),50,IF(N($M29)=0,100,IF(N($L29)=0,0,MEDIAN(0,100,50+50*LN($S29)/LN(Settings!$C$40)))))) -> 100 | AP29: =IF($AA29="",50,MEDIAN(0,100,50+$AA29*100*Settings!$C$41)) -> 50 | AQ29: =IF($H29="",50,MEDIAN(0,100,50+$H29*100*Settings!$C$42)) -> 50 | AR29: =IF(OR($AC29="",$H29=""),50,MEDIAN(0,100,50+SIGN($H29)*50*MEDIAN(0,1,($AC29-1)/Settings!$C$43))) -> 50 | AS29: =IF(OR($V29="",$W29=""),50,MEDIAN(0,100,50+50*($V29-$W29)/Settings!$C$44)) -> 50.461918 | AT29: =IF($AO29="",50,50+(N($AG29)/100)*($AO29-50)) -> 50 | AU29: =IF($B29="","",$B29&"|"&TEXT($A29,"yyyy-mm-dd")) -> USL|2026-08-10 | AV29: =IF($A29="","",IF(COUNTIFS($A$4:$A29,$A29)=1,1,0)) -> 0
A30: 46244 | B30: VODA | C30: 1020 | E30: 1030 | F30: 1050 | G30: 1010 | H30: =IF($B30="","",IFERROR($E30/$D30-1,"")) | I30: 210145280 | J30: 323 | K30: 203088 | L30: 136195 | M30: 74917 | N30: 2307200000000 | O30: DSE Official Daily Market Report | P30: 46265 | Q30: DSE-202608-10to13 | R30: {=IF($B30="","",IFERROR(IF(INDEX('Data Quality'!$U$4:$U$503,ROW()-3)=0,"PENDING",INDEX('Data Quality'!$U$4:$U$503,ROW()-3)),"PENDING"))} -> PASS | S30: =IF($B30="","",IF(N($M30)>0,$L30/$M30,"")) -> 1.8179452 | T30: =IF($B30="","",$L30*$E30) -> 140280850 | U30: =IF($B30="","",$M30*$E30) -> 77164510 | V30: =IF($B30="","",IF(N($N30)>0,$T30/$N30,"")) -> 6.0801339e-05 | W30: =IF($B30="","",IF(N($N30)>0,$U30/$N30,"")) -> 3.3445089e-05 | X30: =IF($B30="","",IF(N($J30)>0,$K30/$J30,"")) -> 628.75542 | Y30: =IF($B30="","",IF(N($J30)>0,$I30/$J30,"")) -> 650604.58 | Z30: =IF($B30="","",IF($AK30<=Settings!$C$21,"",IFERROR(AVERAGEIFS($S$4:$S$503,$B$4:$B$503,$B30,$AK$4:$AK$503,">="&$AK30-Settings!$C$21,$AK$4:$AK$503,"<="&$AK30-1),""))) | AA30: =IF(OR($S30="",$Z30="",N($Z30)=0),"",$S30/$Z30-1) | AB30: =IF($B30="","",IF($AK30<=Settings!$C$22,"",IFERROR(AVERAGEIFS($K$4:$K$503,$B$4:$B$503,$B30,$AK$4:$AK$503,">="&$AK30-Settings!$C$22,$AK$4:$AK$503,"<="&$AK30-1),""))) | AC30: =IF(OR($AB30="",N($AB30)=0),"",$K30/$AB30) | AD30: =IF($B30="","",IF($AK30<=Settings!$C$23,"",IFERROR($E30/SUMIFS($E$4:$E$503,$B$4:$B$503,$B30,$AK$4:$AK$503,$AK30-Settings!$C$23)-1,""))) | AE30: =IF($B30="","",IF($AK30<=Settings!$C$22,"",IFERROR($E30/SUMIFS($E$4:$E$503,$B$4:$B$503,$B30,$AK$4:$AK$503,$AK30-Settings!$C$22)-1,""))) | AF30: =IF($B30="","",IF(N($E30)>0,($F30-$G30)/$E30,"")) -> 0.038834951 | AG30: =IF($B30="","",ROUND((MIN(100,100*N($I30)/Settings!$C$27)+MIN(100,100*N($K30)/Settings!$C$28)+MIN(100,100*N($J30)/Settings!$C$29))/3,1)) -> 53.9 | AH30: =IF($B30="","",IF(SUM(Settings!$C$32:$C$37)=0,"",ROUND((Settings!$C$32*$AO30+Settings!$C$33*$AP30+Settings!$C$34*$AQ30+Settings!$C$35*$AR30+Settings!$C$36*$AS30+Settings!$C$37*$AT30)/SUM(Settings!$C$32:$C$37),1))) -> 57.9 | AI30: =IF($B30="","",MAX(0,100-IF(N($N30)>0,0,20)-IF(AND(N($L30)=0,N($M30)=0),15,0)-IF(N($J30)>0,0,10)-IF(N($K30)>0,0,10)-IF($Z30<>"",0,15)-IF($AB30<>"",0,10)-IF($R30="ERROR",20,IF($R30="WARNING",10,0)))) -> 75 | AJ30: =IF($AH30="","",IF($AH30<Settings!$C$46,"Extreme Sell Pressure",IF($AH30<Settings!$C$47,"Sell Pressure",IF($AH30<=Settings!$C$48,"Neutral",IF($AH30<=Settings!$C$49,"Buy Pressure","Extreme Buy Pressure"))))) -> Neutral | AK30: =IF($B30="","",COUNTIFS($B$4:$B$503,$B30,$A$4:$A$503,"<="&$A30)) -> 1 | AL30: =IF($A30="","",YEAR($A30)) -> 2026 | AM30: =IF($A30="","",_xlfn.ISOWEEKNUM($A30)) -> 33 | AN30: =IF($A30="","",MONTH($A30)) -> 8 | AO30: =IF($B30="","",IF(AND(N($L30)=0,N($M30)=0),50,IF(N($M30)=0,100,IF(N($L30)=0,0,MEDIAN(0,100,50+50*LN($S30)/LN(Settings!$C$40)))))) -> 71.557718 | AP30: =IF($AA30="",50,MEDIAN(0,100,50+$AA30*100*Settings!$C$41)) -> 50 | AQ30: =IF($H30="",50,MEDIAN(0,100,50+$H30*100*Settings!$C$42)) -> 50 | AR30: =IF(OR($AC30="",$H30=""),50,MEDIAN(0,100,50+SIGN($H30)*50*MEDIAN(0,1,($AC30-1)/Settings!$C$43))) -> 50 | AS30: =IF(OR($V30="",$W30=""),50,MEDIAN(0,100,50+50*($V30-$W30)/Settings!$C$44)) -> 52.735625 | AT30: =IF($AO30="",50,50+(N($AG30)/100)*($AO30-50)) -> 61.61961 | AU30: =IF($B30="","",$B30&"|"&TEXT($A30,"yyyy-mm-dd")) -> VODA|2026-08-10 | AV30: =IF($A30="","",IF(COUNTIFS($A$4:$A30,$A30)=1,1,0)) -> 0
A31: 46244 | B31: YETU | C31: 510 | E31: 510 | H31: =IF($B31="","",IFERROR($E31/$D31-1,"")) | I31: 0 | J31: 0 | K31: 0 | L31: 0 | M31: 0 | N31: 6180000000 | O31: DSE Official Daily Market Report | P31: 46265 | Q31: DSE-202608-10to13 | R31: {=IF($B31="","",IFERROR(IF(INDEX('Data Quality'!$U$4:$U$503,ROW()-3)=0,"PENDING",INDEX('Data Quality'!$U$4:$U$503,ROW()-3)),"PENDING"))} -> WARNING | S31: =IF($B31="","",IF(N($M31)>0,$L31/$M31,"")) | T31: =IF($B31="","",$L31*$E31) -> 0 | U31: =IF($B31="","",$M31*$E31) -> 0 | V31: =IF($B31="","",IF(N($N31)>0,$T31/$N31,"")) -> 0 | W31: =IF($B31="","",IF(N($N31)>0,$U31/$N31,"")) -> 0 | X31: =IF($B31="","",IF(N($J31)>0,$K31/$J31,"")) | Y31: =IF($B31="","",IF(N($J31)>0,$I31/$J31,"")) | Z31: =IF($B31="","",IF($AK31<=Settings!$C$21,"",IFERROR(AVERAGEIFS($S$4:$S$503,$B$4:$B$503,$B31,$AK$4:$AK$503,">="&$AK31-Settings!$C$21,$AK$4:$AK$503,"<="&$AK31-1),""))) | AA31: =IF(OR($S31="",$Z31="",N($Z31)=0),"",$S31/$Z31-1) | AB31: =IF($B31="","",IF($AK31<=Settings!$C$22,"",IFERROR(AVERAGEIFS($K$4:$K$503,$B$4:$B$503,$B31,$AK$4:$AK$503,">="&$AK31-Settings!$C$22,$AK$4:$AK$503,"<="&$AK31-1),""))) | AC31: =IF(OR($AB31="",N($AB31)=0),"",$K31/$AB31) | AD31: =IF($B31="","",IF($AK31<=Settings!$C$23,"",IFERROR($E31/SUMIFS($E$4:$E$503,$B$4:$B$503,$B31,$AK$4:$AK$503,$AK31-Settings!$C$23)-1,""))) | AE31: =IF($B31="","",IF($AK31<=Settings!$C$22,"",IFERROR($E31/SUMIFS($E$4:$E$503,$B$4:$B$503,$B31,$AK$4:$AK$503,$AK31-Settings!$C$22)-1,""))) | AF31: =IF($B31="","",IF(N($E31)>0,($F31-$G31)/$E31,"")) -> 0 | AG31: =IF($B31="","",ROUND((MIN(100,100*N($I31)/Settings!$C$27)+MIN(100,100*N($K31)/Settings!$C$28)+MIN(100,100*N($J31)/Settings!$C$29))/3,1)) -> 0 | AH31: =IF($B31="","",IF(SUM(Settings!$C$32:$C$37)=0,"",ROUND((Settings!$C$32*$AO31+Settings!$C$33*$AP31+Settings!$C$34*$AQ31+Settings!$C$35*$AR31+Settings!$C$36*$AS31+Settings!$C$37*$AT31)/SUM(Settings!$C$32:$C$37),1))) -> 50 | AI31: =IF($B31="","",MAX(0,100-IF(N($N31)>0,0,20)-IF(AND(N($L31)=0,N($M31)=0),15,0)-IF(N($J31)>0,0,10)-IF(N($K31)>0,0,10)-IF($Z31<>"",0,15)-IF($AB31<>"",0,10)-IF($R31="ERROR",20,IF($R31="WARNING",10,0)))) -> 30 | AJ31: =IF($AH31="","",IF($AH31<Settings!$C$46,"Extreme Sell Pressure",IF($AH31<Settings!$C$47,"Sell Pressure",IF($AH31<=Settings!$C$48,"Neutral",IF($AH31<=Settings!$C$49,"Buy Pressure","Extreme Buy Pressure"))))) -> Neutral | AK31: =IF($B31="","",COUNTIFS($B$4:$B$503,$B31,$A$4:$A$503,"<="&$A31)) -> 1 | AL31: =IF($A31="","",YEAR($A31)) -> 2026 | AM31: =IF($A31="","",_xlfn.ISOWEEKNUM($A31)) -> 33 | AN31: =IF($A31="","",MONTH($A31)) -> 8 | AO31: =IF($B31="","",IF(AND(N($L31)=0,N($M31)=0),50,IF(N($M31)=0,100,IF(N($L31)=0,0,MEDIAN(0,100,50+50*LN($S31)/LN(Settings!$C$40)))))) -> 50 | AP31: =IF($AA31="",50,MEDIAN(0,100,50+$AA31*100*Settings!$C$41)) -> 50 | AQ31: =IF($H31="",50,MEDIAN(0,100,50+$H31*100*Settings!$C$42)) -> 50 | AR31: =IF(OR($AC31="",$H31=""),50,MEDIAN(0,100,50+SIGN($H31)*50*MEDIAN(0,1,($AC31-1)/Settings!$C$43))) -> 50 | AS31: =IF(OR($V31="",$W31=""),50,MEDIAN(0,100,50+50*($V31-$W31)/Settings!$C$44)) -> 50 | AT31: =IF($AO31="",50,50+(N($AG31)/100)*($AO31-50)) -> 50 | AU31: =IF($B31="","",$B31&"|"&TEXT($A31,"yyyy-mm-dd")) -> YETU|2026-08-10 | AV31: =IF($A31="","",IF(COUNTIFS($A$4:$A31,$A31)=1,1,0)) -> 0
A32: 46245 | B32: AFRIPRISE | C32: 635 | D32: 635 | E32: 630 | F32: 640 | G32: 620 | H32: =IF($B32="","",IFERROR($E32/$D32-1,"")) -> -0.0078740157 | I32: 35937360 | J32: 176 | K32: 57149 | L32: 7197 | M32: 38536 | N32: 92000000000 | O32: DSE Official Daily Market Report | P32: 46265 | Q32: DSE-202608-10to13 | R32: {=IF($B32="","",IFERROR(IF(INDEX('Data Quality'!$U$4:$U$503,ROW()-3)=0,"PENDING",INDEX('Data Quality'!$U$4:$U$503,ROW()-3)),"PENDING"))} -> PASS | S32: =IF($B32="","",IF(N($M32)>0,$L32/$M32,"")) -> 0.18676043 | T32: =IF($B32="","",$L32*$E32) -> 4534110 | U32: =IF($B32="","",$M32*$E32) -> 24277680 | V32: =IF($B32="","",IF(N($N32)>0,$T32/$N32,"")) -> 4.9283804e-05 | W32: =IF($B32="","",IF(N($N32)>0,$U32/$N32,"")) -> 0.00026388783 | X32: =IF($B32="","",IF(N($J32)>0,$K32/$J32,"")) -> 324.71023 | Y32: =IF($B32="","",IF(N($J32)>0,$I32/$J32,"")) -> 204189.55 | Z32: =IF($B32="","",IF($AK32<=Settings!$C$21,"",IFERROR(AVERAGEIFS($S$4:$S$503,$B$4:$B$503,$B32,$AK$4:$AK$503,">="&$AK32-Settings!$C$21,$AK$4:$AK$503,"<="&$AK32-1),""))) | AA32: =IF(OR($S32="",$Z32="",N($Z32)=0),"",$S32/$Z32-1) | AB32: =IF($B32="","",IF($AK32<=Settings!$C$22,"",IFERROR(AVERAGEIFS($K$4:$K$503,$B$4:$B$503,$B32,$AK$4:$AK$503,">="&$AK32-Settings!$C$22,$AK$4:$AK$503,"<="&$AK32-1),""))) | AC32: =IF(OR($AB32="",N($AB32)=0),"",$K32/$AB32) | AD32: =IF($B32="","",IF($AK32<=Settings!$C$23,"",IFERROR($E32/SUMIFS($E$4:$E$503,$B$4:$B$503,$B32,$AK$4:$AK$503,$AK32-Settings!$C$23)-1,""))) | AE32: =IF($B32="","",IF($AK32<=Settings!$C$22,"",IFERROR($E32/SUMIFS($E$4:$E$503,$B$4:$B$503,$B32,$AK$4:$AK$503,$AK32-Settings!$C$22)-1,""))) | AF32: =IF($B32="","",IF(N($E32)>0,($F32-$G32)/$E32,"")) -> 0.031746032 | AG32: =IF($B32="","",ROUND((MIN(100,100*N($I32)/Settings!$C$27)+MIN(100,100*N($K32)/Settings!$C$28)+MIN(100,100*N($J32)/Settings!$C$29))/3,1)) -> 38.3 | AH32: =IF($B32="","",IF(SUM(Settings!$C$32:$C$37)=0,"",ROUND((Settings!$C$32*$AO32+Settings!$C$33*$AP32+Settings!$C$34*$AQ32+Settings!$C$35*$AR32+Settings!$C$36*$AS32+Settings!$C$37*$AT32)/SUM(Settings!$C$32:$C$37),1))) -> 29.8 | AI32: =IF($B32="","",MAX(0,100-IF(N($N32)>0,0,20)-IF(AND(N($L32)=0,N($M32)=0),15,0)-IF(N($J32)>0,0,10)-IF(N($K32)>0,0,10)-IF($Z32<>"",0,15)-IF($AB32<>"",0,10)-IF($R32="ERROR",20,IF($R32="WARNING",10,0)))) -> 75 | AJ32: =IF($AH32="","",IF($AH32<Settings!$C$46,"Extreme Sell Pressure",IF($AH32<Settings!$C$47,"Sell Pressure",IF($AH32<=Settings!$C$48,"Neutral",IF($AH32<=Settings!$C$49,"Buy Pressure","Extreme Buy Pressure"))))) -> Sell Pressure | AK32: =IF($B32="","",COUNTIFS($B$4:$B$503,$B32,$A$4:$A$503,"<="&$A32)) -> 2 | AL32: =IF($A32="","",YEAR($A32)) -> 2026 | AM32: =IF($A32="","",_xlfn.ISOWEEKNUM($A32)) -> 33 | AN32: =IF($A32="","",MONTH($A32)) -> 8 | AO32: =IF($B32="","",IF(AND(N($L32)=0,N($M32)=0),50,IF(N($M32)=0,100,IF(N($L32)=0,0,MEDIAN(0,100,50+50*LN($S32)/LN(Settings!$C$40)))))) -> 0 | AP32: =IF($AA32="",50,MEDIAN(0,100,50+$AA32*100*Settings!$C$41)) -> 50 | AQ32: =IF($H32="",50,MEDIAN(0,100,50+$H32*100*Settings!$C$42)) -> 42.125984 | AR32: =IF(OR($AC32="",$H32=""),50,MEDIAN(0,100,50+SIGN($H32)*50*MEDIAN(0,1,($AC32-1)/Settings!$C$43))) -> 50 | AS32: =IF(OR($V32="",$W32=""),50,MEDIAN(0,100,50+50*($V32-$W32)/Settings!$C$44)) -> 28.539598 | AT32: =IF($AO32="",50,50+(N($AG32)/100)*($AO32-50)) -> 30.85 | AU32: =IF($B32="","",$B32&"|"&TEXT($A32,"yyyy-mm-dd")) -> AFRIPRISE|2026-08-11 | AV32: =IF($A32="","",IF(COUNTIFS($A$4:$A32,$A32)=1,1,0)) -> 1
A33: 46245 | B33: CRDB | C33: 2600 | D33: 2600 | E33: 2600 | F33: 2620 | G33: 2590 | H33: =IF($B33="","",IFERROR($E33/$D33-1,"")) -> 0 | I33: 1442616130 | J33: 1035 | K33: 553818 | L33: 435736 | M33: 138838 | N33: 6790780000000 | O33: DSE Official Daily Market Report | P33: 46265 | Q33: DSE-202608-10to13 | R33: {=IF($B33="","",IFERROR(IF(INDEX('Data Quality'!$U$4:$U$503,ROW()-3)=0,"PENDING",INDEX('Data Quality'!$U$4:$U$503,ROW()-3)),"PENDING"))} -> PASS | S33: =IF($B33="","",IF(N($M33)>0,$L33/$M33,"")) -> 3.1384491 | T33: =IF($B33="","",$L33*$E33) -> 1132913600 | U33: =IF($B33="","",$M33*$E33) -> 360978800 | V33: =IF($B33="","",IF(N($N33)>0,$T33/$N33,"")) -> 0.00016683114 | W33: =IF($B33="","",IF(N($N33)>0,$U33/$N33,"")) -> 5.3157193e-05 | X33: =IF($B33="","",IF(N($J33)>0,$K33/$J33,"")) -> 535.08986 | Y33: =IF($B33="","",IF(N($J33)>0,$I33/$J33,"")) -> 1393832 | Z33: =IF($B33="","",IF($AK33<=Settings!$C$21,"",IFERROR(AVERAGEIFS($S$4:$S$503,$B$4:$B$503,$B33,$AK$4:$AK$503,">="&$AK33-Settings!$C$21,$AK$4:$AK$503,"<="&$AK33-1),""))) | AA33: =IF(OR($S33="",$Z33="",N($Z33)=0),"",$S33/$Z33-1) | AB33: =IF($B33="","",IF($AK33<=Settings!$C$22,"",IFERROR(AVERAGEIFS($K$4:$K$503,$B$4:$B$503,$B33,$AK$4:$AK$503,">="&$AK33-Settings!$C$22,$AK$4:$AK$503,"<="&$AK33-1),""))) | AC33: =IF(OR($AB33="",N($AB33)=0),"",$K33/$AB33) | AD33: =IF($B33="","",IF($AK33<=Settings!$C$23,"",IFERROR($E33/SUMIFS($E$4:$E$503,$B$4:$B$503,$B33,$AK$4:$AK$503,$AK33-Settings!$C$23)-1,""))) | AE33: =IF($B33="","",IF($AK33<=Settings!$C$22,"",IFERROR($E33/SUMIFS($E$4:$E$503,$B$4:$B$503,$B33,$AK$4:$AK$503,$AK33-Settings!$C$22)-1,""))) | AF33: =IF($B33="","",IF(N($E33)>0,($F33-$G33)/$E33,"")) -> 0.011538462 | AG33: =IF($B33="","",ROUND((MIN(100,100*N($I33)/Settings!$C$27)+MIN(100,100*N($K33)/Settings!$C$28)+MIN(100,100*N($J33)/Settings!$C$29))/3,1)) -> 100 | AH33: =IF($B33="","",IF(SUM(Settings!$C$32:$C$37)=0,"",ROUND((Settings!$C$32*$AO33+Settings!$C$33*$AP33+Settings!$C$34*$AQ33+Settings!$C$35*$AR33+Settings!$C$36*$AS33+Settings!$C$37*$AT33)/SUM(Settings!$C$32:$C$37),1))) -> 67.6 | AI33: =IF($B33="","",MAX(0,100-IF(N($N33)>0,0,20)-IF(AND(N($L33)=0,N($M33)=0),15,0)-IF(N($J33)>0,0,10)-IF(N($K33)>0,0,10)-IF($Z33<>"",0,15)-IF($AB33<>"",0,10)-IF($R33="ERROR",20,IF($R33="WARNING",10,0)))) -> 75 | AJ33: =IF($AH33="","",IF($AH33<Settings!$C$46,"Extreme Sell Pressure",IF($AH33<Settings!$C$47,"Sell Pressure",IF($AH33<=Settings!$C$48,"Neutral",IF($AH33<=Settings!$C$49,"Buy Pressure","Extreme Buy Pressure"))))) -> Buy Pressure | AK33: =IF($B33="","",COUNTIFS($B$4:$B$503,$B33,$A$4:$A$503,"<="&$A33)) -> 2 | AL33: =IF($A33="","",YEAR($A33)) -> 2026 | AM33: =IF($A33="","",_xlfn.ISOWEEKNUM($A33)) -> 33 | AN33: =IF($A33="","",MONTH($A33)) -> 8 | AO33: =IF($B33="","",IF(AND(N($L33)=0,N($M33)=0),50,IF(N($M33)=0,100,IF(N($L33)=0,0,MEDIAN(0,100,50+50*LN($S33)/LN(Settings!$C$40)))))) -> 91.251296 | AP33: =IF($AA33="",50,MEDIAN(0,100,50+$AA33*100*Settings!$C$41)) -> 50 | AQ33: =IF($H33="",50,MEDIAN(0,100,50+$H33*100*Settings!$C$42)) -> 50 | AR33: =IF(OR($AC33="",$H33=""),50,MEDIAN(0,100,50+SIGN($H33)*50*MEDIAN(0,1,($AC33-1)/Settings!$C$43))) -> 50 | AS33: =IF(OR($V33="",$W33=""),50,MEDIAN(0,100,50+50*($V33-$W33)/Settings!$C$44)) -> 61.367395 | AT33: =IF($AO33="",50,50+(N($AG33)/100)*($AO33-50)) -> 91.251296 | AU33: =IF($B33="","",$B33&"|"&TEXT($A33,"yyyy-mm-dd")) -> CRDB|2026-08-11 | AV33: =IF($A33="","",IF(COUNTIFS($A$4:$A33,$A33)=1,1,0)) -> 0
A34: 46245 | B34: DCB | C34: 410 | D34: 410 | E34: 400 | F34: 420 | G34: 390 | H34: =IF($B34="","",IFERROR($E34/$D34-1,"")) -> -0.024390244 | I34: 8608950 | J34: 100 | K34: 21550 | L34: 18979 | M34: 96752 | N34: 76630000000 | O34: DSE Official Daily Market Report | P34: 46265 | Q34: DSE-202608-10to13 | R34: {=IF($B34="","",IFERROR(IF(INDEX('Data Quality'!$U$4:$U$503,ROW()-3)=0,"PENDING",INDEX('Data Quality'!$U$4:$U$503,ROW()-3)),"PENDING"))} -> PASS | S34: =IF($B34="","",IF(N($M34)>0,$L34/$M34,"")) -> 0.19616132 | T34: =IF($B34="","",$L34*$E34) -> 7591600 | U34: =IF($B34="","",$M34*$E34) -> 38700800 | V34: =IF($B34="","",IF(N($N34)>0,$T34/$N34,"")) -> 9.906825e-05 | W34: =IF($B34="","",IF(N($N34)>0,$U34/$N34,"")) -> 0.00050503458 | X34: =IF($B34="","",IF(N($J34)>0,$K34/$J34,"")) -> 215.5 | Y34: =IF($B34="","",IF(N($J34)>0,$I34/$J34,"")) -> 86089.5 | Z34: =IF($B34="","",IF($AK34<=Settings!$C$21,"",IFERROR(AVERAGEIFS($S$4:$S$503,$B$4:$B$503,$B34,$AK$4:$AK$503,">="&$AK34-Settings!$C$21,$AK$4:$AK$503,"<="&$AK34-1),""))) | AA34: =IF(OR($S34="",$Z34="",N($Z34)=0),"",$S34/$Z34-1) | AB34: =IF($B34="","",IF($AK34<=Settings!$C$22,"",IFERROR(AVERAGEIFS($K$4:$K$503,$B$4:$B$503,$B34,$AK$4:$AK$503,">="&$AK34-Settings!$C$22,$AK$4:$AK$503,"<="&$AK34-1),""))) | AC34: =IF(OR($AB34="",N($AB34)=0),"",$K34/$AB34) | AD34: =IF($B34="","",IF($AK34<=Settings!$C$23,"",IFERROR($E34/SUMIFS($E$4:$E$503,$B$4:$B$503,$B34,$AK$4:$AK$503,$AK34-Settings!$C$23)-1,""))) | AE34: =IF($B34="","",IF($AK34<=Settings!$C$22,"",IFERROR($E34/SUMIFS($E$4:$E$503,$B$4:$B$503,$B34,$AK$4:$AK$503,$AK34-Settings!$C$22)-1,""))) | AF34: =IF($B34="","",IF(N($E34)>0,($F34-$G34)/$E34,"")) -> 0.075 | AG34: =IF($B34="","",ROUND((MIN(100,100*N($I34)/Settings!$C$27)+MIN(100,100*N($K34)/Settings!$C$28)+MIN(100,100*N($J34)/Settings!$C$29))/3,1)) -> 35.1 | AH34: =IF($B34="","",IF(SUM(Settings!$C$32:$C$37)=0,"",ROUND((Settings!$C$32*$AO34+Settings!$C$33*$AP34+Settings!$C$34*$AQ34+Settings!$C$35*$AR34+Settings!$C$36*$AS34+Settings!$C$37*$AT34)/SUM(Settings!$C$32:$C$37),1))) -> 25.5 | AI34: =IF($B34="","",MAX(0,100-IF(N($N34)>0,0,20)-IF(AND(N($L34)=0,N($M34)=0),15,0)-IF(N($J34)>0,0,10)-IF(N($K34)>0,0,10)-IF($Z34<>"",0,15)-IF($AB34<>"",0,10)-IF($R34="ERROR",20,IF($R34="WARNING",10,0)))) -> 75 | AJ34: =IF($AH34="","",IF($AH34<Settings!$C$46,"Extreme Sell Pressure",IF($AH34<Settings!$C$47,"Sell Pressure",IF($AH34<=Settings!$C$48,"Neutral",IF($AH34<=Settings!$C$49,"Buy Pressure","Extreme Buy Pressure"))))) -> Sell Pressure | AK34: =IF($B34="","",COUNTIFS($B$4:$B$503,$B34,$A$4:$A$503,"<="&$A34)) -> 2 | AL34: =IF($A34="","",YEAR($A34)) -> 2026 | AM34: =IF($A34="","",_xlfn.ISOWEEKNUM($A34)) -> 33 | AN34: =IF($A34="","",MONTH($A34)) -> 8 | AO34: =IF($B34="","",IF(AND(N($L34)=0,N($M34)=0),50,IF(N($M34)=0,100,IF(N($L34)=0,0,MEDIAN(0,100,50+50*LN($S34)/LN(Settings!$C$40)))))) -> 0 | AP34: =IF($AA34="",50,MEDIAN(0,100,50+$AA34*100*Settings!$C$41)) -> 50 | AQ34: =IF($H34="",50,MEDIAN(0,100,50+$H34*100*Settings!$C$42)) -> 25.609756 | AR34: =IF(OR($AC34="",$H34=""),50,MEDIAN(0,100,50+SIGN($H34)*50*MEDIAN(0,1,($AC34-1)/Settings!$C$43))) -> 50 | AS34: =IF(OR($V34="",$W34=""),50,MEDIAN(0,100,50+50*($V34-$W34)/Settings!$C$44)) -> 9.4033668 | AT34: =IF($AO34="",50,50+(N($AG34)/100)*($AO34-50)) -> 32.45 | AU34: =IF($B34="","",$B34&"|"&TEXT($A34,"yyyy-mm-dd")) -> DCB|2026-08-11 | AV34: =IF($A34="","",IF(COUNTIFS($A$4:$A34,$A34)=1,1,0)) -> 0
A35: 46245 | B35: DSE | C35: 6450 | D35: 6450 | E35: 6090 | F35: 6570 | G35: 5800 | H35: =IF($B35="","",IFERROR($E35/$D35-1,"")) -> -0.055813953 | I35: 7567340 | J35: 21 | K35: 1242 | L35: 3464 | M35: 1454 | N35: 145090000000 | O35: DSE Official Daily Market Report | P35: 46265 | Q35: DSE-202608-10to13 | R35: {=IF($B35="","",IFERROR(IF(INDEX('Data Quality'!$U$4:$U$503,ROW()-3)=0,"PENDING",INDEX('Data Quality'!$U$4:$U$503,ROW()-3)),"PENDING"))} -> PASS | S35: =IF($B35="","",IF(N($M35)>0,$L35/$M35,"")) -> 2.3823934 | T35: =IF($B35="","",$L35*$E35) -> 21095760 | U35: =IF($B35="","",$M35*$E35) -> 8854860 | V35: =IF($B35="","",IF(N($N35)>0,$T35/$N35,"")) -> 0.00014539775 | W35: =IF($B35="","",IF(N($N35)>0,$U35/$N35,"")) -> 6.1030119e-05 | X35: =IF($B35="","",IF(N($J35)>0,$K35/$J35,"")) -> 59.142857 | Y35: =IF($B35="","",IF(N($J35)>0,$I35/$J35,"")) -> 360349.52 | Z35: =IF($B35="","",IF($AK35<=Settings!$C$21,"",IFERROR(AVERAGEIFS($S$4:$S$503,$B$4:$B$503,$B35,$AK$4:$AK$503,">="&$AK35-Settings!$C$21,$AK$4:$AK$503,"<="&$AK35-1),""))) | AA35: =IF(OR($S35="",$Z35="",N($Z35)=0),"",$S35/$Z35-1) | AB35: =IF($B35="","",IF($AK35<=Settings!$C$22,"",IFERROR(AVERAGEIFS($K$4:$K$503,$B$4:$B$503,$B35,$AK$4:$AK$503,">="&$AK35-Settings!$C$22,$AK$4:$AK$503,"<="&$AK35-1),""))) | AC35: =IF(OR($AB35="",N($AB35)=0),"",$K35/$AB35) | AD35: =IF($B35="","",IF($AK35<=Settings!$C$23,"",IFERROR($E35/SUMIFS($E$4:$E$503,$B$4:$B$503,$B35,$AK$4:$AK$503,$AK35-Settings!$C$23)-1,""))) | AE35: =IF($B35="","",IF($AK35<=Settings!$C$22,"",IFERROR($E35/SUMIFS($E$4:$E$503,$B$4:$B$503,$B35,$AK$4:$AK$503,$AK35-Settings!$C$22)-1,""))) | AF35: =IF($B35="","",IF(N($E35)>0,($F35-$G35)/$E35,"")) -> 0.12643678 | AG35: =IF($B35="","",ROUND((MIN(100,100*N($I35)/Settings!$C$27)+MIN(100,100*N($K35)/Settings!$C$28)+MIN(100,100*N($J35)/Settings!$C$29))/3,1)) -> 7.3 | AH35: =IF($B35="","",IF(SUM(Settings!$C$32:$C$37)=0,"",ROUND((Settings!$C$32*$AO35+Settings!$C$33*$AP35+Settings!$C$34*$AQ35+Settings!$C$35*$AR35+Settings!$C$36*$AS35+Settings!$C$37*$AT35)/SUM(Settings!$C$32:$C$37),1))) -> 53 | AI35: =IF($B35="","",MAX(0,100-IF(N($N35)>0,0,20)-IF(AND(N($L35)=0,N($M35)=0),15,0)-IF(N($J35)>0,0,10)-IF(N($K35)>0,0,10)-IF($Z35<>"",0,15)-IF($AB35<>"",0,10)-IF($R35="ERROR",20,IF($R35="WARNING",10,0)))) -> 75 | AJ35: =IF($AH35="","",IF($AH35<Settings!$C$46,"Extreme Sell Pressure",IF($AH35<Settings!$C$47,"Sell Pressure",IF($AH35<=Settings!$C$48,"Neutral",IF($AH35<=Settings!$C$49,"Buy Pressure","Extreme Buy Pressure"))))) -> Neutral | AK35: =IF($B35="","",COUNTIFS($B$4:$B$503,$B35,$A$4:$A$503,"<="&$A35)) -> 2 | AL35: =IF($A35="","",YEAR($A35)) -> 2026 | AM35: =IF($A35="","",_xlfn.ISOWEEKNUM($A35)) -> 33 | AN35: =IF($A35="","",MONTH($A35)) -> 8 | AO35: =IF($B35="","",IF(AND(N($L35)=0,N($M35)=0),50,IF(N($M35)=0,100,IF(N($L35)=0,0,MEDIAN(0,100,50+50*LN($S35)/LN(Settings!$C$40)))))) -> 81.310292 | AP35: =IF($AA35="",50,MEDIAN(0,100,50+$AA35*100*Settings!$C$41)) -> 50 | AQ35: =IF($H35="",50,MEDIAN(0,100,50+$H35*100*Settings!$C$42)) -> 0 | AR35: =IF(OR($AC35="",$H35=""),50,MEDIAN(0,100,50+SIGN($H35)*50*MEDIAN(0,1,($AC35-1)/Settings!$C$43))) -> 50 | AS35: =IF(OR($V35="",$W35=""),50,MEDIAN(0,100,50+50*($V35-$W35)/Settings!$C$44)) -> 58.436763 | AT35: =IF($AO35="",50,50+(N($AG35)/100)*($AO35-50)) -> 52.285651 | AU35: =IF($B35="","",$B35&"|"&TEXT($A35,"yyyy-mm-dd")) -> DSE|2026-08-11 | AV35: =IF($A35="","",IF(COUNTIFS($A$4:$A35,$A35)=1,1,0)) -> 0
A36: 46245 | B36: EABL | C36: 5680 | D36: 5680 | E36: 5510 | H36: =IF($B36="","",IFERROR($E36/$D36-1,"")) -> -0.029929577 | I36: 0 | J36: 0 | K36: 0 | L36: 45 | M36: 0 | N36: 4357170000000 | O36: DSE Official Daily Market Report | P36: 46265 | Q36: DSE-202608-10to13 | R36: {=IF($B36="","",IFERROR(IF(INDEX('Data Quality'!$U$4:$U$503,ROW()-3)=0,"PENDING",INDEX('Data Quality'!$U$4:$U$503,ROW()-3)),"PENDING"))} -> PASS | S36: =IF($B36="","",IF(N($M36)>0,$L36/$M36,"")) | T36: =IF($B36="","",$L36*$E36) -> 247950 | U36: =IF($B36="","",$M36*$E36) -> 0 | V36: =IF($B36="","",IF(N($N36)>0,$T36/$N36,"")) -> 5.6906203e-08 | W36: =IF($B36="","",IF(N($N36)>0,$U36/$N36,"")) -> 0 | X36: =IF($B36="","",IF(N($J36)>0,$K36/$J36,"")) | Y36: =IF($B36="","",IF(N($J36)>0,$I36/$J36,"")) | Z36: =IF($B36="","",IF($AK36<=Settings!$C$21,"",IFERROR(AVERAGEIFS($S$4:$S$503,$B$4:$B$503,$B36,$AK$4:$AK$503,">="&$AK36-Settings!$C$21,$AK$4:$AK$503,"<="&$AK36-1),""))) | AA36: =IF(OR($S36="",$Z36="",N($Z36)=0),"",$S36/$Z36-1) | AB36: =IF($B36="","",IF($AK36<=Settings!$C$22,"",IFERROR(AVERAGEIFS($K$4:$K$503,$B$4:$B$503,$B36,$AK$4:$AK$503,">="&$AK36-Settings!$C$22,$AK$4:$AK$503,"<="&$AK36-1),""))) | AC36: =IF(OR($AB36="",N($AB36)=0),"",$K36/$AB36) | AD36: =IF($B36="","",IF($AK36<=Settings!$C$23,"",IFERROR($E36/SUMIFS($E$4:$E$503,$B$4:$B$503,$B36,$AK$4:$AK$503,$AK36-Settings!$C$23)-1,""))) | AE36: =IF($B36="","",IF($AK36<=Settings!$C$22,"",IFERROR($E36/SUMIFS($E$4:$E$503,$B$4:$B$503,$B36,$AK$4:$AK$503,$AK36-Settings!$C$22)-1,""))) | AF36: =IF($B36="","",IF(N($E36)>0,($F36-$G36)/$E36,"")) -> 0 | AG36: =IF($B36="","",ROUND((MIN(100,100*N($I36)/Settings!$C$27)+MIN(100,100*N($K36)/Settings!$C$28)+MIN(100,100*N($J36)/Settings!$C$29))/3,1)) -> 0 | AH36: =IF($B36="","",IF(SUM(Settings!$C$32:$C$37)=0,"",ROUND((Settings!$C$32*$AO36+Settings!$C$33*$AP36+Settings!$C$34*$AQ36+Settings!$C$35*$AR36+Settings!$C$36*$AS36+Settings!$C$37*$AT36)/SUM(Settings!$C$32:$C$37),1))) -> 60.5 | AI36: =IF($B36="","",MAX(0,100-IF(N($N36)>0,0,20)-IF(AND(N($L36)=0,N($M36)=0),15,0)-IF(N($J36)>0,0,10)-IF(N($K36)>0,0,10)-IF($Z36<>"",0,15)-IF($AB36<>"",0,10)-IF($R36="ERROR",20,IF($R36="WARNING",10,0)))) -> 55 | AJ36: =IF($AH36="","",IF($AH36<Settings!$C$46,"Extreme Sell Pressure",IF($AH36<Settings!$C$47,"Sell Pressure",IF($AH36<=Settings!$C$48,"Neutral",IF($AH36<=Settings!$C$49,"Buy Pressure","Extreme Buy Pressure"))))) -> Buy Pressure | AK36: =IF($B36="","",COUNTIFS($B$4:$B$503,$B36,$A$4:$A$503,"<="&$A36)) -> 2 | AL36: =IF($A36="","",YEAR($A36)) -> 2026 | AM36: =IF($A36="","",_xlfn.ISOWEEKNUM($A36)) -> 33 | AN36: =IF($A36="","",MONTH($A36)) -> 8 | AO36: =IF($B36="","",IF(AND(N($L36)=0,N($M36)=0),50,IF(N($M36)=0,100,IF(N($L36)=0,0,MEDIAN(0,100,50+50*LN($S36)/LN(Settings!$C$40)))))) -> 100 | AP36: =IF($AA36="",50,MEDIAN(0,100,50+$AA36*100*Settings!$C$41)) -> 50 | AQ36: =IF($H36="",50,MEDIAN(0,100,50+$H36*100*Settings!$C$42)) -> 20.070423 | AR36: =IF(OR($AC36="",$H36=""),50,MEDIAN(0,100,50+SIGN($H36)*50*MEDIAN(0,1,($AC36-1)/Settings!$C$43))) -> 50 | AS36: =IF(OR($V36="",$W36=""),50,MEDIAN(0,100,50+50*($V36-$W36)/Settings!$C$44)) -> 50.005691 | AT36: =IF($AO36="",50,50+(N($AG36)/100)*($AO36-50)) -> 50 | AU36: =IF($B36="","",$B36&"|"&TEXT($A36,"yyyy-mm-dd")) -> EABL|2026-08-11 | AV36: =IF($A36="","",IF(COUNTIFS($A$4:$A36,$A36)=1,1,0)) -> 0
A37: 46245 | B37: JATU | C37: 265 | D37: 265 | E37: 265 | H37: =IF($B37="","",IFERROR($E37/$D37-1,"")) -> 0 | I37: 0 | J37: 0 | K37: 0 | L37: 0 | M37: 0 | N37: 5280000000 | O37: DSE Official Daily Market Report | P37: 46265 | Q37: DSE-202608-10to13 | R37: {=IF($B37="","",IFERROR(IF(INDEX('Data Quality'!$U$4:$U$503,ROW()-3)=0,"PENDING",INDEX('Data Quality'!$U$4:$U$503,ROW()-3)),"PENDING"))} -> WARNING | S37: =IF($B37="","",IF(N($M37)>0,$L37/$M37,"")) | T37: =IF($B37="","",$L37*$E37) -> 0 | U37: =IF($B37="","",$M37*$E37) -> 0 | V37: =IF($B37="","",IF(N($N37)>0,$T37/$N37,"")) -> 0 | W37: =IF($B37="","",IF(N($N37)>0,$U37/$N37,"")) -> 0 | X37: =IF($B37="","",IF(N($J37)>0,$K37/$J37,"")) | Y37: =IF($B37="","",IF(N($J37)>0,$I37/$J37,"")) | Z37: =IF($B37="","",IF($AK37<=Settings!$C$21,"",IFERROR(AVERAGEIFS($S$4:$S$503,$B$4:$B$503,$B37,$AK$4:$AK$503,">="&$AK37-Settings!$C$21,$AK$4:$AK$503,"<="&$AK37-1),""))) | AA37: =IF(OR($S37="",$Z37="",N($Z37)=0),"",$S37/$Z37-1) | AB37: =IF($B37="","",IF($AK37<=Settings!$C$22,"",IFERROR(AVERAGEIFS($K$4:$K$503,$B$4:$B$503,$B37,$AK$4:$AK$503,">="&$AK37-Settings!$C$22,$AK$4:$AK$503,"<="&$AK37-1),""))) | AC37: =IF(OR($AB37="",N($AB37)=0),"",$K37/$AB37) | AD37: =IF($B37="","",IF($AK37<=Settings!$C$23,"",IFERROR($E37/SUMIFS($E$4:$E$503,$B$4:$B$503,$B37,$AK$4:$AK$503,$AK37-Settings!$C$23)-1,""))) | AE37: =IF($B37="","",IF($AK37<=Settings!$C$22,"",IFERROR($E37/SUMIFS($E$4:$E$503,$B$4:$B$503,$B37,$AK$4:$AK$503,$AK37-Settings!$C$22)-1,""))) | AF37: =IF($B37="","",IF(N($E37)>0,($F37-$G37)/$E37,"")) -> 0 | AG37: =IF($B37="","",ROUND((MIN(100,100*N($I37)/Settings!$C$27)+MIN(100,100*N($K37)/Settings!$C$28)+MIN(100,100*N($J37)/Settings!$C$29))/3,1)) -> 0 | AH37: =IF($B37="","",IF(SUM(Settings!$C$32:$C$37)=0,"",ROUND((Settings!$C$32*$AO37+Settings!$C$33*$AP37+Settings!$C$34*$AQ37+Settings!$C$35*$AR37+Settings!$C$36*$AS37+Settings!$C$37*$AT37)/SUM(Settings!$C$32:$C$37),1))) -> 50 | AI37: =IF($B37="","",MAX(0,100-IF(N($N37)>0,0,20)-IF(AND(N($L37)=0,N($M37)=0),15,0)-IF(N($J37)>0,0,10)-IF(N($K37)>0,0,10)-IF($Z37<>"",0,15)-IF($AB37<>"",0,10)-IF($R37="ERROR",20,IF($R37="WARNING",10,0)))) -> 30 | AJ37: =IF($AH37="","",IF($AH37<Settings!$C$46,"Extreme Sell Pressure",IF($AH37<Settings!$C$47,"Sell Pressure",IF($AH37<=Settings!$C$48,"Neutral",IF($AH37<=Settings!$C$49,"Buy Pressure","Extreme Buy Pressure"))))) -> Neutral | AK37: =IF($B37="","",COUNTIFS($B$4:$B$503,$B37,$A$4:$A$503,"<="&$A37)) -> 2 | AL37: =IF($A37="","",YEAR($A37)) -> 2026 | AM37: =IF($A37="","",_xlfn.ISOWEEKNUM($A37)) -> 33 | AN37: =IF($A37="","",MONTH($A37)) -> 8 | AO37: =IF($B37="","",IF(AND(N($L37)=0,N($M37)=0),50,IF(N($M37)=0,100,IF(N($L37)=0,0,MEDIAN(0,100,50+50*LN($S37)/LN(Settings!$C$40)))))) -> 50 | AP37: =IF($AA37="",50,MEDIAN(0,100,50+$AA37*100*Settings!$C$41)) -> 50 | AQ37: =IF($H37="",50,MEDIAN(0,100,50+$H37*100*Settings!$C$42)) -> 50 | AR37: =IF(OR($AC37="",$H37=""),50,MEDIAN(0,100,50+SIGN($H37)*50*MEDIAN(0,1,($AC37-1)/Settings!$C$43))) -> 50 | AS37: =IF(OR($V37="",$W37=""),50,MEDIAN(0,100,50+50*($V37-$W37)/Settings!$C$44)) -> 50 | AT37: =IF($AO37="",50,50+(N($AG37)/100)*($AO37-50)) -> 50 | AU37: =IF($B37="","",$B37&"|"&TEXT($A37,"yyyy-mm-dd")) -> JATU|2026-08-11 | AV37: =IF($A37="","",IF(COUNTIFS($A$4:$A37,$A37)=1,1,0)) -> 0
A38: 46245 | B38: JHL | C38: 8650 | D38: 8650 | E38: 8650 | H38: =IF($B38="","",IFERROR($E38/$D38-1,"")) -> 0 | I38: 0 | J38: 0 | K38: 0 | L38: 11 | M38: 0 | N38: 626890000000 | O38: DSE Official Daily Market Report | P38: 46265 | Q38: DSE-202608-10to13 | R38: {=IF($B38="","",IFERROR(IF(INDEX('Data Quality'!$U$4:$U$503,ROW()-3)=0,"PENDING",INDEX('Data Quality'!$U$4:$U$503,ROW()-3)),"PENDING"))} -> PASS | S38: =IF($B38="","",IF(N($M38)>0,$L38/$M38,"")) | T38: =IF($B38="","",$L38*$E38) -> 95150 | U38: =IF($B38="","",$M38*$E38) -> 0 | V38: =IF($B38="","",IF(N($N38)>0,$T38/$N38,"")) -> 1.5178101e-07 | W38: =IF($B38="","",IF(N($N38)>0,$U38/$N38,"")) -> 0 | X38: =IF($B38="","",IF(N($J38)>0,$K38/$J38,"")) | Y38: =IF($B38="","",IF(N($J38)>0,$I38/$J38,"")) | Z38: =IF($B38="","",IF($AK38<=Settings!$C$21,"",IFERROR(AVERAGEIFS($S$4:$S$503,$B$4:$B$503,$B38,$AK$4:$AK$503,">="&$AK38-Settings!$C$21,$AK$4:$AK$503,"<="&$AK38-1),""))) | AA38: =IF(OR($S38="",$Z38="",N($Z38)=0),"",$S38/$Z38-1) | AB38: =IF($B38="","",IF($AK38<=Settings!$C$22,"",IFERROR(AVERAGEIFS($K$4:$K$503,$B$4:$B$503,$B38,$AK$4:$AK$503,">="&$AK38-Settings!$C$22,$AK$4:$AK$503,"<="&$AK38-1),""))) | AC38: =IF(OR($AB38="",N($AB38)=0),"",$K38/$AB38) | AD38: =IF($B38="","",IF($AK38<=Settings!$C$23,"",IFERROR($E38/SUMIFS($E$4:$E$503,$B$4:$B$503,$B38,$AK$4:$AK$503,$AK38-Settings!$C$23)-1,""))) | AE38: =IF($B38="","",IF($AK38<=Settings!$C$22,"",IFERROR($E38/SUMIFS($E$4:$E$503,$B$4:$B$503,$B38,$AK$4:$AK$503,$AK38-Settings!$C$22)-1,""))) | AF38: =IF($B38="","",IF(N($E38)>0,($F38-$G38)/$E38,"")) -> 0 | AG38: =IF($B38="","",ROUND((MIN(100,100*N($I38)/Settings!$C$27)+MIN(100,100*N($K38)/Settings!$C$28)+MIN(100,100*N($J38)/Settings!$C$29))/3,1)) -> 0 | AH38: =IF($B38="","",IF(SUM(Settings!$C$32:$C$37)=0,"",ROUND((Settings!$C$32*$AO38+Settings!$C$33*$AP38+Settings!$C$34*$AQ38+Settings!$C$35*$AR38+Settings!$C$36*$AS38+Settings!$C$37*$AT38)/SUM(Settings!$C$32:$C$37),1))) -> 65 | AI38: =IF($B38="","",MAX(0,100-IF(N($N38)>0,0,20)-IF(AND(N($L38)=0,N($M38)=0),15,0)-IF(N($J38)>0,0,10)-IF(N($K38)>0,0,10)-IF($Z38<>"",0,15)-IF($AB38<>"",0,10)-IF($R38="ERROR",20,IF($R38="WARNING",10,0)))) -> 55 | AJ38: =IF($AH38="","",IF($AH38<Settings!$C$46,"Extreme Sell Pressure",IF($AH38<Settings!$C$47,"Sell Pressure",IF($AH38<=Settings!$C$48,"Neutral",IF($AH38<=Settings!$C$49,"Buy Pressure","Extreme Buy Pressure"))))) -> Buy Pressure | AK38: =IF($B38="","",COUNTIFS($B$4:$B$503,$B38,$A$4:$A$503,"<="&$A38)) -> 2 | AL38: =IF($A38="","",YEAR($A38)) -> 2026 | AM38: =IF($A38="","",_xlfn.ISOWEEKNUM($A38)) -> 33 | AN38: =IF($A38="","",MONTH($A38)) -> 8 | AO38: =IF($B38="","",IF(AND(N($L38)=0,N($M38)=0),50,IF(N($M38)=0,100,IF(N($L38)=0,0,MEDIAN(0,100,50+50*LN($S38)/LN(Settings!$C$40)))))) -> 100 | AP38: =IF($AA38="",50,MEDIAN(0,100,50+$AA38*100*Settings!$C$41)) -> 50 | AQ38: =IF($H38="",50,MEDIAN(0,100,50+$H38*100*Settings!$C$42)) -> 50 | AR38: =IF(OR($AC38="",$H38=""),50,MEDIAN(0,100,50+SIGN($H38)*50*MEDIAN(0,1,($AC38-1)/Settings!$C$43))) -> 50 | AS38: =IF(OR($V38="",$W38=""),50,MEDIAN(0,100,50+50*($V38-$W38)/Settings!$C$44)) -> 50.015178 | AT38: =IF($AO38="",50,50+(N($AG38)/100)*($AO38-50)) -> 50 | AU38: =IF($B38="","",$B38&"|"&TEXT($A38,"yyyy-mm-dd")) -> JHL|2026-08-11 | AV38: =IF($A38="","",IF(COUNTIFS($A$4:$A38,$A38)=1,1,0)) -> 0
A39: 46245 | B39: KA | C39: 110 | D39: 110 | E39: 110 | H39: =IF($B39="","",IFERROR($E39/$D39-1,"")) -> 0 | I39: 0 | J39: 0 | K39: 0 | L39: 202 | M39: 0 | N39: 624960000000 | O39: DSE Official Daily Market Report | P39: 46265 | Q39: DSE-202608-10to13 | R39: {=IF($B39="","",IFERROR(IF(INDEX('Data Quality'!$U$4:$U$503,ROW()-3)=0,"PENDING",INDEX('Data Quality'!$U$4:$U$503,ROW()-3)),"PENDING"))} -> PASS | S39: =IF($B39="","",IF(N($M39)>0,$L39/$M39,"")) | T39: =IF($B39="","",$L39*$E39) -> 22220 | U39: =IF($B39="","",$M39*$E39) -> 0 | V39: =IF($B39="","",IF(N($N39)>0,$T39/$N39,"")) -> 3.5554275e-08 | W39: =IF($B39="","",IF(N($N39)>0,$U39/$N39,"")) -> 0 | X39: =IF($B39="","",IF(N($J39)>0,$K39/$J39,"")) | Y39: =IF($B39="","",IF(N($J39)>0,$I39/$J39,"")) | Z39: =IF($B39="","",IF($AK39<=Settings!$C$21,"",IFERROR(AVERAGEIFS($S$4:$S$503,$B$4:$B$503,$B39,$AK$4:$AK$503,">="&$AK39-Settings!$C$21,$AK$4:$AK$503,"<="&$AK39-1),""))) | AA39: =IF(OR($S39="",$Z39="",N($Z39)=0),"",$S39/$Z39-1) | AB39: =IF($B39="","",IF($AK39<=Settings!$C$22,"",IFERROR(AVERAGEIFS($K$4:$K$503,$B$4:$B$503,$B39,$AK$4:$AK$503,">="&$AK39-Settings!$C$22,$AK$4:$AK$503,"<="&$AK39-1),""))) | AC39: =IF(OR($AB39="",N($AB39)=0),"",$K39/$AB39) | AD39: =IF($B39="","",IF($AK39<=Settings!$C$23,"",IFERROR($E39/SUMIFS($E$4:$E$503,$B$4:$B$503,$B39,$AK$4:$AK$503,$AK39-Settings!$C$23)-1,""))) | AE39: =IF($B39="","",IF($AK39<=Settings!$C$22,"",IFERROR($E39/SUMIFS($E$4:$E$503,$B$4:$B$503,$B39,$AK$4:$AK$503,$AK39-Settings!$C$22)-1,""))) | AF39: =IF($B39="","",IF(N($E39)>0,($F39-$G39)/$E39,"")) -> 0 | AG39: =IF($B39="","",ROUND((MIN(100,100*N($I39)/Settings!$C$27)+MIN(100,100*N($K39)/Settings!$C$28)+MIN(100,100*N($J39)/Settings!$C$29))/3,1)) -> 0 | AH39: =IF($B39="","",IF(SUM(Settings!$C$32:$C$37)=0,"",ROUND((Settings!$C$32*$AO39+Settings!$C$33*$AP39+Settings!$C$34*$AQ39+Settings!$C$35*$AR39+Settings!$C$36*$AS39+Settings!$C$37*$AT39)/SUM(Settings!$C$32:$C$37),1))) -> 65 | AI39: =IF($B39="","",MAX(0,100-IF(N($N39)>0,0,20)-IF(AND(N($L39)=0,N($M39)=0),15,0)-IF(N($J39)>0,0,10)-IF(N($K39)>0,0,10)-IF($Z39<>"",0,15)-IF($AB39<>"",0,10)-IF($R39="ERROR",20,IF($R39="WARNING",10,0)))) -> 55 | AJ39: =IF($AH39="","",IF($AH39<Settings!$C$46,"Extreme Sell Pressure",IF($AH39<Settings!$C$47,"Sell Pressure",IF($AH39<=Settings!$C$48,"Neutral",IF($AH39<=Settings!$C$49,"Buy Pressure","Extreme Buy Pressure"))))) -> Buy Pressure | AK39: =IF($B39="","",COUNTIFS($B$4:$B$503,$B39,$A$4:$A$503,"<="&$A39)) -> 2 | AL39: =IF($A39="","",YEAR($A39)) -> 2026 | AM39: =IF($A39="","",_xlfn.ISOWEEKNUM($A39)) -> 33 | AN39: =IF($A39="","",MONTH($A39)) -> 8 | AO39: =IF($B39="","",IF(AND(N($L39)=0,N($M39)=0),50,IF(N($M39)=0,100,IF(N($L39)=0,0,MEDIAN(0,100,50+50*LN($S39)/LN(Settings!$C$40)))))) -> 100 | AP39: =IF($AA39="",50,MEDIAN(0,100,50+$AA39*100*Settings!$C$41)) -> 50 | AQ39: =IF($H39="",50,MEDIAN(0,100,50+$H39*100*Settings!$C$42)) -> 50 | AR39: =IF(OR($AC39="",$H39=""),50,MEDIAN(0,100,50+SIGN($H39)*50*MEDIAN(0,1,($AC39-1)/Settings!$C$43))) -> 50 | AS39: =IF(OR($V39="",$W39=""),50,MEDIAN(0,100,50+50*($V39-$W39)/Settings!$C$44)) -> 50.003555 | AT39: =IF($AO39="",50,50+(N($AG39)/100)*($AO39-50)) -> 50 | AU39: =IF($B39="","",$B39&"|"&TEXT($A39,"yyyy-mm-dd")) -> KA|2026-08-11 | AV39: =IF($A39="","",IF(COUNTIFS($A$4:$A39,$A39)=1,1,0)) -> 0
A40: 46245 | B40: KCB | C40: 1900 | D40: 1900 | E40: 1900 | F40: 1930 | G40: 1880 | H40: =IF($B40="","",IFERROR($E40/$D40-1,"")) -> 0 | I40: 35987640 | J40: 43 | K40: 18977 | L40: 12494 | M40: 0 | N40: 5643650000000 | O40: DSE Official Daily Market Report | P40: 46265 | Q40: DSE-202608-10to13 | R40: {=IF($B40="","",IFERROR(IF(INDEX('Data Quality'!$U$4:$U$503,ROW()-3)=0,"PENDING",INDEX('Data Quality'!$U$4:$U$503,ROW()-3)),"PENDING"))} -> PASS | S40: =IF($B40="","",IF(N($M40)>0,$L40/$M40,"")) | T40: =IF($B40="","",$L40*$E40) -> 23738600 | U40: =IF($B40="","",$M40*$E40) -> 0 | V40: =IF($B40="","",IF(N($N40)>0,$T40/$N40,"")) -> 4.2062495e-06 | W40: =IF($B40="","",IF(N($N40)>0,$U40/$N40,"")) -> 0 | X40: =IF($B40="","",IF(N($J40)>0,$K40/$J40,"")) -> 441.32558 | Y40: =IF($B40="","",IF(N($J40)>0,$I40/$J40,"")) -> 836921.86 | Z40: =IF($B40="","",IF($AK40<=Settings!$C$21,"",IFERROR(AVERAGEIFS($S$4:$S$503,$B$4:$B$503,$B40,$AK$4:$AK$503,">="&$AK40-Settings!$C$21,$AK$4:$AK$503,"<="&$AK40-1),""))) | AA40: =IF(OR($S40="",$Z40="",N($Z40)=0),"",$S40/$Z40-1) | AB40: =IF($B40="","",IF($AK40<=Settings!$C$22,"",IFERROR(AVERAGEIFS($K$4:$K$503,$B$4:$B$503,$B40,$AK$4:$AK$503,">="&$AK40-Settings!$C$22,$AK$4:$AK$503,"<="&$AK40-1),""))) | AC40: =IF(OR($AB40="",N($AB40)=0),"",$K40/$AB40) | AD40: =IF($B40="","",IF($AK40<=Settings!$C$23,"",IFERROR($E40/SUMIFS($E$4:$E$503,$B$4:$B$503,$B40,$AK$4:$AK$503,$AK40-Settings!$C$23)-1,""))) | AE40: =IF($B40="","",IF($AK40<=Settings!$C$22,"",IFERROR($E40/SUMIFS($E$4:$E$503,$B$4:$B$503,$B40,$AK$4:$AK$503,$AK40-Settings!$C$22)-1,""))) | AF40: =IF($B40="","",IF(N($E40)>0,($F40-$G40)/$E40,"")) -> 0.026315789 | AG40: =IF($B40="","",ROUND((MIN(100,100*N($I40)/Settings!$C$27)+MIN(100,100*N($K40)/Settings!$C$28)+MIN(100,100*N($J40)/Settings!$C$29))/3,1)) -> 16.8 | AH40: =IF($B40="","",IF(SUM(Settings!$C$32:$C$37)=0,"",ROUND((Settings!$C$32*$AO40+Settings!$C$33*$AP40+Settings!$C$34*$AQ40+Settings!$C$35*$AR40+Settings!$C$36*$AS40+Settings!$C$37*$AT40)/SUM(Settings!$C$32:$C$37),1))) -> 65.9 | AI40: =IF($B40="","",MAX(0,100-IF(N($N40)>0,0,20)-IF(AND(N($L40)=0,N($M40)=0),15,0)-IF(N($J40)>0,0,10)-IF(N($K40)>0,0,10)-IF($Z40<>"",0,15)-IF($AB40<>"",0,10)-IF($R40="ERROR",20,IF($R40="WARNING",10,0)))) -> 75 | AJ40: =IF($AH40="","",IF($AH40<Settings!$C$46,"Extreme Sell Pressure",IF($AH40<Settings!$C$47,"Sell Pressure",IF($AH40<=Settings!$C$48,"Neutral",IF($AH40<=Settings!$C$49,"Buy Pressure","Extreme Buy Pressure"))))) -> Buy Pressure | AK40: =IF($B40="","",COUNTIFS($B$4:$B$503,$B40,$A$4:$A$503,"<="&$A40)) -> 2 | AL40: =IF($A40="","",YEAR($A40)) -> 2026 | AM40: =IF($A40="","",_xlfn.ISOWEEKNUM($A40)) -> 33 | AN40: =IF($A40="","",MONTH($A40)) -> 8 | AO40: =IF($B40="","",IF(AND(N($L40)=0,N($M40)=0),50,IF(N($M40)=0,100,IF(N($L40)=0,0,MEDIAN(0,100,50+50*LN($S40)/LN(Settings!$C$40)))))) -> 100 | AP40: =IF($AA40="",50,MEDIAN(0,100,50+$AA40*100*Settings!$C$41)) -> 50 | AQ40: =IF($H40="",50,MEDIAN(0,100,50+$H40*100*Settings!$C$42)) -> 50 | AR40: =IF(OR($AC40="",$H40=""),50,MEDIAN(0,100,50+SIGN($H40)*50*MEDIAN(0,1,($AC40-1)/Settings!$C$43))) -> 50 | AS40: =IF(OR($V40="",$W40=""),50,MEDIAN(0,100,50+50*($V40-$W40)/Settings!$C$44)) -> 50.420625 | AT40: =IF($AO40="",50,50+(N($AG40)/100)*($AO40-50)) -> 58.4 | AU40: =IF($B40="","",$B40&"|"&TEXT($A40,"yyyy-mm-dd")) -> KCB|2026-08-11 | AV40: =IF($A40="","",IF(COUNTIFS($A$4:$A40,$A40)=1,1,0)) -> 0
A41: 46245 | B41: MBP | C41: 1660 | D41: 1660 | E41: 1680 | F41: 1700 | G41: 1650 | H41: =IF($B41="","",IFERROR($E41/$D41-1,"")) -> 0.012048193 | I41: 4178510 | J41: 20 | K41: 2480 | L41: 15113 | M41: 21901 | N41: 50380000000 | O41: DSE Official Daily Market Report | P41: 46265 | Q41: DSE-202608-10to13 | R41: {=IF($B41="","",IFERROR(IF(INDEX('Data Quality'!$U$4:$U$503,ROW()-3)=0,"PENDING",INDEX('Data Quality'!$U$4:$U$503,ROW()-3)),"PENDING"))} -> PASS | S41: =IF($B41="","",IF(N($M41)>0,$L41/$M41,"")) -> 0.69005981 | T41: =IF($B41="","",$L41*$E41) -> 25389840 | U41: =IF($B41="","",$M41*$E41) -> 36793680 | V41: =IF($B41="","",IF(N($N41)>0,$T41/$N41,"")) -> 0.00050396665 | W41: =IF($B41="","",IF(N($N41)>0,$U41/$N41,"")) -> 0.00073032314 | X41: =IF($B41="","",IF(N($J41)>0,$K41/$J41,"")) -> 124 | Y41: =IF($B41="","",IF(N($J41)>0,$I41/$J41,"")) -> 208925.5 | Z41: =IF($B41="","",IF($AK41<=Settings!$C$21,"",IFERROR(AVERAGEIFS($S$4:$S$503,$B$4:$B$503,$B41,$AK$4:$AK$503,">="&$AK41-Settings!$C$21,$AK$4:$AK$503,"<="&$AK41-1),""))) | AA41: =IF(OR($S41="",$Z41="",N($Z41)=0),"",$S41/$Z41-1) | AB41: =IF($B41="","",IF($AK41<=Settings!$C$22,"",IFERROR(AVERAGEIFS($K$4:$K$503,$B$4:$B$503,$B41,$AK$4:$AK$503,">="&$AK41-Settings!$C$22,$AK$4:$AK$503,"<="&$AK41-1),""))) | AC41: =IF(OR($AB41="",N($AB41)=0),"",$K41/$AB41) | AD41: =IF($B41="","",IF($AK41<=Settings!$C$23,"",IFERROR($E41/SUMIFS($E$4:$E$503,$B$4:$B$503,$B41,$AK$4:$AK$503,$AK41-Settings!$C$23)-1,""))) | AE41: =IF($B41="","",IF($AK41<=Settings!$C$22,"",IFERROR($E41/SUMIFS($E$4:$E$503,$B$4:$B$503,$B41,$AK$4:$AK$503,$AK41-Settings!$C$22)-1,""))) | AF41: =IF($B41="","",IF(N($E41)>0,($F41-$G41)/$E41,"")) -> 0.029761905 | AG41: =IF($B41="","",ROUND((MIN(100,100*N($I41)/Settings!$C$27)+MIN(100,100*N($K41)/Settings!$C$28)+MIN(100,100*N($J41)/Settings!$C$29))/3,1)) -> 7 | AH41: =IF($B41="","",IF(SUM(Settings!$C$32:$C$37)=0,"",ROUND((Settings!$C$32*$AO41+Settings!$C$33*$AP41+Settings!$C$34*$AQ41+Settings!$C$35*$AR41+Settings!$C$36*$AS41+Settings!$C$37*$AT41)/SUM(Settings!$C$32:$C$37),1))) -> 45.4 | AI41: =IF($B41="","",MAX(0,100-IF(N($N41)>0,0,20)-IF(AND(N($L41)=0,N($M41)=0),15,0)-IF(N($J41)>0,0,10)-IF(N($K41)>0,0,10)-IF($Z41<>"",0,15)-IF($AB41<>"",0,10)-IF($R41="ERROR",20,IF($R41="WARNING",10,0)))) -> 75 | AJ41: =IF($AH41="","",IF($AH41<Settings!$C$46,"Extreme Sell Pressure",IF($AH41<Settings!$C$47,"Sell Pressure",IF($AH41<=Settings!$C$48,"Neutral",IF($AH41<=Settings!$C$49,"Buy Pressure","Extreme Buy Pressure"))))) -> Neutral | AK41: =IF($B41="","",COUNTIFS($B$4:$B$503,$B41,$A$4:$A$503,"<="&$A41)) -> 2 | AL41: =IF($A41="","",YEAR($A41)) -> 2026 | AM41: =IF($A41="","",_xlfn.ISOWEEKNUM($A41)) -> 33 | AN41: =IF($A41="","",MONTH($A41)) -> 8 | AO41: =IF($B41="","",IF(AND(N($L41)=0,N($M41)=0),50,IF(N($M41)=0,100,IF(N($L41)=0,0,MEDIAN(0,100,50+50*LN($S41)/LN(Settings!$C$40)))))) -> 36.619833 | AP41: =IF($AA41="",50,MEDIAN(0,100,50+$AA41*100*Settings!$C$41)) -> 50 | AQ41: =IF($H41="",50,MEDIAN(0,100,50+$H41*100*Settings!$C$42)) -> 62.048193 | AR41: =IF(OR($AC41="",$H41=""),50,MEDIAN(0,100,50+SIGN($H41)*50*MEDIAN(0,1,($AC41-1)/Settings!$C$43))) -> 50 | AS41: =IF(OR($V41="",$W41=""),50,MEDIAN(0,100,50+50*($V41-$W41)/Settings!$C$44)) -> 27.364351 | AT41: =IF($AO41="",50,50+(N($AG41)/100)*($AO41-50)) -> 49.063388 | AU41: =IF($B41="","",$B41&"|"&TEXT($A41,"yyyy-mm-dd")) -> MBP|2026-08-11 | AV41: =IF($A41="","",IF(COUNTIFS($A$4:$A41,$A41)=1,1,0)) -> 0
A42: 46245 | B42: MCB | C42: 525 | D42: 525 | E42: 475 | F42: 515 | G42: 450 | H42: =IF($B42="","",IFERROR($E42/$D42-1,"")) -> -0.095238095 | I42: 110353875 | J42: 595 | K42: 232164 | L42: 2793 | M42: 241297 | N42: 117470000000 | O42: DSE Official Daily Market Report | P42: 46265 | Q42: DSE-202608-10to13 | R42: {=IF($B42="","",IFERROR(IF(INDEX('Data Quality'!$U$4:$U$503,ROW()-3)=0,"PENDING",INDEX('Data Quality'!$U$4:$U$503,ROW()-3)),"PENDING"))} -> PASS | S42: =IF($B42="","",IF(N($M42)>0,$L42/$M42,"")) -> 0.011574947 | T42: =IF($B42="","",$L42*$E42) -> 1326675 | U42: =IF($B42="","",$M42*$E42) -> 114616075 | V42: =IF($B42="","",IF(N($N42)>0,$T42/$N42,"")) -> 1.1293735e-05 | W42: =IF($B42="","",IF(N($N42)>0,$U42/$N42,"")) -> 0.00097570507 | X42: =IF($B42="","",IF(N($J42)>0,$K42/$J42,"")) -> 390.1916 | Y42: =IF($B42="","",IF(N($J42)>0,$I42/$J42,"")) -> 185468.7 | Z42: =IF($B42="","",IF($AK42<=Settings!$C$21,"",IFERROR(AVERAGEIFS($S$4:$S$503,$B$4:$B$503,$B42,$AK$4:$AK$503,">="&$AK42-Settings!$C$21,$AK$4:$AK$503,"<="&$AK42-1),""))) | AA42: =IF(OR($S42="",$Z42="",N($Z42)=0),"",$S42/$Z42-1) | AB42: =IF($B42="","",IF($AK42<=Settings!$C$22,"",IFERROR(AVERAGEIFS($K$4:$K$503,$B$4:$B$503,$B42,$AK$4:$AK$503,">="&$AK42-Settings!$C$22,$AK$4:$AK$503,"<="&$AK42-1),""))) | AC42: =IF(OR($AB42="",N($AB42)=0),"",$K42/$AB42) | AD42: =IF($B42="","",IF($AK42<=Settings!$C$23,"",IFERROR($E42/SUMIFS($E$4:$E$503,$B$4:$B$503,$B42,$AK$4:$AK$503,$AK42-Settings!$C$23)-1,""))) | AE42: =IF($B42="","",IF($AK42<=Settings!$C$22,"",IFERROR($E42/SUMIFS($E$4:$E$503,$B$4:$B$503,$B42,$AK$4:$AK$503,$AK42-Settings!$C$22)-1,""))) | AF42: =IF($B42="","",IF(N($E42)>0,($F42-$G42)/$E42,"")) -> 0.13684211 | AG42: =IF($B42="","",ROUND((MIN(100,100*N($I42)/Settings!$C$27)+MIN(100,100*N($K42)/Settings!$C$28)+MIN(100,100*N($J42)/Settings!$C$29))/3,1)) -> 52.5 | AH42: =IF($B42="","",IF(SUM(Settings!$C$32:$C$37)=0,"",ROUND((Settings!$C$32*$AO42+Settings!$C$33*$AP42+Settings!$C$34*$AQ42+Settings!$C$35*$AR42+Settings!$C$36*$AS42+Settings!$C$37*$AT42)/SUM(Settings!$C$32:$C$37),1))) -> 19.9 | AI42: =IF($B42="","",MAX(0,100-IF(N($N42)>0,0,20)-IF(AND(N($L42)=0,N($M42)=0),15,0)-IF(N($J42)>0,0,10)-IF(N($K42)>0,0,10)-IF($Z42<>"",0,15)-IF($AB42<>"",0,10)-IF($R42="ERROR",20,IF($R42="WARNING",10,0)))) -> 75 | AJ42: =IF($AH42="","",IF($AH42<Settings!$C$46,"Extreme Sell Pressure",IF($AH42<Settings!$C$47,"Sell Pressure",IF($AH42<=Settings!$C$48,"Neutral",IF($AH42<=Settings!$C$49,"Buy Pressure","Extreme Buy Pressure"))))) -> Extreme Sell Pressure | AK42: =IF($B42="","",COUNTIFS($B$4:$B$503,$B42,$A$4:$A$503,"<="&$A42)) -> 2 | AL42: =IF($A42="","",YEAR($A42)) -> 2026 | AM42: =IF($A42="","",_xlfn.ISOWEEKNUM($A42)) -> 33 | AN42: =IF($A42="","",MONTH($A42)) -> 8 | AO42: =IF($B42="","",IF(AND(N($L42)=0,N($M42)=0),50,IF(N($M42)=0,100,IF(N($L42)=0,0,MEDIAN(0,100,50+50*LN($S42)/LN(Settings!$C$40)))))) -> 0 | AP42: =IF($AA42="",50,MEDIAN(0,100,50+$AA42*100*Settings!$C$41)) -> 50 | AQ42: =IF($H42="",50,MEDIAN(0,100,50+$H42*100*Settings!$C$42)) -> 0 | AR42: =IF(OR($AC42="",$H42=""),50,MEDIAN(0,100,50+SIGN($H42)*50*MEDIAN(0,1,($AC42-1)/Settings!$C$43))) -> 50 | AS42: =IF(OR($V42="",$W42=""),50,MEDIAN(0,100,50+50*($V42-$W42)/Settings!$C$44)) -> 0 | AT42: =IF($AO42="",50,50+(N($AG42)/100)*($AO42-50)) -> 23.75 | AU42: =IF($B42="","",$B42&"|"&TEXT($A42,"yyyy-mm-dd")) -> MCB|2026-08-11 | AV42: =IF($A42="","",IF(COUNTIFS($A$4:$A42,$A42)=1,1,0)) -> 0
A43: 46245 | B43: MKCB | C43: 3740 | D43: 3740 | E43: 3870 | F43: 3880 | G43: 3740 | H43: =IF($B43="","",IFERROR($E43/$D43-1,"")) -> 0.034759358 | I43: 4966000 | J43: 9 | K43: 1285 | L43: 1378 | M43: 2154 | N43: 91160000000 | O43: DSE Official Daily Market Report | P43: 46265 | Q43: DSE-202608-10to13 | R43: {=IF($B43="","",IFERROR(IF(INDEX('Data Quality'!$U$4:$U$503,ROW()-3)=0,"PENDING",INDEX('Data Quality'!$U$4:$U$503,ROW()-3)),"PENDING"))} -> PASS | S43: =IF($B43="","",IF(N($M43)>0,$L43/$M43,"")) -> 0.63974002 | T43: =IF($B43="","",$L43*$E43) -> 5332860 | U43: =IF($B43="","",$M43*$E43) -> 8335980 | V43: =IF($B43="","",IF(N($N43)>0,$T43/$N43,"")) -> 5.85e-05 | W43: =IF($B43="","",IF(N($N43)>0,$U43/$N43,"")) -> 9.1443396e-05 | X43: =IF($B43="","",IF(N($J43)>0,$K43/$J43,"")) -> 142.77778 | Y43: =IF($B43="","",IF(N($J43)>0,$I43/$J43,"")) -> 551777.78 | Z43: =IF($B43="","",IF($AK43<=Settings!$C$21,"",IFERROR(AVERAGEIFS($S$4:$S$503,$B$4:$B$503,$B43,$AK$4:$AK$503,">="&$AK43-Settings!$C$21,$AK$4:$AK$503,"<="&$AK43-1),""))) | AA43: =IF(OR($S43="",$Z43="",N($Z43)=0),"",$S43/$Z43-1) | AB43: =IF($B43="","",IF($AK43<=Settings!$C$22,"",IFERROR(AVERAGEIFS($K$4:$K$503,$B$4:$B$503,$B43,$AK$4:$AK$503,">="&$AK43-Settings!$C$22,$AK$4:$AK$503,"<="&$AK43-1),""))) | AC43: =IF(OR($AB43="",N($AB43)=0),"",$K43/$AB43) | AD43: =IF($B43="","",IF($AK43<=Settings!$C$23,"",IFERROR($E43/SUMIFS($E$4:$E$503,$B$4:$B$503,$B43,$AK$4:$AK$503,$AK43-Settings!$C$23)-1,""))) | AE43: =IF($B43="","",IF($AK43<=Settings!$C$22,"",IFERROR($E43/SUMIFS($E$4:$E$503,$B$4:$B$503,$B43,$AK$4:$AK$503,$AK43-Settings!$C$22)-1,""))) | AF43: =IF($B43="","",IF(N($E43)>0,($F43-$G43)/$E43,"")) -> 0.036175711 | AG43: =IF($B43="","",ROUND((MIN(100,100*N($I43)/Settings!$C$27)+MIN(100,100*N($K43)/Settings!$C$28)+MIN(100,100*N($J43)/Settings!$C$29))/3,1)) -> 3.3 | AH43: =IF($B43="","",IF(SUM(Settings!$C$32:$C$37)=0,"",ROUND((Settings!$C$32*$AO43+Settings!$C$33*$AP43+Settings!$C$34*$AQ43+Settings!$C$35*$AR43+Settings!$C$36*$AS43+Settings!$C$37*$AT43)/SUM(Settings!$C$32:$C$37),1))) -> 50 | AI43: =IF($B43="","",MAX(0,100-IF(N($N43)>0,0,20)-IF(AND(N($L43)=0,N($M43)=0),15,0)-IF(N($J43)>0,0,10)-IF(N($K43)>0,0,10)-IF($Z43<>"",0,15)-IF($AB43<>"",0,10)-IF($R43="ERROR",20,IF($R43="WARNING",10,0)))) -> 75 | AJ43: =IF($AH43="","",IF($AH43<Settings!$C$46,"Extreme Sell Pressure",IF($AH43<Settings!$C$47,"Sell Pressure",IF($AH43<=Settings!$C$48,"Neutral",IF($AH43<=Settings!$C$49,"Buy Pressure","Extreme Buy Pressure"))))) -> Neutral | AK43: =IF($B43="","",COUNTIFS($B$4:$B$503,$B43,$A$4:$A$503,"<="&$A43)) -> 2 | AL43: =IF($A43="","",YEAR($A43)) -> 2026 | AM43: =IF($A43="","",_xlfn.ISOWEEKNUM($A43)) -> 33 | AN43: =IF($A43="","",MONTH($A43)) -> 8 | AO43: =IF($B43="","",IF(AND(N($L43)=0,N($M43)=0),50,IF(N($M43)=0,100,IF(N($L43)=0,0,MEDIAN(0,100,50+50*LN($S43)/LN(Settings!$C$40)))))) -> 33.888941 | AP43: =IF($AA43="",50,MEDIAN(0,100,50+$AA43*100*Settings!$C$41)) -> 50 | AQ43: =IF($H43="",50,MEDIAN(0,100,50+$H43*100*Settings!$C$42)) -> 84.759358 | AR43: =IF(OR($AC43="",$H43=""),50,MEDIAN(0,100,50+SIGN($H43)*50*MEDIAN(0,1,($AC43-1)/Settings!$C$43))) -> 50 | AS43: =IF(OR($V43="",$W43=""),50,MEDIAN(0,100,50+50*($V43-$W43)/Settings!$C$44)) -> 46.70566 | AT43: =IF($AO43="",50,50+(N($AG43)/100)*($AO43-50)) -> 49.468335 | AU43: =IF($B43="","",$B43&"|"&TEXT($A43,"yyyy-mm-dd")) -> MKCB|2026-08-11 | AV43: =IF($A43="","",IF(COUNTIFS($A$4:$A43,$A43)=1,1,0)) -> 0
A44: 46245 | B44: MUCOBA | C44: 455 | D44: 455 | E44: 465 | F44: 465 | G44: 465 | H44: =IF($B44="","",IFERROR($E44/$D44-1,"")) -> 0.021978022 | I44: 1685625 | J44: 29 | K44: 3625 | L44: 2724 | M44: 500 | N44: 15190000000 | O44: DSE Official Daily Market Report | P44: 46265 | Q44: DSE-202608-10to13 | R44: {=IF($B44="","",IFERROR(IF(INDEX('Data Quality'!$U$4:$U$503,ROW()-3)=0,"PENDING",INDEX('Data Quality'!$U$4:$U$503,ROW()-3)),"PENDING"))} -> PASS | S44: =IF($B44="","",IF(N($M44)>0,$L44/$M44,"")) -> 5.448 | T44: =IF($B44="","",$L44*$E44) -> 1266660 | U44: =IF($B44="","",$M44*$E44) -> 232500 | V44: =IF($B44="","",IF(N($N44)>0,$T44/$N44,"")) -> 8.3387755e-05 | W44: =IF($B44="","",IF(N($N44)>0,$U44/$N44,"")) -> 1.5306122e-05 | X44: =IF($B44="","",IF(N($J44)>0,$K44/$J44,"")) -> 125 | Y44: =IF($B44="","",IF(N($J44)>0,$I44/$J44,"")) -> 58125 | Z44: =IF($B44="","",IF($AK44<=Settings!$C$21,"",IFERROR(AVERAGEIFS($S$4:$S$503,$B$4:$B$503,$B44,$AK$4:$AK$503,">="&$AK44-Settings!$C$21,$AK$4:$AK$503,"<="&$AK44-1),""))) | AA44: =IF(OR($S44="",$Z44="",N($Z44)=0),"",$S44/$Z44-1) | AB44: =IF($B44="","",IF($AK44<=Settings!$C$22,"",IFERROR(AVERAGEIFS($K$4:$K$503,$B$4:$B$503,$B44,$AK$4:$AK$503,">="&$AK44-Settings!$C$22,$AK$4:$AK$503,"<="&$AK44-1),""))) | AC44: =IF(OR($AB44="",N($AB44)=0),"",$K44/$AB44) | AD44: =IF($B44="","",IF($AK44<=Settings!$C$23,"",IFERROR($E44/SUMIFS($E$4:$E$503,$B$4:$B$503,$B44,$AK$4:$AK$503,$AK44-Settings!$C$23)-1,""))) | AE44: =IF($B44="","",IF($AK44<=Settings!$C$22,"",IFERROR($E44/SUMIFS($E$4:$E$503,$B$4:$B$503,$B44,$AK$4:$AK$503,$AK44-Settings!$C$22)-1,""))) | AF44: =IF($B44="","",IF(N($E44)>0,($F44-$G44)/$E44,"")) -> 0 | AG44: =IF($B44="","",ROUND((MIN(100,100*N($I44)/Settings!$C$27)+MIN(100,100*N($K44)/Settings!$C$28)+MIN(100,100*N($J44)/Settings!$C$29))/3,1)) -> 10 | AH44: =IF($B44="","",IF(SUM(Settings!$C$32:$C$37)=0,"",ROUND((Settings!$C$32*$AO44+Settings!$C$33*$AP44+Settings!$C$34*$AQ44+Settings!$C$35*$AR44+Settings!$C$36*$AS44+Settings!$C$37*$AT44)/SUM(Settings!$C$32:$C$37),1))) -> 69.5 | AI44: =IF($B44="","",MAX(0,100-IF(N($N44)>0,0,20)-IF(AND(N($L44)=0,N($M44)=0),15,0)-IF(N($J44)>0,0,10)-IF(N($K44)>0,0,10)-IF($Z44<>"",0,15)-IF($AB44<>"",0,10)-IF($R44="ERROR",20,IF($R44="WARNING",10,0)))) -> 75 | AJ44: =IF($AH44="","",IF($AH44<Settings!$C$46,"Extreme Sell Pressure",IF($AH44<Settings!$C$47,"Sell Pressure",IF($AH44<=Settings!$C$48,"Neutral",IF($AH44<=Settings!$C$49,"Buy Pressure","Extreme Buy Pressure"))))) -> Buy Pressure | AK44: =IF($B44="","",COUNTIFS($B$4:$B$503,$B44,$A$4:$A$503,"<="&$A44)) -> 2 | AL44: =IF($A44="","",YEAR($A44)) -> 2026 | AM44: =IF($A44="","",_xlfn.ISOWEEKNUM($A44)) -> 33 | AN44: =IF($A44="","",MONTH($A44)) -> 8 | AO44: =IF($B44="","",IF(AND(N($L44)=0,N($M44)=0),50,IF(N($M44)=0,100,IF(N($L44)=0,0,MEDIAN(0,100,50+50*LN($S44)/LN(Settings!$C$40)))))) -> 100 | AP44: =IF($AA44="",50,MEDIAN(0,100,50+$AA44*100*Settings!$C$41)) -> 50 | AQ44: =IF($H44="",50,MEDIAN(0,100,50+$H44*100*Settings!$C$42)) -> 71.978022 | AR44: =IF(OR($AC44="",$H44=""),50,MEDIAN(0,100,50+SIGN($H44)*50*MEDIAN(0,1,($AC44-1)/Settings!$C$43))) -> 50 | AS44: =IF(OR($V44="",$W44=""),50,MEDIAN(0,100,50+50*($V44-$W44)/Settings!$C$44)) -> 56.808163 | AT44: =IF($AO44="",50,50+(N($AG44)/100)*($AO44-50)) -> 55 | AU44: =IF($B44="","",$B44&"|"&TEXT($A44,"yyyy-mm-dd")) -> MUCOBA|2026-08-11 | AV44: =IF($A44="","",IF(COUNTIFS($A$4:$A44,$A44)=1,1,0)) -> 0
A45: 46245 | B45: NICO | C45: 3590 | D45: 3590 | E45: 3610 | F45: 3700 | G45: 3600 | H45: =IF($B45="","",IFERROR($E45/$D45-1,"")) -> 0.0055710306 | I45: 27442940 | J45: 49 | K45: 7589 | L45: 7249 | M45: 9631 | N45: 222540000000 | O45: DSE Official Daily Market Report | P45: 46265 | Q45: DSE-202608-10to13 | R45: {=IF($B45="","",IFERROR(IF(INDEX('Data Quality'!$U$4:$U$503,ROW()-3)=0,"PENDING",INDEX('Data Quality'!$U$4:$U$503,ROW()-3)),"PENDING"))} -> PASS | S45: =IF($B45="","",IF(N($M45)>0,$L45/$M45,"")) -> 0.75267366 | T45: =IF($B45="","",$L45*$E45) -> 26168890 | U45: =IF($B45="","",$M45*$E45) -> 34767910 | V45: =IF($B45="","",IF(N($N45)>0,$T45/$N45,"")) -> 0.00011759185 | W45: =IF($B45="","",IF(N($N45)>0,$U45/$N45,"")) -> 0.00015623218 | X45: =IF($B45="","",IF(N($J45)>0,$K45/$J45,"")) -> 154.87755 | Y45: =IF($B45="","",IF(N($J45)>0,$I45/$J45,"")) -> 560060 | Z45: =IF($B45="","",IF($AK45<=Settings!$C$21,"",IFERROR(AVERAGEIFS($S$4:$S$503,$B$4:$B$503,$B45,$AK$4:$AK$503,">="&$AK45-Settings!$C$21,$AK$4:$AK$503,"<="&$AK45-1),""))) | AA45: =IF(OR($S45="",$Z45="",N($Z45)=0),"",$S45/$Z45-1) | AB45: =IF($B45="","",IF($AK45<=Settings!$C$22,"",IFERROR(AVERAGEIFS($K$4:$K$503,$B$4:$B$503,$B45,$AK$4:$AK$503,">="&$AK45-Settings!$C$22,$AK$4:$AK$503,"<="&$AK45-1),""))) | AC45: =IF(OR($AB45="",N($AB45)=0),"",$K45/$AB45) | AD45: =IF($B45="","",IF($AK45<=Settings!$C$23,"",IFERROR($E45/SUMIFS($E$4:$E$503,$B$4:$B$503,$B45,$AK$4:$AK$503,$AK45-Settings!$C$23)-1,""))) | AE45: =IF($B45="","",IF($AK45<=Settings!$C$22,"",IFERROR($E45/SUMIFS($E$4:$E$503,$B$4:$B$503,$B45,$AK$4:$AK$503,$AK45-Settings!$C$22)-1,""))) | AF45: =IF($B45="","",IF(N($E45)>0,($F45-$G45)/$E45,"")) -> 0.027700831 | AG45: =IF($B45="","",ROUND((MIN(100,100*N($I45)/Settings!$C$27)+MIN(100,100*N($K45)/Settings!$C$28)+MIN(100,100*N($J45)/Settings!$C$29))/3,1)) -> 17.8 | AH45: =IF($B45="","",IF(SUM(Settings!$C$32:$C$37)=0,"",ROUND((Settings!$C$32*$AO45+Settings!$C$33*$AP45+Settings!$C$34*$AQ45+Settings!$C$35*$AR45+Settings!$C$36*$AS45+Settings!$C$37*$AT45)/SUM(Settings!$C$32:$C$37),1))) -> 47.2 | AI45: =IF($B45="","",MAX(0,100-IF(N($N45)>0,0,20)-IF(AND(N($L45)=0,N($M45)=0),15,0)-IF(N($J45)>0,0,10)-IF(N($K45)>0,0,10)-IF($Z45<>"",0,15)-IF($AB45<>"",0,10)-IF($R45="ERROR",20,IF($R45="WARNING",10,0)))) -> 75 | AJ45: =IF($AH45="","",IF($AH45<Settings!$C$46,"Extreme Sell Pressure",IF($AH45<Settings!$C$47,"Sell Pressure",IF($AH45<=Settings!$C$48,"Neutral",IF($AH45<=Settings!$C$49,"Buy Pressure","Extreme Buy Pressure"))))) -> Neutral | AK45: =IF($B45="","",COUNTIFS($B$4:$B$503,$B45,$A$4:$A$503,"<="&$A45)) -> 2 | AL45: =IF($A45="","",YEAR($A45)) -> 2026 | AM45: =IF($A45="","",_xlfn.ISOWEEKNUM($A45)) -> 33 | AN45: =IF($A45="","",MONTH($A45)) -> 8 | AO45: =IF($B45="","",IF(AND(N($L45)=0,N($M45)=0),50,IF(N($M45)=0,100,IF(N($L45)=0,0,MEDIAN(0,100,50+50*LN($S45)/LN(Settings!$C$40)))))) -> 39.75241 | AP45: =IF($AA45="",50,MEDIAN(0,100,50+$AA45*100*Settings!$C$41)) -> 50 | AQ45: =IF($H45="",50,MEDIAN(0,100,50+$H45*100*Settings!$C$42)) -> 55.571031 | AR45: =IF(OR($AC45="",$H45=""),50,MEDIAN(0,100,50+SIGN($H45)*50*MEDIAN(0,1,($AC45-1)/Settings!$C$43))) -> 50 | AS45: =IF(OR($V45="",$W45=""),50,MEDIAN(0,100,50+50*($V45-$W45)/Settings!$C$44)) -> 46.135967 | AT45: =IF($AO45="",50,50+(N($AG45)/100)*($AO45-50)) -> 48.175929 | AU45: =IF($B45="","",$B45&"|"&TEXT($A45,"yyyy-mm-dd")) -> NICO|2026-08-11 | AV45: =IF($A45="","",IF(COUNTIFS($A$4:$A45,$A45)=1,1,0)) -> 0
A46: 46245 | B46: NMB | C46: 17600 | D46: 17600 | E46: 17600 | F46: 17600 | G46: 17570 | H46: =IF($B46="","",IFERROR($E46/$D46-1,"")) -> 0 | I46: 2026478370 | J46: 486 | K46: 115239 | L46: 11414 | M46: 58384 | N46: 8800000000000 | O46: DSE Official Daily Market Report | P46: 46265 | Q46: DSE-202608-10to13 | R46: {=IF($B46="","",IFERROR(IF(INDEX('Data Quality'!$U$4:$U$503,ROW()-3)=0,"PENDING",INDEX('Data Quality'!$U$4:$U$503,ROW()-3)),"PENDING"))} -> PASS | S46: =IF($B46="","",IF(N($M46)>0,$L46/$M46,"")) -> 0.19549877 | T46: =IF($B46="","",$L46*$E46) -> 200886400 | U46: =IF($B46="","",$M46*$E46) -> 1027558400 | V46: =IF($B46="","",IF(N($N46)>0,$T46/$N46,"")) -> 2.2828e-05 | W46: =IF($B46="","",IF(N($N46)>0,$U46/$N46,"")) -> 0.000116768 | X46: =IF($B46="","",IF(N($J46)>0,$K46/$J46,"")) -> 237.11728 | Y46: =IF($B46="","",IF(N($J46)>0,$I46/$J46,"")) -> 4169708.6 | Z46: =IF($B46="","",IF($AK46<=Settings!$C$21,"",IFERROR(AVERAGEIFS($S$4:$S$503,$B$4:$B$503,$B46,$AK$4:$AK$503,">="&$AK46-Settings!$C$21,$AK$4:$AK$503,"<="&$AK46-1),""))) | AA46: =IF(OR($S46="",$Z46="",N($Z46)=0),"",$S46/$Z46-1) | AB46: =IF($B46="","",IF($AK46<=Settings!$C$22,"",IFERROR(AVERAGEIFS($K$4:$K$503,$B$4:$B$503,$B46,$AK$4:$AK$503,">="&$AK46-Settings!$C$22,$AK$4:$AK$503,"<="&$AK46-1),""))) | AC46: =IF(OR($AB46="",N($AB46)=0),"",$K46/$AB46) | AD46: =IF($B46="","",IF($AK46<=Settings!$C$23,"",IFERROR($E46/SUMIFS($E$4:$E$503,$B$4:$B$503,$B46,$AK$4:$AK$503,$AK46-Settings!$C$23)-1,""))) | AE46: =IF($B46="","",IF($AK46<=Settings!$C$22,"",IFERROR($E46/SUMIFS($E$4:$E$503,$B$4:$B$503,$B46,$AK$4:$AK$503,$AK46-Settings!$C$22)-1,""))) | AF46: =IF($B46="","",IF(N($E46)>0,($F46-$G46)/$E46,"")) -> 0.0017045455 | AG46: =IF($B46="","",ROUND((MIN(100,100*N($I46)/Settings!$C$27)+MIN(100,100*N($K46)/Settings!$C$28)+MIN(100,100*N($J46)/Settings!$C$29))/3,1)) -> 74.3 | AH46: =IF($B46="","",IF(SUM(Settings!$C$32:$C$37)=0,"",ROUND((Settings!$C$32*$AO46+Settings!$C$33*$AP46+Settings!$C$34*$AQ46+Settings!$C$35*$AR46+Settings!$C$36*$AS46+Settings!$C$37*$AT46)/SUM(Settings!$C$32:$C$37),1))) -> 30.3 | AI46: =IF($B46="","",MAX(0,100-IF(N($N46)>0,0,20)-IF(AND(N($L46)=0,N($M46)=0),15,0)-IF(N($J46)>0,0,10)-IF(N($K46)>0,0,10)-IF($Z46<>"",0,15)-IF($AB46<>"",0,10)-IF($R46="ERROR",20,IF($R46="WARNING",10,0)))) -> 75 | AJ46: =IF($AH46="","",IF($AH46<Settings!$C$46,"Extreme Sell Pressure",IF($AH46<Settings!$C$47,"Sell Pressure",IF($AH46<=Settings!$C$48,"Neutral",IF($AH46<=Settings!$C$49,"Buy Pressure","Extreme Buy Pressure"))))) -> Sell Pressure | AK46: =IF($B46="","",COUNTIFS($B$4:$B$503,$B46,$A$4:$A$503,"<="&$A46)) -> 2 | AL46: =IF($A46="","",YEAR($A46)) -> 2026 | AM46: =IF($A46="","",_xlfn.ISOWEEKNUM($A46)) -> 33 | AN46: =IF($A46="","",MONTH($A46)) -> 8 | AO46: =IF($B46="","",IF(AND(N($L46)=0,N($M46)=0),50,IF(N($M46)=0,100,IF(N($L46)=0,0,MEDIAN(0,100,50+50*LN($S46)/LN(Settings!$C$40)))))) -> 0 | AP46: =IF($AA46="",50,MEDIAN(0,100,50+$AA46*100*Settings!$C$41)) -> 50 | AQ46: =IF($H46="",50,MEDIAN(0,100,50+$H46*100*Settings!$C$42)) -> 50 | AR46: =IF(OR($AC46="",$H46=""),50,MEDIAN(0,100,50+SIGN($H46)*50*MEDIAN(0,1,($AC46-1)/Settings!$C$43))) -> 50 | AS46: =IF(OR($V46="",$W46=""),50,MEDIAN(0,100,50+50*($V46-$W46)/Settings!$C$44)) -> 40.606 | AT46: =IF($AO46="",50,50+(N($AG46)/100)*($AO46-50)) -> 12.85 | AU46: =IF($B46="","",$B46&"|"&TEXT($A46,"yyyy-mm-dd")) -> NMB|2026-08-11 | AV46: =IF($A46="","",IF(COUNTIFS($A$4:$A46,$A46)=1,1,0)) -> 0
A47: 46245 | B47: NMG | C47: 265 | D47: 265 | E47: 270 | H47: =IF($B47="","",IFERROR($E47/$D47-1,"")) -> 0.018867925 | I47: 0 | J47: 0 | K47: 0 | L47: 343 | M47: 0 | N47: 50910000000 | O47: DSE Official Daily Market Report | P47: 46265 | Q47: DSE-202608-10to13 | R47: {=IF($B47="","",IFERROR(IF(INDEX('Data Quality'!$U$4:$U$503,ROW()-3)=0,"PENDING",INDEX('Data Quality'!$U$4:$U$503,ROW()-3)),"PENDING"))} -> PASS | S47: =IF($B47="","",IF(N($M47)>0,$L47/$M47,"")) | T47: =IF($B47="","",$L47*$E47) -> 92610 | U47: =IF($B47="","",$M47*$E47) -> 0 | V47: =IF($B47="","",IF(N($N47)>0,$T47/$N47,"")) -> 1.8190925e-06 | W47: =IF($B47="","",IF(N($N47)>0,$U47/$N47,"")) -> 0 | X47: =IF($B47="","",IF(N($J47)>0,$K47/$J47,"")) | Y47: =IF($B47="","",IF(N($J47)>0,$I47/$J47,"")) | Z47: =IF($B47="","",IF($AK47<=Settings!$C$21,"",IFERROR(AVERAGEIFS($S$4:$S$503,$B$4:$B$503,$B47,$AK$4:$AK$503,">="&$AK47-Settings!$C$21,$AK$4:$AK$503,"<="&$AK47-1),""))) | AA47: =IF(OR($S47="",$Z47="",N($Z47)=0),"",$S47/$Z47-1) | AB47: =IF($B47="","",IF($AK47<=Settings!$C$22,"",IFERROR(AVERAGEIFS($K$4:$K$503,$B$4:$B$503,$B47,$AK$4:$AK$503,">="&$AK47-Settings!$C$22,$AK$4:$AK$503,"<="&$AK47-1),""))) | AC47: =IF(OR($AB47="",N($AB47)=0),"",$K47/$AB47) | AD47: =IF($B47="","",IF($AK47<=Settings!$C$23,"",IFERROR($E47/SUMIFS($E$4:$E$503,$B$4:$B$503,$B47,$AK$4:$AK$503,$AK47-Settings!$C$23)-1,""))) | AE47: =IF($B47="","",IF($AK47<=Settings!$C$22,"",IFERROR($E47/SUMIFS($E$4:$E$503,$B$4:$B$503,$B47,$AK$4:$AK$503,$AK47-Settings!$C$22)-1,""))) | AF47: =IF($B47="","",IF(N($E47)>0,($F47-$G47)/$E47,"")) -> 0 | AG47: =IF($B47="","",ROUND((MIN(100,100*N($I47)/Settings!$C$27)+MIN(100,100*N($K47)/Settings!$C$28)+MIN(100,100*N($J47)/Settings!$C$29))/3,1)) -> 0 | AH47: =IF($B47="","",IF(SUM(Settings!$C$32:$C$37)=0,"",ROUND((Settings!$C$32*$AO47+Settings!$C$33*$AP47+Settings!$C$34*$AQ47+Settings!$C$35*$AR47+Settings!$C$36*$AS47+Settings!$C$37*$AT47)/SUM(Settings!$C$32:$C$37),1))) -> 67.8 | AI47: =IF($B47="","",MAX(0,100-IF(N($N47)>0,0,20)-IF(AND(N($L47)=0,N($M47)=0),15,0)-IF(N($J47)>0,0,10)-IF(N($K47)>0,0,10)-IF($Z47<>"",0,15)-IF($AB47<>"",0,10)-IF($R47="ERROR",20,IF($R47="WARNING",10,0)))) -> 55 | AJ47: =IF($AH47="","",IF($AH47<Settings!$C$46,"Extreme Sell Pressure",IF($AH47<Settings!$C$47,"Sell Pressure",IF($AH47<=Settings!$C$48,"Neutral",IF($AH47<=Settings!$C$49,"Buy Pressure","Extreme Buy Pressure"))))) -> Buy Pressure | AK47: =IF($B47="","",COUNTIFS($B$4:$B$503,$B47,$A$4:$A$503,"<="&$A47)) -> 2 | AL47: =IF($A47="","",YEAR($A47)) -> 2026 | AM47: =IF($A47="","",_xlfn.ISOWEEKNUM($A47)) -> 33 | AN47: =IF($A47="","",MONTH($A47)) -> 8 | AO47: =IF($B47="","",IF(AND(N($L47)=0,N($M47)=0),50,IF(N($M47)=0,100,IF(N($L47)=0,0,MEDIAN(0,100,50+50*LN($S47)/LN(Settings!$C$40)))))) -> 100 | AP47: =IF($AA47="",50,MEDIAN(0,100,50+$AA47*100*Settings!$C$41)) -> 50 | AQ47: =IF($H47="",50,MEDIAN(0,100,50+$H47*100*Settings!$C$42)) -> 68.867925 | AR47: =IF(OR($AC47="",$H47=""),50,MEDIAN(0,100,50+SIGN($H47)*50*MEDIAN(0,1,($AC47-1)/Settings!$C$43))) -> 50 | AS47: =IF(OR($V47="",$W47=""),50,MEDIAN(0,100,50+50*($V47-$W47)/Settings!$C$44)) -> 50.181909 | AT47: =IF($AO47="",50,50+(N($AG47)/100)*($AO47-50)) -> 50 | AU47: =IF($B47="","",$B47&"|"&TEXT($A47,"yyyy-mm-dd")) -> NMG|2026-08-11 | AV47: =IF($A47="","",IF(COUNTIFS($A$4:$A47,$A47)=1,1,0)) -> 0
A48: 46245 | B48: PAL | C48: 310 | D48: 310 | E48: 305 | F48: 310 | G48: 300 | H48: =IF($B48="","",IFERROR($E48/$D48-1,"")) -> -0.016129032 | I48: 1749860 | J48: 40 | K48: 5738 | L48: 3560 | M48: 9532 | N48: 48940000000 | O48: DSE Official Daily Market Report | P48: 46265 | Q48: DSE-202608-10to13 | R48: {=IF($B48="","",IFERROR(IF(INDEX('Data Quality'!$U$4:$U$503,ROW()-3)=0,"PENDING",INDEX('Data Quality'!$U$4:$U$503,ROW()-3)),"PENDING"))} -> PASS | S48: =IF($B48="","",IF(N($M48)>0,$L48/$M48,"")) -> 0.37347881 | T48: =IF($B48="","",$L48*$E48) -> 1085800 | U48: =IF($B48="","",$M48*$E48) -> 2907260 | V48: =IF($B48="","",IF(N($N48)>0,$T48/$N48,"")) -> 2.2186351e-05 | W48: =IF($B48="","",IF(N($N48)>0,$U48/$N48,"")) -> 5.9404577e-05 | X48: =IF($B48="","",IF(N($J48)>0,$K48/$J48,"")) -> 143.45 | Y48: =IF($B48="","",IF(N($J48)>0,$I48/$J48,"")) -> 43746.5 | Z48: =IF($B48="","",IF($AK48<=Settings!$C$21,"",IFERROR(AVERAGEIFS($S$4:$S$503,$B$4:$B$503,$B48,$AK$4:$AK$503,">="&$AK48-Settings!$C$21,$AK$4:$AK$503,"<="&$AK48-1),""))) | AA48: =IF(OR($S48="",$Z48="",N($Z48)=0),"",$S48/$Z48-1) | AB48: =IF($B48="","",IF($AK48<=Settings!$C$22,"",IFERROR(AVERAGEIFS($K$4:$K$503,$B$4:$B$503,$B48,$AK$4:$AK$503,">="&$AK48-Settings!$C$22,$AK$4:$AK$503,"<="&$AK48-1),""))) | AC48: =IF(OR($AB48="",N($AB48)=0),"",$K48/$AB48) | AD48: =IF($B48="","",IF($AK48<=Settings!$C$23,"",IFERROR($E48/SUMIFS($E$4:$E$503,$B$4:$B$503,$B48,$AK$4:$AK$503,$AK48-Settings!$C$23)-1,""))) | AE48: =IF($B48="","",IF($AK48<=Settings!$C$22,"",IFERROR($E48/SUMIFS($E$4:$E$503,$B$4:$B$503,$B48,$AK$4:$AK$503,$AK48-Settings!$C$22)-1,""))) | AF48: =IF($B48="","",IF(N($E48)>0,($F48-$G48)/$E48,"")) -> 0.032786885 | AG48: =IF($B48="","",ROUND((MIN(100,100*N($I48)/Settings!$C$27)+MIN(100,100*N($K48)/Settings!$C$28)+MIN(100,100*N($J48)/Settings!$C$29))/3,1)) -> 13.8 | AH48: =IF($B48="","",IF(SUM(Settings!$C$32:$C$37)=0,"",ROUND((Settings!$C$32*$AO48+Settings!$C$33*$AP48+Settings!$C$34*$AQ48+Settings!$C$35*$AR48+Settings!$C$36*$AS48+Settings!$C$37*$AT48)/SUM(Settings!$C$32:$C$37),1))) -> 36.1 | AI48: =IF($B48="","",MAX(0,100-IF(N($N48)>0,0,20)-IF(AND(N($L48)=0,N($M48)=0),15,0)-IF(N($J48)>0,0,10)-IF(N($K48)>0,0,10)-IF($Z48<>"",0,15)-IF($AB48<>"",0,10)-IF($R48="ERROR",20,IF($R48="WARNING",10,0)))) -> 75 | AJ48: =IF($AH48="","",IF($AH48<Settings!$C$46,"Extreme Sell Pressure",IF($AH48<Settings!$C$47,"Sell Pressure",IF($AH48<=Settings!$C$48,"Neutral",IF($AH48<=Settings!$C$49,"Buy Pressure","Extreme Buy Pressure"))))) -> Sell Pressure | AK48: =IF($B48="","",COUNTIFS($B$4:$B$503,$B48,$A$4:$A$503,"<="&$A48)) -> 2 | AL48: =IF($A48="","",YEAR($A48)) -> 2026 | AM48: =IF($A48="","",_xlfn.ISOWEEKNUM($A48)) -> 33 | AN48: =IF($A48="","",MONTH($A48)) -> 8 | AO48: =IF($B48="","",IF(AND(N($L48)=0,N($M48)=0),50,IF(N($M48)=0,100,IF(N($L48)=0,0,MEDIAN(0,100,50+50*LN($S48)/LN(Settings!$C$40)))))) -> 14.477457 | AP48: =IF($AA48="",50,MEDIAN(0,100,50+$AA48*100*Settings!$C$41)) -> 50 | AQ48: =IF($H48="",50,MEDIAN(0,100,50+$H48*100*Settings!$C$42)) -> 33.870968 | AR48: =IF(OR($AC48="",$H48=""),50,MEDIAN(0,100,50+SIGN($H48)*50*MEDIAN(0,1,($AC48-1)/Settings!$C$43))) -> 50 | AS48: =IF(OR($V48="",$W48=""),50,MEDIAN(0,100,50+50*($V48-$W48)/Settings!$C$44)) -> 46.278177 | AT48: =IF($AO48="",50,50+(N($AG48)/100)*($AO48-50)) -> 45.097889 | AU48: =IF($B48="","",$B48&"|"&TEXT($A48,"yyyy-mm-dd")) -> PAL|2026-08-11 | AV48: =IF($A48="","",IF(COUNTIFS($A$4:$A48,$A48)=1,1,0)) -> 0
A49: 46245 | B49: SWALA | C49: 450 | D49: 450 | E49: 450 | H49: =IF($B49="","",IFERROR($E49/$D49-1,"")) -> 0 | I49: 0 | J49: 0 | K49: 0 | L49: 0 | M49: 0 | N49: 47790000000 | O49: DSE Official Daily Market Report | P49: 46265 | Q49: DSE-202608-10to13 | R49: {=IF($B49="","",IFERROR(IF(INDEX('Data Quality'!$U$4:$U$503,ROW()-3)=0,"PENDING",INDEX('Data Quality'!$U$4:$U$503,ROW()-3)),"PENDING"))} -> WARNING | S49: =IF($B49="","",IF(N($M49)>0,$L49/$M49,"")) | T49: =IF($B49="","",$L49*$E49) -> 0 | U49: =IF($B49="","",$M49*$E49) -> 0 | V49: =IF($B49="","",IF(N($N49)>0,$T49/$N49,"")) -> 0 | W49: =IF($B49="","",IF(N($N49)>0,$U49/$N49,"")) -> 0 | X49: =IF($B49="","",IF(N($J49)>0,$K49/$J49,"")) | Y49: =IF($B49="","",IF(N($J49)>0,$I49/$J49,"")) | Z49: =IF($B49="","",IF($AK49<=Settings!$C$21,"",IFERROR(AVERAGEIFS($S$4:$S$503,$B$4:$B$503,$B49,$AK$4:$AK$503,">="&$AK49-Settings!$C$21,$AK$4:$AK$503,"<="&$AK49-1),""))) | AA49: =IF(OR($S49="",$Z49="",N($Z49)=0),"",$S49/$Z49-1) | AB49: =IF($B49="","",IF($AK49<=Settings!$C$22,"",IFERROR(AVERAGEIFS($K$4:$K$503,$B$4:$B$503,$B49,$AK$4:$AK$503,">="&$AK49-Settings!$C$22,$AK$4:$AK$503,"<="&$AK49-1),""))) | AC49: =IF(OR($AB49="",N($AB49)=0),"",$K49/$AB49) | AD49: =IF($B49="","",IF($AK49<=Settings!$C$23,"",IFERROR($E49/SUMIFS($E$4:$E$503,$B$4:$B$503,$B49,$AK$4:$AK$503,$AK49-Settings!$C$23)-1,""))) | AE49: =IF($B49="","",IF($AK49<=Settings!$C$22,"",IFERROR($E49/SUMIFS($E$4:$E$503,$B$4:$B$503,$B49,$AK$4:$AK$503,$AK49-Settings!$C$22)-1,""))) | AF49: =IF($B49="","",IF(N($E49)>0,($F49-$G49)/$E49,"")) -> 0 | AG49: =IF($B49="","",ROUND((MIN(100,100*N($I49)/Settings!$C$27)+MIN(100,100*N($K49)/Settings!$C$28)+MIN(100,100*N($J49)/Settings!$C$29))/3,1)) -> 0 | AH49: =IF($B49="","",IF(SUM(Settings!$C$32:$C$37)=0,"",ROUND((Settings!$C$32*$AO49+Settings!$C$33*$AP49+Settings!$C$34*$AQ49+Settings!$C$35*$AR49+Settings!$C$36*$AS49+Settings!$C$37*$AT49)/SUM(Settings!$C$32:$C$37),1))) -> 50 | AI49: =IF($B49="","",MAX(0,100-IF(N($N49)>0,0,20)-IF(AND(N($L49)=0,N($M49)=0),15,0)-IF(N($J49)>0,0,10)-IF(N($K49)>0,0,10)-IF($Z49<>"",0,15)-IF($AB49<>"",0,10)-IF($R49="ERROR",20,IF($R49="WARNING",10,0)))) -> 30 | AJ49: =IF($AH49="","",IF($AH49<Settings!$C$46,"Extreme Sell Pressure",IF($AH49<Settings!$C$47,"Sell Pressure",IF($AH49<=Settings!$C$48,"Neutral",IF($AH49<=Settings!$C$49,"Buy Pressure","Extreme Buy Pressure"))))) -> Neutral | AK49: =IF($B49="","",COUNTIFS($B$4:$B$503,$B49,$A$4:$A$503,"<="&$A49)) -> 2 | AL49: =IF($A49="","",YEAR($A49)) -> 2026 | AM49: =IF($A49="","",_xlfn.ISOWEEKNUM($A49)) -> 33 | AN49: =IF($A49="","",MONTH($A49)) -> 8 | AO49: =IF($B49="","",IF(AND(N($L49)=0,N($M49)=0),50,IF(N($M49)=0,100,IF(N($L49)=0,0,MEDIAN(0,100,50+50*LN($S49)/LN(Settings!$C$40)))))) -> 50 | AP49: =IF($AA49="",50,MEDIAN(0,100,50+$AA49*100*Settings!$C$41)) -> 50 | AQ49: =IF($H49="",50,MEDIAN(0,100,50+$H49*100*Settings!$C$42)) -> 50 | AR49: =IF(OR($AC49="",$H49=""),50,MEDIAN(0,100,50+SIGN($H49)*50*MEDIAN(0,1,($AC49-1)/Settings!$C$43))) -> 50 | AS49: =IF(OR($V49="",$W49=""),50,MEDIAN(0,100,50+50*($V49-$W49)/Settings!$C$44)) -> 50 | AT49: =IF($AO49="",50,50+(N($AG49)/100)*($AO49-50)) -> 50 | AU49: =IF($B49="","",$B49&"|"&TEXT($A49,"yyyy-mm-dd")) -> SWALA|2026-08-11 | AV49: =IF($A49="","",IF(COUNTIFS($A$4:$A49,$A49)=1,1,0)) -> 0
A50: 46245 | B50: SWIS | C50: 2620 | D50: 2620 | E50: 2340 | F50: 2680 | G50: 2300 | H50: =IF($B50="","",IFERROR($E50/$D50-1,"")) -> -0.10687023 | I50: 34455560 | J50: 55 | K50: 14675 | L50: 2605 | M50: 9957 | N50: 84240000000 | O50: DSE Official Daily Market Report | P50: 46265 | Q50: DSE-202608-10to13 | R50: {=IF($B50="","",IFERROR(IF(INDEX('Data Quality'!$U$4:$U$503,ROW()-3)=0,"PENDING",INDEX('Data Quality'!$U$4:$U$503,ROW()-3)),"PENDING"))} -> PASS | S50: =IF($B50="","",IF(N($M50)>0,$L50/$M50,"")) -> 0.26162499 | T50: =IF($B50="","",$L50*$E50) -> 6095700 | U50: =IF($B50="","",$M50*$E50) -> 23299380 | V50: =IF($B50="","",IF(N($N50)>0,$T50/$N50,"")) -> 7.2361111e-05 | W50: =IF($B50="","",IF(N($N50)>0,$U50/$N50,"")) -> 0.00027658333 | X50: =IF($B50="","",IF(N($J50)>0,$K50/$J50,"")) -> 266.81818 | Y50: =IF($B50="","",IF(N($J50)>0,$I50/$J50,"")) -> 626464.73 | Z50: =IF($B50="","",IF($AK50<=Settings!$C$21,"",IFERROR(AVERAGEIFS($S$4:$S$503,$B$4:$B$503,$B50,$AK$4:$AK$503,">="&$AK50-Settings!$C$21,$AK$4:$AK$503,"<="&$AK50-1),""))) | AA50: =IF(OR($S50="",$Z50="",N($Z50)=0),"",$S50/$Z50-1) | AB50: =IF($B50="","",IF($AK50<=Settings!$C$22,"",IFERROR(AVERAGEIFS($K$4:$K$503,$B$4:$B$503,$B50,$AK$4:$AK$503,">="&$AK50-Settings!$C$22,$AK$4:$AK$503,"<="&$AK50-1),""))) | AC50: =IF(OR($AB50="",N($AB50)=0),"",$K50/$AB50) | AD50: =IF($B50="","",IF($AK50<=Settings!$C$23,"",IFERROR($E50/SUMIFS($E$4:$E$503,$B$4:$B$503,$B50,$AK$4:$AK$503,$AK50-Settings!$C$23)-1,""))) | AE50: =IF($B50="","",IF($AK50<=Settings!$C$22,"",IFERROR($E50/SUMIFS($E$4:$E$503,$B$4:$B$503,$B50,$AK$4:$AK$503,$AK50-Settings!$C$22)-1,""))) | AF50: =IF($B50="","",IF(N($E50)>0,($F50-$G50)/$E50,"")) -> 0.16239316 | AG50: =IF($B50="","",ROUND((MIN(100,100*N($I50)/Settings!$C$27)+MIN(100,100*N($K50)/Settings!$C$28)+MIN(100,100*N($J50)/Settings!$C$29))/3,1)) -> 20.5 | AH50: =IF($B50="","",IF(SUM(Settings!$C$32:$C$37)=0,"",ROUND((Settings!$C$32*$AO50+Settings!$C$33*$AP50+Settings!$C$34*$AQ50+Settings!$C$35*$AR50+Settings!$C$36*$AS50+Settings!$C$37*$AT50)/SUM(Settings!$C$32:$C$37),1))) -> 25 | AI50: =IF($B50="","",MAX(0,100-IF(N($N50)>0,0,20)-IF(AND(N($L50)=0,N($M50)=0),15,0)-IF(N($J50)>0,0,10)-IF(N($K50)>0,0,10)-IF($Z50<>"",0,15)-IF($AB50<>"",0,10)-IF($R50="ERROR",20,IF($R50="WARNING",10,0)))) -> 75 | AJ50: =IF($AH50="","",IF($AH50<Settings!$C$46,"Extreme Sell Pressure",IF($AH50<Settings!$C$47,"Sell Pressure",IF($AH50<=Settings!$C$48,"Neutral",IF($AH50<=Settings!$C$49,"Buy Pressure","Extreme Buy Pressure"))))) -> Sell Pressure | AK50: =IF($B50="","",COUNTIFS($B$4:$B$503,$B50,$A$4:$A$503,"<="&$A50)) -> 2 | AL50: =IF($A50="","",YEAR($A50)) -> 2026 | AM50: =IF($A50="","",_xlfn.ISOWEEKNUM($A50)) -> 33 | AN50: =IF($A50="","",MONTH($A50)) -> 8 | AO50: =IF($B50="","",IF(AND(N($L50)=0,N($M50)=0),50,IF(N($M50)=0,100,IF(N($L50)=0,0,MEDIAN(0,100,50+50*LN($S50)/LN(Settings!$C$40)))))) -> 1.6393061 | AP50: =IF($AA50="",50,MEDIAN(0,100,50+$AA50*100*Settings!$C$41)) -> 50 | AQ50: =IF($H50="",50,MEDIAN(0,100,50+$H50*100*Settings!$C$42)) -> 0 | AR50: =IF(OR($AC50="",$H50=""),50,MEDIAN(0,100,50+SIGN($H50)*50*MEDIAN(0,1,($AC50-1)/Settings!$C$43))) -> 50 | AS50: =IF(OR($V50="",$W50=""),50,MEDIAN(0,100,50+50*($V50-$W50)/Settings!$C$44)) -> 29.577778 | AT50: =IF($AO50="",50,50+(N($AG50)/100)*($AO50-50)) -> 40.086058 | AU50: =IF($B50="","",$B50&"|"&TEXT($A50,"yyyy-mm-dd")) -> SWIS|2026-08-11 | AV50: =IF($A50="","",IF(COUNTIFS($A$4:$A50,$A50)=1,1,0)) -> 0
A51: 46245 | B51: TBL | C51: 9950 | D51: 9950 | E51: 9970 | F51: 10000 | G51: 9950 | H51: =IF($B51="","",IFERROR($E51/$D51-1,"")) -> 0.0020100503 | I51: 49704950 | J51: 33 | K51: 4983 | L51: 41 | M51: 764 | N51: 2941710000000 | O51: DSE Official Daily Market Report | P51: 46265 | Q51: DSE-202608-10to13 | R51: {=IF($B51="","",IFERROR(IF(INDEX('Data Quality'!$U$4:$U$503,ROW()-3)=0,"PENDING",INDEX('Data Quality'!$U$4:$U$503,ROW()-3)),"PENDING"))} -> PASS | S51: =IF($B51="","",IF(N($M51)>0,$L51/$M51,"")) -> 0.053664921 | T51: =IF($B51="","",$L51*$E51) -> 408770 | U51: =IF($B51="","",$M51*$E51) -> 7617080 | V51: =IF($B51="","",IF(N($N51)>0,$T51/$N51,"")) -> 1.3895659e-07 | W51: =IF($B51="","",IF(N($N51)>0,$U51/$N51,"")) -> 2.5893375e-06 | X51: =IF($B51="","",IF(N($J51)>0,$K51/$J51,"")) -> 151 | Y51: =IF($B51="","",IF(N($J51)>0,$I51/$J51,"")) -> 1506210.6 | Z51: =IF($B51="","",IF($AK51<=Settings!$C$21,"",IFERROR(AVERAGEIFS($S$4:$S$503,$B$4:$B$503,$B51,$AK$4:$AK$503,">="&$AK51-Settings!$C$21,$AK$4:$AK$503,"<="&$AK51-1),""))) | AA51: =IF(OR($S51="",$Z51="",N($Z51)=0),"",$S51/$Z51-1) | AB51: =IF($B51="","",IF($AK51<=Settings!$C$22,"",IFERROR(AVERAGEIFS($K$4:$K$503,$B$4:$B$503,$B51,$AK$4:$AK$503,">="&$AK51-Settings!$C$22,$AK$4:$AK$503,"<="&$AK51-1),""))) | AC51: =IF(OR($AB51="",N($AB51)=0),"",$K51/$AB51) | AD51: =IF($B51="","",IF($AK51<=Settings!$C$23,"",IFERROR($E51/SUMIFS($E$4:$E$503,$B$4:$B$503,$B51,$AK$4:$AK$503,$AK51-Settings!$C$23)-1,""))) | AE51: =IF($B51="","",IF($AK51<=Settings!$C$22,"",IFERROR($E51/SUMIFS($E$4:$E$503,$B$4:$B$503,$B51,$AK$4:$AK$503,$AK51-Settings!$C$22)-1,""))) | AF51: =IF($B51="","",IF(N($E51)>0,($F51-$G51)/$E51,"")) -> 0.0050150451 | AG51: =IF($B51="","",ROUND((MIN(100,100*N($I51)/Settings!$C$27)+MIN(100,100*N($K51)/Settings!$C$28)+MIN(100,100*N($J51)/Settings!$C$29))/3,1)) -> 13 | AH51: =IF($B51="","",IF(SUM(Settings!$C$32:$C$37)=0,"",ROUND((Settings!$C$32*$AO51+Settings!$C$33*$AP51+Settings!$C$34*$AQ51+Settings!$C$35*$AR51+Settings!$C$36*$AS51+Settings!$C$37*$AT51)/SUM(Settings!$C$32:$C$37),1))) -> 34.6 | AI51: =IF($B51="","",MAX(0,100-IF(N($N51)>0,0,20)-IF(AND(N($L51)=0,N($M51)=0),15,0)-IF(N($J51)>0,0,10)-IF(N($K51)>0,0,10)-IF($Z51<>"",0,15)-IF($AB51<>"",0,10)-IF($R51="ERROR",20,IF($R51="WARNING",10,0)))) -> 75 | AJ51: =IF($AH51="","",IF($AH51<Settings!$C$46,"Extreme Sell Pressure",IF($AH51<Settings!$C$47,"Sell Pressure",IF($AH51<=Settings!$C$48,"Neutral",IF($AH51<=Settings!$C$49,"Buy Pressure","Extreme Buy Pressure"))))) -> Sell Pressure | AK51: =IF($B51="","",COUNTIFS($B$4:$B$503,$B51,$A$4:$A$503,"<="&$A51)) -> 2 | AL51: =IF($A51="","",YEAR($A51)) -> 2026 | AM51: =IF($A51="","",_xlfn.ISOWEEKNUM($A51)) -> 33 | AN51: =IF($A51="","",MONTH($A51)) -> 8 | AO51: =IF($B51="","",IF(AND(N($L51)=0,N($M51)=0),50,IF(N($M51)=0,100,IF(N($L51)=0,0,MEDIAN(0,100,50+50*LN($S51)/LN(Settings!$C$40)))))) -> 0 | AP51: =IF($AA51="",50,MEDIAN(0,100,50+$AA51*100*Settings!$C$41)) -> 50 | AQ51: =IF($H51="",50,MEDIAN(0,100,50+$H51*100*Settings!$C$42)) -> 52.01005 | AR51: =IF(OR($AC51="",$H51=""),50,MEDIAN(0,100,50+SIGN($H51)*50*MEDIAN(0,1,($AC51-1)/Settings!$C$43))) -> 50 | AS51: =IF(OR($V51="",$W51=""),50,MEDIAN(0,100,50+50*($V51-$W51)/Settings!$C$44)) -> 49.754962 | AT51: =IF($AO51="",50,50+(N($AG51)/100)*($AO51-50)) -> 43.5 | AU51: =IF($B51="","",$B51&"|"&TEXT($A51,"yyyy-mm-dd")) -> TBL|2026-08-11 | AV51: =IF($A51="","",IF(COUNTIFS($A$4:$A51,$A51)=1,1,0)) -> 0
A52: 46245 | B52: TCC | C52: 12500 | D52: 12500 | E52: 12500 | F52: 12500 | G52: 12500 | H52: =IF($B52="","",IFERROR($E52/$D52-1,"")) -> 0 | I52: 8300000 | J52: 18 | K52: 664 | L52: 10123 | M52: 0 | N52: 1250000000000 | O52: DSE Official Daily Market Report | P52: 46265 | Q52: DSE-202608-10to13 | R52: {=IF($B52="","",IFERROR(IF(INDEX('Data Quality'!$U$4:$U$503,ROW()-3)=0,"PENDING",INDEX('Data Quality'!$U$4:$U$503,ROW()-3)),"PENDING"))} -> PASS | S52: =IF($B52="","",IF(N($M52)>0,$L52/$M52,"")) | T52: =IF($B52="","",$L52*$E52) -> 126537500 | U52: =IF($B52="","",$M52*$E52) -> 0 | V52: =IF($B52="","",IF(N($N52)>0,$T52/$N52,"")) -> 0.00010123 | W52: =IF($B52="","",IF(N($N52)>0,$U52/$N52,"")) -> 0 | X52: =IF($B52="","",IF(N($J52)>0,$K52/$J52,"")) -> 36.888889 | Y52: =IF($B52="","",IF(N($J52)>0,$I52/$J52,"")) -> 461111.11 | Z52: =IF($B52="","",IF($AK52<=Settings!$C$21,"",IFERROR(AVERAGEIFS($S$4:$S$503,$B$4:$B$503,$B52,$AK$4:$AK$503,">="&$AK52-Settings!$C$21,$AK$4:$AK$503,"<="&$AK52-1),""))) | AA52: =IF(OR($S52="",$Z52="",N($Z52)=0),"",$S52/$Z52-1) | AB52: =IF($B52="","",IF($AK52<=Settings!$C$22,"",IFERROR(AVERAGEIFS($K$4:$K$503,$B$4:$B$503,$B52,$AK$4:$AK$503,">="&$AK52-Settings!$C$22,$AK$4:$AK$503,"<="&$AK52-1),""))) | AC52: =IF(OR($AB52="",N($AB52)=0),"",$K52/$AB52) | AD52: =IF($B52="","",IF($AK52<=Settings!$C$23,"",IFERROR($E52/SUMIFS($E$4:$E$503,$B$4:$B$503,$B52,$AK$4:$AK$503,$AK52-Settings!$C$23)-1,""))) | AE52: =IF($B52="","",IF($AK52<=Settings!$C$22,"",IFERROR($E52/SUMIFS($E$4:$E$503,$B$4:$B$503,$B52,$AK$4:$AK$503,$AK52-Settings!$C$22)-1,""))) | AF52: =IF($B52="","",IF(N($E52)>0,($F52-$G52)/$E52,"")) -> 0 | AG52: =IF($B52="","",ROUND((MIN(100,100*N($I52)/Settings!$C$27)+MIN(100,100*N($K52)/Settings!$C$28)+MIN(100,100*N($J52)/Settings!$C$29))/3,1)) -> 6.3 | AH52: =IF($B52="","",IF(SUM(Settings!$C$32:$C$37)=0,"",ROUND((Settings!$C$32*$AO52+Settings!$C$33*$AP52+Settings!$C$34*$AQ52+Settings!$C$35*$AR52+Settings!$C$36*$AS52+Settings!$C$37*$AT52)/SUM(Settings!$C$32:$C$37),1))) -> 66.3 | AI52: =IF($B52="","",MAX(0,100-IF(N($N52)>0,0,20)-IF(AND(N($L52)=0,N($M52)=0),15,0)-IF(N($J52)>0,0,10)-IF(N($K52)>0,0,10)-IF($Z52<>"",0,15)-IF($AB52<>"",0,10)-IF($R52="ERROR",20,IF($R52="WARNING",10,0)))) -> 75 | AJ52: =IF($AH52="","",IF($AH52<Settings!$C$46,"Extreme Sell Pressure",IF($AH52<Settings!$C$47,"Sell Pressure",IF($AH52<=Settings!$C$48,"Neutral",IF($AH52<=Settings!$C$49,"Buy Pressure","Extreme Buy Pressure"))))) -> Buy Pressure | AK52: =IF($B52="","",COUNTIFS($B$4:$B$503,$B52,$A$4:$A$503,"<="&$A52)) -> 2 | AL52: =IF($A52="","",YEAR($A52)) -> 2026 | AM52: =IF($A52="","",_xlfn.ISOWEEKNUM($A52)) -> 33 | AN52: =IF($A52="","",MONTH($A52)) -> 8 | AO52: =IF($B52="","",IF(AND(N($L52)=0,N($M52)=0),50,IF(N($M52)=0,100,IF(N($L52)=0,0,MEDIAN(0,100,50+50*LN($S52)/LN(Settings!$C$40)))))) -> 100 | AP52: =IF($AA52="",50,MEDIAN(0,100,50+$AA52*100*Settings!$C$41)) -> 50 | AQ52: =IF($H52="",50,MEDIAN(0,100,50+$H52*100*Settings!$C$42)) -> 50 | AR52: =IF(OR($AC52="",$H52=""),50,MEDIAN(0,100,50+SIGN($H52)*50*MEDIAN(0,1,($AC52-1)/Settings!$C$43))) -> 50 | AS52: =IF(OR($V52="",$W52=""),50,MEDIAN(0,100,50+50*($V52-$W52)/Settings!$C$44)) -> 60.123 | AT52: =IF($AO52="",50,50+(N($AG52)/100)*($AO52-50)) -> 53.15 | AU52: =IF($B52="","",$B52&"|"&TEXT($A52,"yyyy-mm-dd")) -> TCC|2026-08-11 | AV52: =IF($A52="","",IF(COUNTIFS($A$4:$A52,$A52)=1,1,0)) -> 0
